Workbook

Sheet Gantt Cutover
A1: Gantt de cutover — Portland Colombia (Go-Live 09-11-2026)
A2: Base: plan de cutover acordado (Cutover_Colombia_GoLive_09Nov.pptx) y buenas prácticas SAP Activate. Edite solo las columnas Estado y Comentarios (amarillas).
A3: ="Fecha de consulta: "&TEXT(Hoy!$C$4,"dd-mm-yyyy")&" · Equipo de proyecto en Bogotá del 02 al 12-11 · Feriados de Colombia sombreados" -> Fecha de consulta: 28-10-2026 · Equipo de proyecto en Bogotá del 02 al 12-11 · Feriados de Colombia sombreados | P3: Octubre | AB3: Noviembre
P4: M | Q4: M | R4: J | S4: V | T4: S | U4: D | V4: L | W4: M | X4: M | Y4: J | Z4: V | AA4: S | AB4: D | AC4: L | AD4: M | AE4: M | AF4: J | AG4: V | AH4: S | AI4: D | AJ4: L | AK4: M | AL4: M | AM4: J | AN4: V | AO4: S | AP4: D | AQ4: L | AR4: M | AS4: M | AT4: J | AU4: V
A5: ID | B5: Fase | C5: Actividad / hito | D5: Tipo | E5: Detalle / entregable | F5: Frente | G5: Responsable | H5: Participantes | I5: Modalidad | J5: Inicio | K5: Fin | L5: Días | M5: Estado | N5: Alerta | O5: Comentarios | P5: 46315 | Q5: 46316 | R5: 46317 | S5: 46318 | T5: 46319 | U5: 46320 | V5: 46321 | W5: 46322 | X5: 46323 | Y5: 46324 | Z5: 46325 | AA5: 46326 | AB5: 46327 | AC5: 46328 | AD5: 46329 | AE5: 46330 | AF5: 46331 | AG5: 46332 | AH5: 46333 | AI5: 46334 | AJ5: 46335 | AK5: 46336 | AL5: 46337 | AM5: 46338 | AN5: 46339 | AO5: 46340 | AP5: 46341 | AQ5: 46342 | AR5: 46343 | AS5: 46344 | AT5: 46345 | AU5: 46346 | AW5: es_act | AX5: hoy | AY5: n_hoy | AZ5: venc | BA5: n_venc
A6: 0 | B6: 0. Equipo de proyecto en Colombia | C6: Equipo de proyecto en Colombia | D6: Fase | J6: =MIN(J7:J11) -> 46328 | K6: =MAX(K7:K11) -> 46346 | L6: =K6-J6+1 -> 19 | M6: =IF(COUNTIF(M7:M11,"Finalizado")=ROWS(M7:M11),"Finalizado",IF(OR(COUNTIF(M7:M11,"Demorado")>0,COUNTIF(N7:N11,"Vencida")>0),"Demorado",IF(COUNTIF(M7:M11,"En curso")+COUNTIF(M7:M11,"Finalizado")>0,"En curso","No iniciado"))) -> No iniciado | N6: =IF(COUNTIF(N7:N11,"Vencida")>0,COUNTIF(N7:N11,"Vencida")&" vencida(s)","") | O6: =COUNTIF(M7:M11,"Finalizado")&" de "&ROWS(M7:M11)&" finalizadas" -> 0 de 5 finalizadas | AW6: 0
A7: C01 | B7: 0. Equipo de proyecto en Colombia | C7: Equipo de proyecto en Bogotá | D7: Actividad | E7: Germán Faundes, Daniela Correa, Oscar Sella y Gabriel Salinas: preparación, carga, Go-Live y primera semana de Hypercare. | F7: PMO | G7: Gerente de Proyecto | H7: Gerente de Contabilidad Regional; TI Portland FICO; PMO Portland | I7: Presencial | J7: 46328 | K7: 46338 | L7: =K7-J7+1 -> 11 | M7: No iniciado | N7: =IF(M7="Finalizado","",IF(K7<Hoy!$C$4,"Vencida",IF(AND(J7<=Hoy!$C$4,M7="No iniciado"),"Sin iniciar",""))) | P7: =IF(AND($D7="Hito",P$5=$J7),"◆","") | Q7: =IF(AND($D7="Hito",Q$5=$J7),"◆","") | R7: =IF(AND($D7="Hito",R$5=$J7),"◆","") | S7: =IF(AND($D7="Hito",S$5=$J7),"◆","") | T7: =IF(AND($D7="Hito",T$5=$J7),"◆","") | U7: =IF(AND($D7="Hito",U$5=$J7),"◆","") | V7: =IF(AND($D7="Hito",V$5=$J7),"◆","") | W7: =IF(AND($D7="Hito",W$5=$J7),"◆","") | ... AU7: =IF(AND($D7="Hito",AU$5=$J7),"◆","") | AW7: 1 | AX7: =IF(AND(J7<=Hoy!$C$4,K7>=Hoy!$C$4),1,0) -> 0 | AY7: =IF(AX7=1,SUM($AX$6:AX7),"") | AZ7: =IF(N7="Vencida",1,0) -> 0 | BA7: =IF(AZ7=1,SUM($AZ$6:AZ7),"")
A8: C02 | B8: 0. Equipo de proyecto en Colombia | C8: Visita del Gerente General | D8: Actividad | E8: Daniel Yung: acompañamiento de Go / No-Go y Go-Live. | F8: PMO | G8: Gerente General | H8: Gerente de Proyecto | I8: Presencial | J8: 46334 | K8: 46336 | L8: =K8-J8+1 -> 3 | M8: No iniciado | N8: =IF(M8="Finalizado","",IF(K8<Hoy!$C$4,"Vencida",IF(AND(J8<=Hoy!$C$4,M8="No iniciado"),"Sin iniciar",""))) | P8: =IF(AND($D8="Hito",P$5=$J8),"◆","") | Q8: =IF(AND($D8="Hito",Q$5=$J8),"◆","") | R8: =IF(AND($D8="Hito",R$5=$J8),"◆","") | S8: =IF(AND($D8="Hito",S$5=$J8),"◆","") | T8: =IF(AND($D8="Hito",T$5=$J8),"◆","") | U8: =IF(AND($D8="Hito",U$5=$J8),"◆","") | V8: =IF(AND($D8="Hito",V$5=$J8),"◆","") | W8: =IF(AND($D8="Hito",W$5=$J8),"◆","") | ... AU8: =IF(AND($D8="Hito",AU$5=$J8),"◆","") | AW8: 1 | AX8: =IF(AND(J8<=Hoy!$C$4,K8>=Hoy!$C$4),1,0) -> 0 | AY8: =IF(AX8=1,SUM($AX$6:AX8),"") | AZ8: =IF(N8="Vencida",1,0) -> 0 | BA8: =IF(AZ8=1,SUM($AZ$6:AZ8),"")
A9: C03 | B9: 0. Equipo de proyecto en Colombia | C9: Apoyo externo para migración – 1ª visita | D9: Actividad | E9: Sebastián Salom: preparación y ejecución de la carga de datos maestros y saldos iniciales. | F9: PMO | G9: Externo – Migración | H9: Gerente de Contabilidad Regional | I9: Presencial | J9: 46329 | K9: 46332 | L9: =K9-J9+1 -> 4 | M9: No iniciado | N9: =IF(M9="Finalizado","",IF(K9<Hoy!$C$4,"Vencida",IF(AND(J9<=Hoy!$C$4,M9="No iniciado"),"Sin iniciar",""))) | P9: =IF(AND($D9="Hito",P$5=$J9),"◆","") | Q9: =IF(AND($D9="Hito",Q$5=$J9),"◆","") | R9: =IF(AND($D9="Hito",R$5=$J9),"◆","") | S9: =IF(AND($D9="Hito",S$5=$J9),"◆","") | T9: =IF(AND($D9="Hito",T$5=$J9),"◆","") | U9: =IF(AND($D9="Hito",U$5=$J9),"◆","") | V9: =IF(AND($D9="Hito",V$5=$J9),"◆","") | W9: =IF(AND($D9="Hito",W$5=$J9),"◆","") | ... AU9: =IF(AND($D9="Hito",AU$5=$J9),"◆","") | AW9: 1 | AX9: =IF(AND(J9<=Hoy!$C$4,K9>=Hoy!$C$4),1,0) -> 0 | AY9: =IF(AX9=1,SUM($AX$6:AX9),"") | AZ9: =IF(N9="Vencida",1,0) -> 0 | BA9: =IF(AZ9=1,SUM($AZ$6:AZ9),"")
A10: C04 | B10: 0. Equipo de proyecto en Colombia | C10: Apoyo externo para migración – 2ª visita | D10: Actividad | E10: Sebastián Salom: apoyo a la regularización y cuadraturas post Go-Live. | F10: PMO | G10: Externo – Migración | H10: Gerente de Contabilidad Regional | I10: Presencial | J10: 46335 | K10: 46338 | L10: =K10-J10+1 -> 4 | M10: No iniciado | N10: =IF(M10="Finalizado","",IF(K10<Hoy!$C$4,"Vencida",IF(AND(J10<=Hoy!$C$4,M10="No iniciado"),"Sin iniciar",""))) | P10: =IF(AND($D10="Hito",P$5=$J10),"◆","") | Q10: =IF(AND($D10="Hito",Q$5=$J10),"◆","") | R10: =IF(AND($D10="Hito",R$5=$J10),"◆","") | S10: =IF(AND($D10="Hito",S$5=$J10),"◆","") | T10: =IF(AND($D10="Hito",T$5=$J10),"◆","") | U10: =IF(AND($D10="Hito",U$5=$J10),"◆","") | V10: =IF(AND($D10="Hito",V$5=$J10),"◆","") | W10: =IF(AND($D10="Hito",W$5=$J10),"◆","") | ... AU10: =IF(AND($D10="Hito",AU$5=$J10),"◆","") | AW10: 1 | AX10: =IF(AND(J10<=Hoy!$C$4,K10>=Hoy!$C$4),1,0) -> 0 | AY10: =IF(AX10=1,SUM($AX$6:AX10),"") | AZ10: =IF(N10="Vencida",1,0) -> 0 | BA10: =IF(AZ10=1,SUM($AZ$6:AZ10),"")
A11: C05 | B11: 0. Equipo de proyecto en Colombia | C11: Soporte adicional post Go-Live | D11: Actividad | E11: Alonso Cuba (Portland TI Perú): soporte en sitio durante la segunda semana de Hypercare. | F11: PMO | G11: TI Portland Perú | H11: Gerente de Proyecto | I11: Presencial | J11: 46341 | K11: 46346 | L11: =K11-J11+1 -> 6 | M11: No iniciado | N11: =IF(M11="Finalizado","",IF(K11<Hoy!$C$4,"Vencida",IF(AND(J11<=Hoy!$C$4,M11="No iniciado"),"Sin iniciar",""))) | P11: =IF(AND($D11="Hito",P$5=$J11),"◆","") | Q11: =IF(AND($D11="Hito",Q$5=$J11),"◆","") | R11: =IF(AND($D11="Hito",R$5=$J11),"◆","") | S11: =IF(AND($D11="Hito",S$5=$J11),"◆","") | T11: =IF(AND($D11="Hito",T$5=$J11),"◆","") | U11: =IF(AND($D11="Hito",U$5=$J11),"◆","") | V11: =IF(AND($D11="Hito",V$5=$J11),"◆","") | W11: =IF(AND($D11="Hito",W$5=$J11),"◆","") | ... AU11: =IF(AND($D11="Hito",AU$5=$J11),"◆","") | AW11: 1 | AX11: =IF(AND(J11<=Hoy!$C$4,K11>=Hoy!$C$4),1,0) -> 0 | AY11: =IF(AX11=1,SUM($AX$6:AX11),"") | AZ11: =IF(N11="Vencida",1,0) -> 0 | BA11: =IF(AZ11=1,SUM($AZ$6:AZ11),"")
A12: 1 | B12: 1. Pruebas y Validación Modelos de Negocios | C12: Pruebas y Validación Modelos de Negocios | D12: Fase | J12: =MIN(J13:J15) -> 46321 | K12: =MAX(K13:K15) -> 46325 | L12: =K12-J12+1 -> 5 | M12: =IF(COUNTIF(M13:M15,"Finalizado")=ROWS(M13:M15),"Finalizado",IF(OR(COUNTIF(M13:M15,"Demorado")>0,COUNTIF(N13:N15,"Vencida")>0),"Demorado",IF(COUNTIF(M13:M15,"En curso")+COUNTIF(M13:M15,"Finalizado")>0,"En curso","No iniciado"))) -> En curso | N12: =IF(COUNTIF(N13:N15,"Vencida")>0,COUNTIF(N13:N15,"Vencida")&" vencida(s)","") | O12: =COUNTIF(M13:M15,"Finalizado")&" de "&ROWS(M13:M15)&" finalizadas" -> 0 de 3 finalizadas | AW12: 0
A13: C06 | B13: 1. Pruebas y Validación Modelos de Negocios | C13: Pruebas y ajustes a Modelos de Negocio | D13: Actividad | E13: Pruebas y ajustes de escenarios. | F13: Negocio | G13: Jefe de Implementación | H13: Implementador – Consultor FI/CO; Implementador – Consultor MM/SD; TI Portland FICO; TI Portland MM; Contabilidad Colombia; Comercial / Facturación Colombia; Logística / Bodega Colombia | I13: Remoto | J13: 46321 | K13: 46325 | L13: =K13-J13+1 -> 5 | M13: En curso | N13: =IF(M13="Finalizado","",IF(K13<Hoy!$C$4,"Vencida",IF(AND(J13<=Hoy!$C$4,M13="No iniciado"),"Sin iniciar",""))) | P13: =IF(AND($D13="Hito",P$5=$J13),"◆","") | Q13: =IF(AND($D13="Hito",Q$5=$J13),"◆","") | R13: =IF(AND($D13="Hito",R$5=$J13),"◆","") | S13: =IF(AND($D13="Hito",S$5=$J13),"◆","") | T13: =IF(AND($D13="Hito",T$5=$J13),"◆","") | U13: =IF(AND($D13="Hito",U$5=$J13),"◆","") | V13: =IF(AND($D13="Hito",V$5=$J13),"◆","") | W13: =IF(AND($D13="Hito",W$5=$J13),"◆","") | ... AU13: =IF(AND($D13="Hito",AU$5=$J13),"◆","") | AW13: 1 | AX13: =IF(AND(J13<=Hoy!$C$4,K13>=Hoy!$C$4),1,0) -> 1 | AY13: =IF(AX13=1,SUM($AX$6:AX13),"") -> 1 | AZ13: =IF(N13="Vencida",1,0) -> 0 | BA13: =IF(AZ13=1,SUM($AZ$6:AZ13),"")
A14: C07 | B14: 1. Pruebas y Validación Modelos de Negocios | C14: Pruebas y Ajustes a FFEE | D14: Actividad | E14: Los 4 escenarios de Documentos Electrónicos aprobador por DIAN y el Negocio. (Distribución, Exportacion, Nota Credito, Nota Débito) | F14: Localización-FFEE | G14: Jefe de Implementación | H14: TI Portland SD y FFEE; Implementador – FFEE/Formularios | I14: Remoto | J14: 46321 | K14: 46325 | L14: =K14-J14+1 -> 5 | M14: En curso | N14: =IF(M14="Finalizado","",IF(K14<Hoy!$C$4,"Vencida",IF(AND(J14<=Hoy!$C$4,M14="No iniciado"),"Sin iniciar",""))) | P14: =IF(AND($D14="Hito",P$5=$J14),"◆","") | Q14: =IF(AND($D14="Hito",Q$5=$J14),"◆","") | R14: =IF(AND($D14="Hito",R$5=$J14),"◆","") | S14: =IF(AND($D14="Hito",S$5=$J14),"◆","") | T14: =IF(AND($D14="Hito",T$5=$J14),"◆","") | U14: =IF(AND($D14="Hito",U$5=$J14),"◆","") | V14: =IF(AND($D14="Hito",V$5=$J14),"◆","") | W14: =IF(AND($D14="Hito",W$5=$J14),"◆","") | ... AU14: =IF(AND($D14="Hito",AU$5=$J14),"◆","") | AW14: 1 | AX14: =IF(AND(J14<=Hoy!$C$4,K14>=Hoy!$C$4),1,0) -> 1 | AY14: =IF(AX14=1,SUM($AX$6:AX14),"") -> 2 | AZ14: =IF(N14="Vencida",1,0) -> 0 | BA14: =IF(AZ14=1,SUM($AZ$6:AZ14),"")
A15: C09 | B15: 1. Pruebas y Validación Modelos de Negocios | C15: Validación de Modelos de Negocio y Facturación Electrónica | D15: Hito | E15: Modelos de negocio y documentos electrónicos (distribución, exportación, NC, ND) validados por el negocio y la DIAN. | F15: Negocio | G15: Jefe de Implementación | H15: Comercial / Facturación Colombia; Contabilidad Colombia; Logística / Bodega Colombia; TI Portland SD y FFEE | I15: Remoto | J15: 46325 | K15: 46325 | L15: =K15-J15+1 -> 1 | M15: No iniciado | N15: =IF(M15="Finalizado","",IF(K15<Hoy!$C$4,"Vencida",IF(AND(J15<=Hoy!$C$4,M15="No iniciado"),"Sin iniciar",""))) | P15: =IF(AND($D15="Hito",P$5=$J15),"◆","") | Q15: =IF(AND($D15="Hito",Q$5=$J15),"◆","") | R15: =IF(AND($D15="Hito",R$5=$J15),"◆","") | S15: =IF(AND($D15="Hito",S$5=$J15),"◆","") | T15: =IF(AND($D15="Hito",T$5=$J15),"◆","") | U15: =IF(AND($D15="Hito",U$5=$J15),"◆","") | V15: =IF(AND($D15="Hito",V$5=$J15),"◆","") | W15: =IF(AND($D15="Hito",W$5=$J15),"◆","") | ... AU15: =IF(AND($D15="Hito",AU$5=$J15),"◆","") | AW15: 1 | AX15: =IF(AND(J15<=Hoy!$C$4,K15>=Hoy!$C$4),1,0) -> 0 | AY15: =IF(AX15=1,SUM($AX$6:AX15),"") | AZ15: =IF(N15="Vencida",1,0) -> 0 | BA15: =IF(AZ15=1,SUM($AZ$6:AZ15),"")
A16: 2 | B16: 2. Datos maestros y Localización | C16: Datos maestros y Localización | D16: Fase | J16: =MIN(J17:J20) -> 46324 | K16: =MAX(K17:K20) -> 46328 | L16: =K16-J16+1 -> 5 | M16: =IF(COUNTIF(M17:M20,"Finalizado")=ROWS(M17:M20),"Finalizado",IF(OR(COUNTIF(M17:M20,"Demorado")>0,COUNTIF(N17:N20,"Vencida")>0),"Demorado",IF(COUNTIF(M17:M20,"En curso")+COUNTIF(M17:M20,"Finalizado")>0,"En curso","No iniciado"))) -> En curso | N16: =IF(COUNTIF(N17:N20,"Vencida")>0,COUNTIF(N17:N20,"Vencida")&" vencida(s)","") | O16: =COUNTIF(M17:M20,"Finalizado")&" de "&ROWS(M17:M20)&" finalizadas" -> 0 de 4 finalizadas | AW16: 0
A17: C10 | B17: 2. Datos maestros y Localización | C17: Plan de cuentas e impuestos validados en producción | D17: Actividad | E17: Cuentas, IVA, retenciones e ICA; se valida después del transporte 2. | F17: Financiero | G17: Gerente de Contabilidad Regional | H17: Contabilidad Colombia; TI Portland FICO; Implementador – Consultor FI/CO | I17: Remoto | J17: 46324 | K17: 46325 | L17: =K17-J17+1 -> 2 | M17: No iniciado | N17: =IF(M17="Finalizado","",IF(K17<Hoy!$C$4,"Vencida",IF(AND(J17<=Hoy!$C$4,M17="No iniciado"),"Sin iniciar",""))) | P17: =IF(AND($D17="Hito",P$5=$J17),"◆","") | Q17: =IF(AND($D17="Hito",Q$5=$J17),"◆","") | R17: =IF(AND($D17="Hito",R$5=$J17),"◆","") | S17: =IF(AND($D17="Hito",S$5=$J17),"◆","") | T17: =IF(AND($D17="Hito",T$5=$J17),"◆","") | U17: =IF(AND($D17="Hito",U$5=$J17),"◆","") | V17: =IF(AND($D17="Hito",V$5=$J17),"◆","") | W17: =IF(AND($D17="Hito",W$5=$J17),"◆","") | ... AU17: =IF(AND($D17="Hito",AU$5=$J17),"◆","") | AW17: 1 | AX17: =IF(AND(J17<=Hoy!$C$4,K17>=Hoy!$C$4),1,0) -> 0 | AY17: =IF(AX17=1,SUM($AX$6:AX17),"") | AZ17: =IF(N17="Vencida",1,0) -> 0 | BA17: =IF(AZ17=1,SUM($AZ$6:AZ17),"")
A18: C11 | B18: 2. Datos maestros y Localización | C18: Cierre de planillas de datos maestros del negocio | D18: Hito | E18: Planillas de clientes, proveedores y materiales entregadas a TI. | F18: Negocio | G18: Gerente de Contabilidad Regional | H18: Contabilidad Colombia; Comercial / Facturación Colombia; Logística / Bodega Colombia | I18: Remoto | J18: 46325 | K18: 46325 | L18: =K18-J18+1 -> 1 | M18: En curso | N18: =IF(M18="Finalizado","",IF(K18<Hoy!$C$4,"Vencida",IF(AND(J18<=Hoy!$C$4,M18="No iniciado"),"Sin iniciar",""))) | P18: =IF(AND($D18="Hito",P$5=$J18),"◆","") | Q18: =IF(AND($D18="Hito",Q$5=$J18),"◆","") | R18: =IF(AND($D18="Hito",R$5=$J18),"◆","") | S18: =IF(AND($D18="Hito",S$5=$J18),"◆","") | T18: =IF(AND($D18="Hito",T$5=$J18),"◆","") | U18: =IF(AND($D18="Hito",U$5=$J18),"◆","") | V18: =IF(AND($D18="Hito",V$5=$J18),"◆","") | W18: =IF(AND($D18="Hito",W$5=$J18),"◆","") | ... AU18: =IF(AND($D18="Hito",AU$5=$J18),"◆","") | AW18: 1 | AX18: =IF(AND(J18<=Hoy!$C$4,K18>=Hoy!$C$4),1,0) -> 0 | AY18: =IF(AX18=1,SUM($AX$6:AX18),"") | AZ18: =IF(N18="Vencida",1,0) -> 0 | BA18: =IF(AZ18=1,SUM($AZ$6:AZ18),"")
A19: C12 | B19: 2. Datos maestros y Localización | C19: Consolidación y formato de planillas por TI | D19: Actividad | E19: TI consolida y formatea las planillas en las plantillas de carga y las entrega a la Gerente de Contabilidad Regional. | F19: Técnico | G19: TI Portland MM | H19: TI Portland SD y FFEE; TI Portland FICO | I19: Remoto | J19: 46325 | K19: 46328 | L19: =K19-J19+1 -> 4 | M19: En curso | N19: =IF(M19="Finalizado","",IF(K19<Hoy!$C$4,"Vencida",IF(AND(J19<=Hoy!$C$4,M19="No iniciado"),"Sin iniciar",""))) | P19: =IF(AND($D19="Hito",P$5=$J19),"◆","") | Q19: =IF(AND($D19="Hito",Q$5=$J19),"◆","") | R19: =IF(AND($D19="Hito",R$5=$J19),"◆","") | S19: =IF(AND($D19="Hito",S$5=$J19),"◆","") | T19: =IF(AND($D19="Hito",T$5=$J19),"◆","") | U19: =IF(AND($D19="Hito",U$5=$J19),"◆","") | V19: =IF(AND($D19="Hito",V$5=$J19),"◆","") | W19: =IF(AND($D19="Hito",W$5=$J19),"◆","") | ... AU19: =IF(AND($D19="Hito",AU$5=$J19),"◆","") | AW19: 1 | AX19: =IF(AND(J19<=Hoy!$C$4,K19>=Hoy!$C$4),1,0) -> 0 | AY19: =IF(AX19=1,SUM($AX$6:AX19),"") | AZ19: =IF(N19="Vencida",1,0) -> 0 | BA19: =IF(AZ19=1,SUM($AZ$6:AZ19),"")
A20: C13 | B20: 2. Datos maestros y Localización | C20: Planillas de carga aprobadas | D20: Hito | E20: Revisión y aprobación de la Gerente de Contabilidad Regional. | F20: Financiero | G20: Gerente de Contabilidad Regional | H20: TI Portland FICO; TI Portland MM; TI Portland SD y FFEE | I20: Presencial | J20: 46328 | K20: 46328 | L20: =K20-J20+1 -> 1 | M20: No iniciado | N20: =IF(M20="Finalizado","",IF(K20<Hoy!$C$4,"Vencida",IF(AND(J20<=Hoy!$C$4,M20="No iniciado"),"Sin iniciar",""))) | P20: =IF(AND($D20="Hito",P$5=$J20),"◆","") | Q20: =IF(AND($D20="Hito",Q$5=$J20),"◆","") | R20: =IF(AND($D20="Hito",R$5=$J20),"◆","") | S20: =IF(AND($D20="Hito",S$5=$J20),"◆","") | T20: =IF(AND($D20="Hito",T$5=$J20),"◆","") | U20: =IF(AND($D20="Hito",U$5=$J20),"◆","") | V20: =IF(AND($D20="Hito",V$5=$J20),"◆","") | W20: =IF(AND($D20="Hito",W$5=$J20),"◆","") | ... AU20: =IF(AND($D20="Hito",AU$5=$J20),"◆","") | AW20: 1 | AX20: =IF(AND(J20<=Hoy!$C$4,K20>=Hoy!$C$4),1,0) -> 0 | AY20: =IF(AX20=1,SUM($AX$6:AX20),"") | AZ20: =IF(N20="Vencida",1,0) -> 0 | BA20: =IF(AZ20=1,SUM($AZ$6:AZ20),"")
A21: 3 | B21: 3. Cierre del sistema actual | C21: Cierre del sistema actual | D21: Fase | J21: =MIN(J22:J27) -> 46321 | K21: =MAX(K22:K27) -> 46330 | L21: =K21-J21+1 -> 10 | M21: =IF(COUNTIF(M22:M27,"Finalizado")=ROWS(M22:M27),"Finalizado",IF(OR(COUNTIF(M22:M27,"Demorado")>0,COUNTIF(N22:N27,"Vencida")>0),"Demorado",IF(COUNTIF(M22:M27,"En curso")+COUNTIF(M22:M27,"Finalizado")>0,"En curso","No iniciado"))) -> En curso | N21: =IF(COUNTIF(N22:N27,"Vencida")>0,COUNTIF(N22:N27,"Vencida")&" vencida(s)","") | O21: =COUNTIF(M22:M27,"Finalizado")&" de "&ROWS(M22:M27)&" finalizadas" -> 0 de 6 finalizadas | AW21: 0
A22: C14 | B22: 3. Cierre del sistema actual | C22: Registro de últimas operaciones en sistema actual | D22: Actividad | E22: Todas las transacciones de octubre ingresadas antes del corte. | F22: Negocio | G22: Contabilidad Colombia | H22: Comercial / Facturación Colombia; Logística / Bodega Colombia; Tesorería Colombia | I22: Remoto | J22: 46321 | K22: 46323 | L22: =K22-J22+1 -> 3 | M22: En curso | N22: =IF(M22="Finalizado","",IF(K22<Hoy!$C$4,"Vencida",IF(AND(J22<=Hoy!$C$4,M22="No iniciado"),"Sin iniciar",""))) | P22: =IF(AND($D22="Hito",P$5=$J22),"◆","") | Q22: =IF(AND($D22="Hito",Q$5=$J22),"◆","") | R22: =IF(AND($D22="Hito",R$5=$J22),"◆","") | S22: =IF(AND($D22="Hito",S$5=$J22),"◆","") | T22: =IF(AND($D22="Hito",T$5=$J22),"◆","") | U22: =IF(AND($D22="Hito",U$5=$J22),"◆","") | V22: =IF(AND($D22="Hito",V$5=$J22),"◆","") | W22: =IF(AND($D22="Hito",W$5=$J22),"◆","") | ... AU22: =IF(AND($D22="Hito",AU$5=$J22),"◆","") | AW22: 1 | AX22: =IF(AND(J22<=Hoy!$C$4,K22>=Hoy!$C$4),1,0) -> 1 | AY22: =IF(AX22=1,SUM($AX$6:AX22),"") -> 3 | AZ22: =IF(N22="Vencida",1,0) -> 0 | BA22: =IF(AZ22=1,SUM($AZ$6:AZ22),"")
A23: C15 | B23: 3. Cierre del sistema actual | C23: Cierre de registros del sistema actual | D23: Hito | E23: El sistema actual queda solo para consulta. | F23: Negocio | G23: Contabilidad Colombia | H23: Gerencia Colombia; PMO Portland | I23: Remoto | J23: 46323 | K23: 46323 | L23: =K23-J23+1 -> 1 | M23: En curso | N23: =IF(M23="Finalizado","",IF(K23<Hoy!$C$4,"Vencida",IF(AND(J23<=Hoy!$C$4,M23="No iniciado"),"Sin iniciar",""))) | P23: =IF(AND($D23="Hito",P$5=$J23),"◆","") | Q23: =IF(AND($D23="Hito",Q$5=$J23),"◆","") | R23: =IF(AND($D23="Hito",R$5=$J23),"◆","") | S23: =IF(AND($D23="Hito",S$5=$J23),"◆","") | T23: =IF(AND($D23="Hito",T$5=$J23),"◆","") | U23: =IF(AND($D23="Hito",U$5=$J23),"◆","") | V23: =IF(AND($D23="Hito",V$5=$J23),"◆","") | W23: =IF(AND($D23="Hito",W$5=$J23),"◆","") | ... AU23: =IF(AND($D23="Hito",AU$5=$J23),"◆","") | AW23: 1 | AX23: =IF(AND(J23<=Hoy!$C$4,K23>=Hoy!$C$4),1,0) -> 1 | AY23: =IF(AX23=1,SUM($AX$6:AX23),"") -> 4 | AZ23: =IF(N23="Vencida",1,0) -> 0 | BA23: =IF(AZ23=1,SUM($AZ$6:AZ23),"")
A24: C16 | B24: 3. Cierre del sistema actual | C24: Toma de inventario físico | D24: Actividad | E24: Conteo y reconteo de diferencias. | F24: Logístico | G24: Logística / Bodega Colombia | H24: Contabilidad Colombia; TI Portland MM | I24: Presencial | J24: 46324 | K24: 46329 | L24: =K24-J24+1 -> 6 | M24: No iniciado | N24: =IF(M24="Finalizado","",IF(K24<Hoy!$C$4,"Vencida",IF(AND(J24<=Hoy!$C$4,M24="No iniciado"),"Sin iniciar",""))) | P24: =IF(AND($D24="Hito",P$5=$J24),"◆","") | Q24: =IF(AND($D24="Hito",Q$5=$J24),"◆","") | R24: =IF(AND($D24="Hito",R$5=$J24),"◆","") | S24: =IF(AND($D24="Hito",S$5=$J24),"◆","") | T24: =IF(AND($D24="Hito",T$5=$J24),"◆","") | U24: =IF(AND($D24="Hito",U$5=$J24),"◆","") | V24: =IF(AND($D24="Hito",V$5=$J24),"◆","") | W24: =IF(AND($D24="Hito",W$5=$J24),"◆","") | ... AU24: =IF(AND($D24="Hito",AU$5=$J24),"◆","") | AW24: 1 | AX24: =IF(AND(J24<=Hoy!$C$4,K24>=Hoy!$C$4),1,0) -> 0 | AY24: =IF(AX24=1,SUM($AX$6:AX24),"") | AZ24: =IF(N24="Vencida",1,0) -> 0 | BA24: =IF(AZ24=1,SUM($AZ$6:AZ24),"")
A25: C17 | B25: 3. Cierre del sistema actual | C25: Valorización y conciliación del inventario | D25: Actividad | E25: Inventario contado valorizado y cuadrado contra contabilidad. | F25: Logístico | G25: Contabilidad Colombia | H25: Logística / Bodega Colombia; Gerente de Contabilidad Regional | I25: Presencial | J25: 46329 | K25: 46330 | L25: =K25-J25+1 -> 2 | M25: No iniciado | N25: =IF(M25="Finalizado","",IF(K25<Hoy!$C$4,"Vencida",IF(AND(J25<=Hoy!$C$4,M25="No iniciado"),"Sin iniciar",""))) | P25: =IF(AND($D25="Hito",P$5=$J25),"◆","") | Q25: =IF(AND($D25="Hito",Q$5=$J25),"◆","") | R25: =IF(AND($D25="Hito",R$5=$J25),"◆","") | S25: =IF(AND($D25="Hito",S$5=$J25),"◆","") | T25: =IF(AND($D25="Hito",T$5=$J25),"◆","") | U25: =IF(AND($D25="Hito",U$5=$J25),"◆","") | V25: =IF(AND($D25="Hito",V$5=$J25),"◆","") | W25: =IF(AND($D25="Hito",W$5=$J25),"◆","") | ... AU25: =IF(AND($D25="Hito",AU$5=$J25),"◆","") | AW25: 1 | AX25: =IF(AND(J25<=Hoy!$C$4,K25>=Hoy!$C$4),1,0) -> 0 | AY25: =IF(AX25=1,SUM($AX$6:AX25),"") | AZ25: =IF(N25="Vencida",1,0) -> 0 | BA25: =IF(AZ25=1,SUM($AZ$6:AZ25),"")
A26: C18 | B26: 3. Cierre del sistema actual | C26: Cierre contable de octubre con cuadratura de saldos | D26: Actividad | E26: Conciliaciones bancarias, impuestos y retenciones, clientes, proveedores, inventario y mayor cuadrados. | F26: Financiero | G26: Contabilidad Colombia | H26: Gerente de Contabilidad Regional; Tesorería Colombia | I26: Presencial | J26: 46324 | K26: 46330 | L26: =K26-J26+1 -> 7 | M26: No iniciado | N26: =IF(M26="Finalizado","",IF(K26<Hoy!$C$4,"Vencida",IF(AND(J26<=Hoy!$C$4,M26="No iniciado"),"Sin iniciar",""))) | P26: =IF(AND($D26="Hito",P$5=$J26),"◆","") | Q26: =IF(AND($D26="Hito",Q$5=$J26),"◆","") | R26: =IF(AND($D26="Hito",R$5=$J26),"◆","") | S26: =IF(AND($D26="Hito",S$5=$J26),"◆","") | T26: =IF(AND($D26="Hito",T$5=$J26),"◆","") | U26: =IF(AND($D26="Hito",U$5=$J26),"◆","") | V26: =IF(AND($D26="Hito",V$5=$J26),"◆","") | W26: =IF(AND($D26="Hito",W$5=$J26),"◆","") | ... AU26: =IF(AND($D26="Hito",AU$5=$J26),"◆","") | AW26: 1 | AX26: =IF(AND(J26<=Hoy!$C$4,K26>=Hoy!$C$4),1,0) -> 0 | AY26: =IF(AX26=1,SUM($AX$6:AX26),"") | AZ26: =IF(N26="Vencida",1,0) -> 0 | BA26: =IF(AZ26=1,SUM($AZ$6:AZ26),"")
A27: C19 | B27: 3. Cierre del sistema actual | C27: Cierre contable con saldos cuadrados | D27: Hito | E27: Balance de octubre aprobado: base para la carga de saldos. | F27: Financiero | G27: Gerente de Contabilidad Regional | H27: Contabilidad Colombia; Gerencia Colombia | I27: Presencial | J27: 46330 | K27: 46330 | L27: =K27-J27+1 -> 1 | M27: No iniciado | N27: =IF(M27="Finalizado","",IF(K27<Hoy!$C$4,"Vencida",IF(AND(J27<=Hoy!$C$4,M27="No iniciado"),"Sin iniciar",""))) | P27: =IF(AND($D27="Hito",P$5=$J27),"◆","") | Q27: =IF(AND($D27="Hito",Q$5=$J27),"◆","") | R27: =IF(AND($D27="Hito",R$5=$J27),"◆","") | S27: =IF(AND($D27="Hito",S$5=$J27),"◆","") | T27: =IF(AND($D27="Hito",T$5=$J27),"◆","") | U27: =IF(AND($D27="Hito",U$5=$J27),"◆","") | V27: =IF(AND($D27="Hito",V$5=$J27),"◆","") | W27: =IF(AND($D27="Hito",W$5=$J27),"◆","") | ... AU27: =IF(AND($D27="Hito",AU$5=$J27),"◆","") | AW27: 1 | AX27: =IF(AND(J27<=Hoy!$C$4,K27>=Hoy!$C$4),1,0) -> 0 | AY27: =IF(AX27=1,SUM($AX$6:AX27),"") | AZ27: =IF(N27="Vencida",1,0) -> 0 | BA27: =IF(AZ27=1,SUM($AZ$6:AZ27),"")
A28: 4 | B28: 4. Operación en contingencia | C28: Operación en contingencia | D28: Fase | J28: =MIN(J29:J31) -> 46329 | K28: =MAX(K29:K31) -> 46332 | L28: =K28-J28+1 -> 4 | M28: =IF(COUNTIF(M29:M31,"Finalizado")=ROWS(M29:M31),"Finalizado",IF(OR(COUNTIF(M29:M31,"Demorado")>0,COUNTIF(N29:N31,"Vencida")>0),"Demorado",IF(COUNTIF(M29:M31,"En curso")+COUNTIF(M29:M31,"Finalizado")>0,"En curso","No iniciado"))) -> No iniciado | N28: =IF(COUNTIF(N29:N31,"Vencida")>0,COUNTIF(N29:N31,"Vencida")&" vencida(s)","") | O28: =COUNTIF(M29:M31,"Finalizado")&" de "&ROWS(M29:M31)&" finalizadas" -> 0 de 3 finalizadas | AW28: 0
A29: C20 | B29: 4. Operación en contingencia | C29: Ventas con facturas manuales | D29: Actividad | E29: Emisión controlada según procedimiento de contingencia. | F29: Negocio | G29: Comercial / Facturación Colombia | H29: TI Portland SD y FFEE; Proveedor FE (Estupendo) | I29: Presencial | J29: 46329 | K29: 46332 | L29: =K29-J29+1 -> 4 | M29: No iniciado | N29: =IF(M29="Finalizado","",IF(K29<Hoy!$C$4,"Vencida",IF(AND(J29<=Hoy!$C$4,M29="No iniciado"),"Sin iniciar",""))) | P29: =IF(AND($D29="Hito",P$5=$J29),"◆","") | Q29: =IF(AND($D29="Hito",Q$5=$J29),"◆","") | R29: =IF(AND($D29="Hito",R$5=$J29),"◆","") | S29: =IF(AND($D29="Hito",S$5=$J29),"◆","") | T29: =IF(AND($D29="Hito",T$5=$J29),"◆","") | U29: =IF(AND($D29="Hito",U$5=$J29),"◆","") | V29: =IF(AND($D29="Hito",V$5=$J29),"◆","") | W29: =IF(AND($D29="Hito",W$5=$J29),"◆","") | ... AU29: =IF(AND($D29="Hito",AU$5=$J29),"◆","") | AW29: 1 | AX29: =IF(AND(J29<=Hoy!$C$4,K29>=Hoy!$C$4),1,0) -> 0 | AY29: =IF(AX29=1,SUM($AX$6:AX29),"") | AZ29: =IF(N29="Vencida",1,0) -> 0 | BA29: =IF(AZ29=1,SUM($AZ$6:AZ29),"")
A30: C21 | B30: 4. Operación en contingencia | C30: Compras y recepciones manuales | D30: Actividad | E30: Registro en planilla de pedidos y recepciones. | F30: Logístico | G30: Logística / Bodega Colombia | H30: TI Portland MM | I30: Presencial | J30: 46329 | K30: 46332 | L30: =K30-J30+1 -> 4 | M30: No iniciado | N30: =IF(M30="Finalizado","",IF(K30<Hoy!$C$4,"Vencida",IF(AND(J30<=Hoy!$C$4,M30="No iniciado"),"Sin iniciar",""))) | P30: =IF(AND($D30="Hito",P$5=$J30),"◆","") | Q30: =IF(AND($D30="Hito",Q$5=$J30),"◆","") | R30: =IF(AND($D30="Hito",R$5=$J30),"◆","") | S30: =IF(AND($D30="Hito",S$5=$J30),"◆","") | T30: =IF(AND($D30="Hito",T$5=$J30),"◆","") | U30: =IF(AND($D30="Hito",U$5=$J30),"◆","") | V30: =IF(AND($D30="Hito",V$5=$J30),"◆","") | W30: =IF(AND($D30="Hito",W$5=$J30),"◆","") | ... AU30: =IF(AND($D30="Hito",AU$5=$J30),"◆","") | AW30: 1 | AX30: =IF(AND(J30<=Hoy!$C$4,K30>=Hoy!$C$4),1,0) -> 0 | AY30: =IF(AX30=1,SUM($AX$6:AX30),"") | AZ30: =IF(N30="Vencida",1,0) -> 0 | BA30: =IF(AZ30=1,SUM($AZ$6:AZ30),"")
A31: C22 | B31: 4. Operación en contingencia | C31: Cobros y pagos manuales | D31: Actividad | E31: Registro en planilla de movimientos bancarios. | F31: Financiero | G31: Tesorería Colombia | H31: Contabilidad Colombia | I31: Presencial | J31: 46329 | K31: 46332 | L31: =K31-J31+1 -> 4 | M31: No iniciado | N31: =IF(M31="Finalizado","",IF(K31<Hoy!$C$4,"Vencida",IF(AND(J31<=Hoy!$C$4,M31="No iniciado"),"Sin iniciar",""))) | P31: =IF(AND($D31="Hito",P$5=$J31),"◆","") | Q31: =IF(AND($D31="Hito",Q$5=$J31),"◆","") | R31: =IF(AND($D31="Hito",R$5=$J31),"◆","") | S31: =IF(AND($D31="Hito",S$5=$J31),"◆","") | T31: =IF(AND($D31="Hito",T$5=$J31),"◆","") | U31: =IF(AND($D31="Hito",U$5=$J31),"◆","") | V31: =IF(AND($D31="Hito",V$5=$J31),"◆","") | W31: =IF(AND($D31="Hito",W$5=$J31),"◆","") | ... AU31: =IF(AND($D31="Hito",AU$5=$J31),"◆","") | AW31: 1 | AX31: =IF(AND(J31<=Hoy!$C$4,K31>=Hoy!$C$4),1,0) -> 0 | AY31: =IF(AX31=1,SUM($AX$6:AX31),"") | AZ31: =IF(N31="Vencida",1,0) -> 0 | BA31: =IF(AZ31=1,SUM($AZ$6:AZ31),"")
A32: 5 | B32: 5. Secuencia de Paso a Producción | C32: Secuencia de Paso a Producción | D32: Fase | J32: =MIN(J33:J40) -> 46321 | K32: =MAX(K33:K40) -> 46330 | L32: =K32-J32+1 -> 10 | M32: =IF(COUNTIF(M33:M40,"Finalizado")=ROWS(M33:M40),"Finalizado",IF(OR(COUNTIF(M33:M40,"Demorado")>0,COUNTIF(N33:N40,"Vencida")>0),"Demorado",IF(COUNTIF(M33:M40,"En curso")+COUNTIF(M33:M40,"Finalizado")>0,"En curso","No iniciado"))) -> En curso | N32: =IF(COUNTIF(N33:N40,"Vencida")>0,COUNTIF(N33:N40,"Vencida")&" vencida(s)","") | O32: =COUNTIF(M33:M40,"Finalizado")&" de "&ROWS(M33:M40)&" finalizadas" -> 0 de 8 finalizadas | AW32: 0
A33: C23 | B33: 5. Secuencia de Paso a Producción | C33: Pruebas de Regresión Perú | D33: Actividad | E33: Ejecución de Flujos de Compra, Venta y Facturación en la sociedad 2000 para validar que no hay impacto en lo existente. | F33: Negocio | G33: TI Portland Perú | H33: TI Portland Perú | I33: Remoto | J33: 46321 | K33: 46323 | L33: =K33-J33+1 -> 3 | M33: En curso | N33: =IF(M33="Finalizado","",IF(K33<Hoy!$C$4,"Vencida",IF(AND(J33<=Hoy!$C$4,M33="No iniciado"),"Sin iniciar",""))) | P33: =IF(AND($D33="Hito",P$5=$J33),"◆","") | Q33: =IF(AND($D33="Hito",Q$5=$J33),"◆","") | R33: =IF(AND($D33="Hito",R$5=$J33),"◆","") | S33: =IF(AND($D33="Hito",S$5=$J33),"◆","") | T33: =IF(AND($D33="Hito",T$5=$J33),"◆","") | U33: =IF(AND($D33="Hito",U$5=$J33),"◆","") | V33: =IF(AND($D33="Hito",V$5=$J33),"◆","") | W33: =IF(AND($D33="Hito",W$5=$J33),"◆","") | ... AU33: =IF(AND($D33="Hito",AU$5=$J33),"◆","") | AW33: 1 | AX33: =IF(AND(J33<=Hoy!$C$4,K33>=Hoy!$C$4),1,0) -> 1 | AY33: =IF(AX33=1,SUM($AX$6:AX33),"") -> 5 | AZ33: =IF(N33="Vencida",1,0) -> 0 | BA33: =IF(AZ33=1,SUM($AZ$6:AZ33),"")
A34: C24 | B34: 5. Secuencia de Paso a Producción | C34: Paso a producción 1: estructuras organizativas y configuraciones base | D34: Actividad | E34: Sociedad, centros, almacenes, organizaciones de compra y venta y parametrización base. | F34: Técnico | G34: Jefe de Implementación | H34: Implementador – Consultor FI/CO; Implementador – Consultor MM/SD; Implementador – FFEE/Formularios; TI Portland FICO | I34: Remoto | J34: 46324 | K34: 46325 | L34: =K34-J34+1 -> 2 | M34: No iniciado | N34: =IF(M34="Finalizado","",IF(K34<Hoy!$C$4,"Vencida",IF(AND(J34<=Hoy!$C$4,M34="No iniciado"),"Sin iniciar",""))) | P34: =IF(AND($D34="Hito",P$5=$J34),"◆","") | Q34: =IF(AND($D34="Hito",Q$5=$J34),"◆","") | R34: =IF(AND($D34="Hito",R$5=$J34),"◆","") | S34: =IF(AND($D34="Hito",S$5=$J34),"◆","") | T34: =IF(AND($D34="Hito",T$5=$J34),"◆","") | U34: =IF(AND($D34="Hito",U$5=$J34),"◆","") | V34: =IF(AND($D34="Hito",V$5=$J34),"◆","") | W34: =IF(AND($D34="Hito",W$5=$J34),"◆","") | ... AU34: =IF(AND($D34="Hito",AU$5=$J34),"◆","") | AW34: 1 | AX34: =IF(AND(J34<=Hoy!$C$4,K34>=Hoy!$C$4),1,0) -> 0 | AY34: =IF(AX34=1,SUM($AX$6:AX34),"") | AZ34: =IF(N34="Vencida",1,0) -> 0 | BA34: =IF(AZ34=1,SUM($AZ$6:AZ34),"")
A35: C25 | B35: 5. Secuencia de Paso a Producción | C35: Paso a producción 2: plan de cuentas | D35: Actividad | E35: Plan de cuentas, determinación de cuentas e impuestos. | F35: Técnico | G35: Jefe de Implementación | H35: Implementador – Consultor FI/CO; Implementador – Consultor MM/SD; Implementador – FFEE/Formularios; TI Portland FICO | I35: Remoto | J35: 46324 | K35: 46325 | L35: =K35-J35+1 -> 2 | M35: No iniciado | N35: =IF(M35="Finalizado","",IF(K35<Hoy!$C$4,"Vencida",IF(AND(J35<=Hoy!$C$4,M35="No iniciado"),"Sin iniciar",""))) | P35: =IF(AND($D35="Hito",P$5=$J35),"◆","") | Q35: =IF(AND($D35="Hito",Q$5=$J35),"◆","") | R35: =IF(AND($D35="Hito",R$5=$J35),"◆","") | S35: =IF(AND($D35="Hito",S$5=$J35),"◆","") | T35: =IF(AND($D35="Hito",T$5=$J35),"◆","") | U35: =IF(AND($D35="Hito",U$5=$J35),"◆","") | V35: =IF(AND($D35="Hito",V$5=$J35),"◆","") | W35: =IF(AND($D35="Hito",W$5=$J35),"◆","") | ... AU35: =IF(AND($D35="Hito",AU$5=$J35),"◆","") | AW35: 1 | AX35: =IF(AND(J35<=Hoy!$C$4,K35>=Hoy!$C$4),1,0) -> 0 | AY35: =IF(AX35=1,SUM($AX$6:AX35),"") | AZ35: =IF(N35="Vencida",1,0) -> 0 | BA35: =IF(AZ35=1,SUM($AZ$6:AZ35),"")
A36: C26 | B36: 5. Secuencia de Paso a Producción | C36: Paso a producción 3: centros de costos | D36: Actividad | E36: Jerarquía estándar y centros de costo / beneficio. | F36: Técnico | G36: Jefe de Implementación | H36: Implementador – Consultor FI/CO; Implementador – Consultor MM/SD; Implementador – FFEE/Formularios; TI Portland FICO | I36: Remoto | J36: 46324 | K36: 46325 | L36: =K36-J36+1 -> 2 | M36: No iniciado | N36: =IF(M36="Finalizado","",IF(K36<Hoy!$C$4,"Vencida",IF(AND(J36<=Hoy!$C$4,M36="No iniciado"),"Sin iniciar",""))) | P36: =IF(AND($D36="Hito",P$5=$J36),"◆","") | Q36: =IF(AND($D36="Hito",Q$5=$J36),"◆","") | R36: =IF(AND($D36="Hito",R$5=$J36),"◆","") | S36: =IF(AND($D36="Hito",S$5=$J36),"◆","") | T36: =IF(AND($D36="Hito",T$5=$J36),"◆","") | U36: =IF(AND($D36="Hito",U$5=$J36),"◆","") | V36: =IF(AND($D36="Hito",V$5=$J36),"◆","") | W36: =IF(AND($D36="Hito",W$5=$J36),"◆","") | ... AU36: =IF(AND($D36="Hito",AU$5=$J36),"◆","") | AW36: 1 | AX36: =IF(AND(J36<=Hoy!$C$4,K36>=Hoy!$C$4),1,0) -> 0 | AY36: =IF(AX36=1,SUM($AX$6:AX36),"") | AZ36: =IF(N36="Vencida",1,0) -> 0 | BA36: =IF(AZ36=1,SUM($AZ$6:AZ36),"")
A37: C27 | B37: 5. Secuencia de Paso a Producción | C37: Paso a producción 4: modelos de negocio y Facturación Electrónica | D37: Actividad | E37: Procesos de compra, venta y formularios; habilitación productiva de FE con Estupendo y DIAN. | F37: Técnico | G37: Jefe de Implementación | H37: Implementador – Consultor FI/CO; Implementador – Consultor MM/SD; Implementador – FFEE/Formularios; TI Portland FICO; TI Portland SD y FFEE; Proveedor FE (Estupendo) | I37: Remoto | J37: 46324 | K37: 46325 | L37: =K37-J37+1 -> 2 | M37: No iniciado | N37: =IF(M37="Finalizado","",IF(K37<Hoy!$C$4,"Vencida",IF(AND(J37<=Hoy!$C$4,M37="No iniciado"),"Sin iniciar",""))) | P37: =IF(AND($D37="Hito",P$5=$J37),"◆","") | Q37: =IF(AND($D37="Hito",Q$5=$J37),"◆","") | R37: =IF(AND($D37="Hito",R$5=$J37),"◆","") | S37: =IF(AND($D37="Hito",S$5=$J37),"◆","") | T37: =IF(AND($D37="Hito",T$5=$J37),"◆","") | U37: =IF(AND($D37="Hito",U$5=$J37),"◆","") | V37: =IF(AND($D37="Hito",V$5=$J37),"◆","") | W37: =IF(AND($D37="Hito",W$5=$J37),"◆","") | ... AU37: =IF(AND($D37="Hito",AU$5=$J37),"◆","") | AW37: 1 | AX37: =IF(AND(J37<=Hoy!$C$4,K37>=Hoy!$C$4),1,0) -> 0 | AY37: =IF(AX37=1,SUM($AX$6:AX37),"") | AZ37: =IF(N37="Vencida",1,0) -> 0 | BA37: =IF(AZ37=1,SUM($AZ$6:AZ37),"")
A38: C28 | B38: 5. Secuencia de Paso a Producción | C38: Paso a producción 5: carga de datos maestros | D38: Actividad | E38: Clientes, proveedores, materiales y activos fijos; antes de la carga de saldos. Preparación y ejecución: Sebastián Salom (externo). | F38: Financiero | G38: Gerente de Contabilidad Regional | H38: Externo – Migración; TI Portland FICO; TI Portland MM; TI Portland SD y FFEE; Implementador – Consultor FI/CO; Implementador – Consultor MM/SD | I38: Presencial | J38: 46329 | K38: 46330 | L38: =K38-J38+1 -> 2 | M38: No iniciado | N38: =IF(M38="Finalizado","",IF(K38<Hoy!$C$4,"Vencida",IF(AND(J38<=Hoy!$C$4,M38="No iniciado"),"Sin iniciar",""))) | P38: =IF(AND($D38="Hito",P$5=$J38),"◆","") | Q38: =IF(AND($D38="Hito",Q$5=$J38),"◆","") | R38: =IF(AND($D38="Hito",R$5=$J38),"◆","") | S38: =IF(AND($D38="Hito",S$5=$J38),"◆","") | T38: =IF(AND($D38="Hito",T$5=$J38),"◆","") | U38: =IF(AND($D38="Hito",U$5=$J38),"◆","") | V38: =IF(AND($D38="Hito",V$5=$J38),"◆","") | W38: =IF(AND($D38="Hito",W$5=$J38),"◆","") | ... AU38: =IF(AND($D38="Hito",AU$5=$J38),"◆","") | AW38: 1 | AX38: =IF(AND(J38<=Hoy!$C$4,K38>=Hoy!$C$4),1,0) -> 0 | AY38: =IF(AX38=1,SUM($AX$6:AX38),"") | AZ38: =IF(N38="Vencida",1,0) -> 0 | BA38: =IF(AZ38=1,SUM($AZ$6:AZ38),"")
A39: C29 | B39: 5. Secuencia de Paso a Producción | C39: Validación y Ajustes | D39: Actividad | E39: Revisión de las estructuras y datos cargados y aplicación de ajustes requeridos (delta) | F39: Técnico | G39: Jefe de Implementación | H39: Implementador – Consultor FI/CO; Implementador – Consultor MM/SD; Implementador – FFEE/Formularios; TI Portland FICO; TI Portland SD y FFEE; Proveedor FE (Estupendo) | I39: Remoto | J39: 46329 | K39: 46330 | L39: =K39-J39+1 -> 2 | M39: No iniciado | N39: =IF(M39="Finalizado","",IF(K39<Hoy!$C$4,"Vencida",IF(AND(J39<=Hoy!$C$4,M39="No iniciado"),"Sin iniciar",""))) | P39: =IF(AND($D39="Hito",P$5=$J39),"◆","") | Q39: =IF(AND($D39="Hito",Q$5=$J39),"◆","") | R39: =IF(AND($D39="Hito",R$5=$J39),"◆","") | S39: =IF(AND($D39="Hito",S$5=$J39),"◆","") | T39: =IF(AND($D39="Hito",T$5=$J39),"◆","") | U39: =IF(AND($D39="Hito",U$5=$J39),"◆","") | V39: =IF(AND($D39="Hito",V$5=$J39),"◆","") | W39: =IF(AND($D39="Hito",W$5=$J39),"◆","") | ... AU39: =IF(AND($D39="Hito",AU$5=$J39),"◆","") | AW39: 1 | AX39: =IF(AND(J39<=Hoy!$C$4,K39>=Hoy!$C$4),1,0) -> 0 | AY39: =IF(AX39=1,SUM($AX$6:AX39),"") | AZ39: =IF(N39="Vencida",1,0) -> 0 | BA39: =IF(AZ39=1,SUM($AZ$6:AZ39),"")
A40: C30 | B40: 5. Secuencia de Paso a Producción | C40: Datos maestros cargados y validados | D40: Hito | E40: Conformidad sobre muestra de registros cargados. Preparación y ejecución: Sebastián Salom (externo). | F40: Financiero | G40: Gerente de Contabilidad Regional | H40: Externo – Migración; Contabilidad Colombia; Comercial / Facturación Colombia; Logística / Bodega Colombia | I40: Presencial | J40: 46330 | K40: 46330 | L40: =K40-J40+1 -> 1 | M40: No iniciado | N40: =IF(M40="Finalizado","",IF(K40<Hoy!$C$4,"Vencida",IF(AND(J40<=Hoy!$C$4,M40="No iniciado"),"Sin iniciar",""))) | P40: =IF(AND($D40="Hito",P$5=$J40),"◆","") | Q40: =IF(AND($D40="Hito",Q$5=$J40),"◆","") | R40: =IF(AND($D40="Hito",R$5=$J40),"◆","") | S40: =IF(AND($D40="Hito",S$5=$J40),"◆","") | T40: =IF(AND($D40="Hito",T$5=$J40),"◆","") | U40: =IF(AND($D40="Hito",U$5=$J40),"◆","") | V40: =IF(AND($D40="Hito",V$5=$J40),"◆","") | W40: =IF(AND($D40="Hito",W$5=$J40),"◆","") | ... AU40: =IF(AND($D40="Hito",AU$5=$J40),"◆","") | AW40: 1 | AX40: =IF(AND(J40<=Hoy!$C$4,K40>=Hoy!$C$4),1,0) -> 0 | AY40: =IF(AX40=1,SUM($AX$6:AX40),"") | AZ40: =IF(N40="Vencida",1,0) -> 0 | BA40: =IF(AZ40=1,SUM($AZ$6:AZ40),"")
A41: 6 | B41: 6. Carga de Saldos Iniciales | C41: Carga de Saldos Iniciales | D41: Fase | J41: =MIN(J42:J47) -> 46330 | K41: =MAX(K42:K47) -> 46332 | L41: =K41-J41+1 -> 3 | M41: =IF(COUNTIF(M42:M47,"Finalizado")=ROWS(M42:M47),"Finalizado",IF(OR(COUNTIF(M42:M47,"Demorado")>0,COUNTIF(N42:N47,"Vencida")>0),"Demorado",IF(COUNTIF(M42:M47,"En curso")+COUNTIF(M42:M47,"Finalizado")>0,"En curso","No iniciado"))) -> No iniciado | N41: =IF(COUNTIF(N42:N47,"Vencida")>0,COUNTIF(N42:N47,"Vencida")&" vencida(s)","") | O41: =COUNTIF(M42:M47,"Finalizado")&" de "&ROWS(M42:M47)&" finalizadas" -> 0 de 6 finalizadas | AW41: 0
A42: C31 | B42: 6. Carga de Saldos Iniciales | C42: Carga de partidas abiertas de clientes y proveedores | D42: Actividad | E42: Migration Cockpit, en COP y USD. Preparación y ejecución: Sebastián Salom (externo). | F42: Financiero | G42: Gerente de Contabilidad Regional | H42: Externo – Migración; Implementador – Consultor FI/CO; TI Portland FICO; Contabilidad Colombia | I42: Presencial | J42: 46330 | K42: 46331 | L42: =K42-J42+1 -> 2 | M42: No iniciado | N42: =IF(M42="Finalizado","",IF(K42<Hoy!$C$4,"Vencida",IF(AND(J42<=Hoy!$C$4,M42="No iniciado"),"Sin iniciar",""))) | P42: =IF(AND($D42="Hito",P$5=$J42),"◆","") | Q42: =IF(AND($D42="Hito",Q$5=$J42),"◆","") | R42: =IF(AND($D42="Hito",R$5=$J42),"◆","") | S42: =IF(AND($D42="Hito",S$5=$J42),"◆","") | T42: =IF(AND($D42="Hito",T$5=$J42),"◆","") | U42: =IF(AND($D42="Hito",U$5=$J42),"◆","") | V42: =IF(AND($D42="Hito",V$5=$J42),"◆","") | W42: =IF(AND($D42="Hito",W$5=$J42),"◆","") | ... AU42: =IF(AND($D42="Hito",AU$5=$J42),"◆","") | AW42: 1 | AX42: =IF(AND(J42<=Hoy!$C$4,K42>=Hoy!$C$4),1,0) -> 0 | AY42: =IF(AX42=1,SUM($AX$6:AX42),"") | AZ42: =IF(N42="Vencida",1,0) -> 0 | BA42: =IF(AZ42=1,SUM($AZ$6:AZ42),"")
A43: C32 | B43: 6. Carga de Saldos Iniciales | C43: Carga de saldos de mayor y bancos (COP/USD) | D43: Actividad | E43: Saldos iniciales contra cuentas de migración. Preparación y ejecución: Sebastián Salom (externo). | F43: Financiero | G43: Gerente de Contabilidad Regional | H43: Externo – Migración; Implementador – Consultor FI/CO; TI Portland FICO; Tesorería Colombia | I43: Presencial | J43: 46331 | K43: 46331 | L43: =K43-J43+1 -> 1 | M43: No iniciado | N43: =IF(M43="Finalizado","",IF(K43<Hoy!$C$4,"Vencida",IF(AND(J43<=Hoy!$C$4,M43="No iniciado"),"Sin iniciar",""))) | P43: =IF(AND($D43="Hito",P$5=$J43),"◆","") | Q43: =IF(AND($D43="Hito",Q$5=$J43),"◆","") | R43: =IF(AND($D43="Hito",R$5=$J43),"◆","") | S43: =IF(AND($D43="Hito",S$5=$J43),"◆","") | T43: =IF(AND($D43="Hito",T$5=$J43),"◆","") | U43: =IF(AND($D43="Hito",U$5=$J43),"◆","") | V43: =IF(AND($D43="Hito",V$5=$J43),"◆","") | W43: =IF(AND($D43="Hito",W$5=$J43),"◆","") | ... AU43: =IF(AND($D43="Hito",AU$5=$J43),"◆","") | AW43: 1 | AX43: =IF(AND(J43<=Hoy!$C$4,K43>=Hoy!$C$4),1,0) -> 0 | AY43: =IF(AX43=1,SUM($AX$6:AX43),"") | AZ43: =IF(N43="Vencida",1,0) -> 0 | BA43: =IF(AZ43=1,SUM($AZ$6:AZ43),"")
A44: C33 | B44: 6. Carga de Saldos Iniciales | C44: Carga de inventario inicial | D44: Actividad | E44: Stock valorizado por material y almacén. Preparación y ejecución: Sebastián Salom (externo). | F44: Logístico | G44: Gerente de Contabilidad Regional | H44: Externo – Migración; Implementador – Consultor MM/SD; TI Portland MM; Logística / Bodega Colombia | I44: Presencial | J44: 46331 | K44: 46332 | L44: =K44-J44+1 -> 2 | M44: No iniciado | N44: =IF(M44="Finalizado","",IF(K44<Hoy!$C$4,"Vencida",IF(AND(J44<=Hoy!$C$4,M44="No iniciado"),"Sin iniciar",""))) | P44: =IF(AND($D44="Hito",P$5=$J44),"◆","") | Q44: =IF(AND($D44="Hito",Q$5=$J44),"◆","") | R44: =IF(AND($D44="Hito",R$5=$J44),"◆","") | S44: =IF(AND($D44="Hito",S$5=$J44),"◆","") | T44: =IF(AND($D44="Hito",T$5=$J44),"◆","") | U44: =IF(AND($D44="Hito",U$5=$J44),"◆","") | V44: =IF(AND($D44="Hito",V$5=$J44),"◆","") | W44: =IF(AND($D44="Hito",W$5=$J44),"◆","") | ... AU44: =IF(AND($D44="Hito",AU$5=$J44),"◆","") | AW44: 1 | AX44: =IF(AND(J44<=Hoy!$C$4,K44>=Hoy!$C$4),1,0) -> 0 | AY44: =IF(AX44=1,SUM($AX$6:AX44),"") | AZ44: =IF(N44="Vencida",1,0) -> 0 | BA44: =IF(AZ44=1,SUM($AZ$6:AZ44),"")
A45: C34 | B45: 6. Carga de Saldos Iniciales | C45: Carga de activos fijos | D45: Actividad | E45: Valor de adquisición y depreciación acumulada. Preparación y ejecución: Sebastián Salom (externo). | F45: Financiero | G45: Gerente de Contabilidad Regional | H45: Externo – Migración; Implementador – Consultor FI/CO; TI Portland FICO; Contabilidad Colombia | I45: Presencial | J45: 46331 | K45: 46332 | L45: =K45-J45+1 -> 2 | M45: No iniciado | N45: =IF(M45="Finalizado","",IF(K45<Hoy!$C$4,"Vencida",IF(AND(J45<=Hoy!$C$4,M45="No iniciado"),"Sin iniciar",""))) | P45: =IF(AND($D45="Hito",P$5=$J45),"◆","") | Q45: =IF(AND($D45="Hito",Q$5=$J45),"◆","") | R45: =IF(AND($D45="Hito",R$5=$J45),"◆","") | S45: =IF(AND($D45="Hito",S$5=$J45),"◆","") | T45: =IF(AND($D45="Hito",T$5=$J45),"◆","") | U45: =IF(AND($D45="Hito",U$5=$J45),"◆","") | V45: =IF(AND($D45="Hito",V$5=$J45),"◆","") | W45: =IF(AND($D45="Hito",W$5=$J45),"◆","") | ... AU45: =IF(AND($D45="Hito",AU$5=$J45),"◆","") | AW45: 1 | AX45: =IF(AND(J45<=Hoy!$C$4,K45>=Hoy!$C$4),1,0) -> 0 | AY45: =IF(AX45=1,SUM($AX$6:AX45),"") | AZ45: =IF(N45="Vencida",1,0) -> 0 | BA45: =IF(AZ45=1,SUM($AZ$6:AZ45),"")
A46: C35 | B46: 6. Carga de Saldos Iniciales | C46: Validación de saldos y cuentas de migración en cero | D46: Actividad | E46: Saldos SAP contra balance de octubre. Preparación y ejecución: Sebastián Salom (externo). | F46: Financiero | G46: Gerente de Contabilidad Regional | H46: Externo – Migración; Contabilidad Colombia; Implementador – Consultor FI/CO; TI Portland FICO | I46: Presencial | J46: 46332 | K46: 46332 | L46: =K46-J46+1 -> 1 | M46: No iniciado | N46: =IF(M46="Finalizado","",IF(K46<Hoy!$C$4,"Vencida",IF(AND(J46<=Hoy!$C$4,M46="No iniciado"),"Sin iniciar",""))) | P46: =IF(AND($D46="Hito",P$5=$J46),"◆","") | Q46: =IF(AND($D46="Hito",Q$5=$J46),"◆","") | R46: =IF(AND($D46="Hito",R$5=$J46),"◆","") | S46: =IF(AND($D46="Hito",S$5=$J46),"◆","") | T46: =IF(AND($D46="Hito",T$5=$J46),"◆","") | U46: =IF(AND($D46="Hito",U$5=$J46),"◆","") | V46: =IF(AND($D46="Hito",V$5=$J46),"◆","") | W46: =IF(AND($D46="Hito",W$5=$J46),"◆","") | ... AU46: =IF(AND($D46="Hito",AU$5=$J46),"◆","") | AW46: 1 | AX46: =IF(AND(J46<=Hoy!$C$4,K46>=Hoy!$C$4),1,0) -> 0 | AY46: =IF(AX46=1,SUM($AX$6:AX46),"") | AZ46: =IF(N46="Vencida",1,0) -> 0 | BA46: =IF(AZ46=1,SUM($AZ$6:AZ46),"")
A47: C36 | B47: 6. Carga de Saldos Iniciales | C47: Saldos iniciales cargados | D47: Hito | E47: Acta de conformidad de saldos. Preparación y ejecución: Sebastián Salom (externo). | F47: Financiero | G47: Gerente de Contabilidad Regional | H47: Externo – Migración; Contabilidad Colombia; Gerencia Colombia | I47: Presencial | J47: 46332 | K47: 46332 | L47: =K47-J47+1 -> 1 | M47: No iniciado | N47: =IF(M47="Finalizado","",IF(K47<Hoy!$C$4,"Vencida",IF(AND(J47<=Hoy!$C$4,M47="No iniciado"),"Sin iniciar",""))) | P47: =IF(AND($D47="Hito",P$5=$J47),"◆","") | Q47: =IF(AND($D47="Hito",Q$5=$J47),"◆","") | R47: =IF(AND($D47="Hito",R$5=$J47),"◆","") | S47: =IF(AND($D47="Hito",S$5=$J47),"◆","") | T47: =IF(AND($D47="Hito",T$5=$J47),"◆","") | U47: =IF(AND($D47="Hito",U$5=$J47),"◆","") | V47: =IF(AND($D47="Hito",V$5=$J47),"◆","") | W47: =IF(AND($D47="Hito",W$5=$J47),"◆","") | ... AU47: =IF(AND($D47="Hito",AU$5=$J47),"◆","") | AW47: 1 | AX47: =IF(AND(J47<=Hoy!$C$4,K47>=Hoy!$C$4),1,0) -> 0 | AY47: =IF(AX47=1,SUM($AX$6:AX47),"") | AZ47: =IF(N47="Vencida",1,0) -> 0 | BA47: =IF(AZ47=1,SUM($AZ$6:AZ47),"")
A48: 7 | B48: 7. Go / No-Go y entrada en vivo | C48: Go / No-Go y entrada en vivo | D48: Fase | J48: =MIN(J49:J52) -> 46333 | K48: =MAX(K49:K52) -> 46335 | L48: =K48-J48+1 -> 3 | M48: =IF(COUNTIF(M49:M52,"Finalizado")=ROWS(M49:M52),"Finalizado",IF(OR(COUNTIF(M49:M52,"Demorado")>0,COUNTIF(N49:N52,"Vencida")>0),"Demorado",IF(COUNTIF(M49:M52,"En curso")+COUNTIF(M49:M52,"Finalizado")>0,"En curso","No iniciado"))) -> No iniciado | N48: =IF(COUNTIF(N49:N52,"Vencida")>0,COUNTIF(N49:N52,"Vencida")&" vencida(s)","") | O48: =COUNTIF(M49:M52,"Finalizado")&" de "&ROWS(M49:M52)&" finalizadas" -> 0 de 4 finalizadas | AW48: 0
A49: C37 | B49: 7. Go / No-Go y entrada en vivo | C49: Pruebas de Go / No-Go en producción | D49: Actividad | E49: Venta con FE aceptada por DIAN, compra, cobro y pago. | F49: Negocio | G49: Gerente de Proyecto | H49: Comercial / Facturación Colombia; Logística / Bodega Colombia; Tesorería Colombia; TI Portland FICO; Implementador – Consultor FI/CO; Implementador – Consultor MM/SD; Implementador – FFEE/Formularios | I49: Presencial | J49: 46333 | K49: 46333 | L49: =K49-J49+1 -> 1 | M49: No iniciado | N49: =IF(M49="Finalizado","",IF(K49<Hoy!$C$4,"Vencida",IF(AND(J49<=Hoy!$C$4,M49="No iniciado"),"Sin iniciar",""))) | P49: =IF(AND($D49="Hito",P$5=$J49),"◆","") | Q49: =IF(AND($D49="Hito",Q$5=$J49),"◆","") | R49: =IF(AND($D49="Hito",R$5=$J49),"◆","") | S49: =IF(AND($D49="Hito",S$5=$J49),"◆","") | T49: =IF(AND($D49="Hito",T$5=$J49),"◆","") | U49: =IF(AND($D49="Hito",U$5=$J49),"◆","") | V49: =IF(AND($D49="Hito",V$5=$J49),"◆","") | W49: =IF(AND($D49="Hito",W$5=$J49),"◆","") | ... AU49: =IF(AND($D49="Hito",AU$5=$J49),"◆","") | AW49: 1 | AX49: =IF(AND(J49<=Hoy!$C$4,K49>=Hoy!$C$4),1,0) -> 0 | AY49: =IF(AX49=1,SUM($AX$6:AX49),"") | AZ49: =IF(N49="Vencida",1,0) -> 0 | BA49: =IF(AZ49=1,SUM($AZ$6:AZ49),"")
A50: C38 | B50: 7. Go / No-Go y entrada en vivo | C50: Reunión de Go / No-Go | D50: Hito | E50: El comité revisa los criterios y decide la entrada en vivo. | F50: PMO | G50: Comité de Proyecto | H50: Gerente de Proyecto; Gerencia Colombia; Gerente de Contabilidad Regional; PMO Portland; Jefe de Implementación | I50: Presencial | J50: 46333 | K50: 46333 | L50: =K50-J50+1 -> 1 | M50: No iniciado | N50: =IF(M50="Finalizado","",IF(K50<Hoy!$C$4,"Vencida",IF(AND(J50<=Hoy!$C$4,M50="No iniciado"),"Sin iniciar",""))) | P50: =IF(AND($D50="Hito",P$5=$J50),"◆","") | Q50: =IF(AND($D50="Hito",Q$5=$J50),"◆","") | R50: =IF(AND($D50="Hito",R$5=$J50),"◆","") | S50: =IF(AND($D50="Hito",S$5=$J50),"◆","") | T50: =IF(AND($D50="Hito",T$5=$J50),"◆","") | U50: =IF(AND($D50="Hito",U$5=$J50),"◆","") | V50: =IF(AND($D50="Hito",V$5=$J50),"◆","") | W50: =IF(AND($D50="Hito",W$5=$J50),"◆","") | ... AU50: =IF(AND($D50="Hito",AU$5=$J50),"◆","") | AW50: 1 | AX50: =IF(AND(J50<=Hoy!$C$4,K50>=Hoy!$C$4),1,0) -> 0 | AY50: =IF(AX50=1,SUM($AX$6:AX50),"") | AZ50: =IF(N50="Vencida",1,0) -> 0 | BA50: =IF(AZ50=1,SUM($AZ$6:AZ50),"")
A51: C39 | B51: 7. Go / No-Go y entrada en vivo | C51: Go-Live: apertura de SAP a los usuarios | D51: Hito | E51: Inicio de la operación en SAP S/4HANA. | F51: PMO | G51: Gerente de Proyecto | H51: Todos | I51: Presencial | J51: 46335 | K51: 46335 | L51: =K51-J51+1 -> 1 | M51: No iniciado | N51: =IF(M51="Finalizado","",IF(K51<Hoy!$C$4,"Vencida",IF(AND(J51<=Hoy!$C$4,M51="No iniciado"),"Sin iniciar",""))) | P51: =IF(AND($D51="Hito",P$5=$J51),"◆","") | Q51: =IF(AND($D51="Hito",Q$5=$J51),"◆","") | R51: =IF(AND($D51="Hito",R$5=$J51),"◆","") | S51: =IF(AND($D51="Hito",S$5=$J51),"◆","") | T51: =IF(AND($D51="Hito",T$5=$J51),"◆","") | U51: =IF(AND($D51="Hito",U$5=$J51),"◆","") | V51: =IF(AND($D51="Hito",V$5=$J51),"◆","") | W51: =IF(AND($D51="Hito",W$5=$J51),"◆","") | ... AU51: =IF(AND($D51="Hito",AU$5=$J51),"◆","") | AW51: 1 | AX51: =IF(AND(J51<=Hoy!$C$4,K51>=Hoy!$C$4),1,0) -> 0 | AY51: =IF(AX51=1,SUM($AX$6:AX51),"") | AZ51: =IF(N51="Vencida",1,0) -> 0 | BA51: =IF(AZ51=1,SUM($AZ$6:AZ51),"")
A52: C40 | B52: 7. Go / No-Go y entrada en vivo | C52: Primera factura electrónica emitida desde SAP | D52: Hito | E52: Aceptación DIAN confirmada. | F52: Localización-FFEE | G52: Comercial / Facturación Colombia | H52: TI Portland SD y FFEE; Proveedor FE (Estupendo) | I52: Presencial | J52: 46335 | K52: 46335 | L52: =K52-J52+1 -> 1 | M52: No iniciado | N52: =IF(M52="Finalizado","",IF(K52<Hoy!$C$4,"Vencida",IF(AND(J52<=Hoy!$C$4,M52="No iniciado"),"Sin iniciar",""))) | P52: =IF(AND($D52="Hito",P$5=$J52),"◆","") | Q52: =IF(AND($D52="Hito",Q$5=$J52),"◆","") | R52: =IF(AND($D52="Hito",R$5=$J52),"◆","") | S52: =IF(AND($D52="Hito",S$5=$J52),"◆","") | T52: =IF(AND($D52="Hito",T$5=$J52),"◆","") | U52: =IF(AND($D52="Hito",U$5=$J52),"◆","") | V52: =IF(AND($D52="Hito",V$5=$J52),"◆","") | W52: =IF(AND($D52="Hito",W$5=$J52),"◆","") | ... AU52: =IF(AND($D52="Hito",AU$5=$J52),"◆","") | AW52: 1 | AX52: =IF(AND(J52<=Hoy!$C$4,K52>=Hoy!$C$4),1,0) -> 0 | AY52: =IF(AX52=1,SUM($AX$6:AX52),"") | AZ52: =IF(N52="Vencida",1,0) -> 0 | BA52: =IF(AZ52=1,SUM($AZ$6:AZ52),"")
A53: 8 | B53: 8. Regularización de operaciones | C53: Regularización de operaciones | D53: Fase | J53: =MIN(J54:J57) -> 46335 | K53: =MAX(K54:K57) -> 46338 | L53: =K53-J53+1 -> 4 | M53: =IF(COUNTIF(M54:M57,"Finalizado")=ROWS(M54:M57),"Finalizado",IF(OR(COUNTIF(M54:M57,"Demorado")>0,COUNTIF(N54:N57,"Vencida")>0),"Demorado",IF(COUNTIF(M54:M57,"En curso")+COUNTIF(M54:M57,"Finalizado")>0,"En curso","No iniciado"))) -> No iniciado | N53: =IF(COUNTIF(N54:N57,"Vencida")>0,COUNTIF(N54:N57,"Vencida")&" vencida(s)","") | O53: =COUNTIF(M54:M57,"Finalizado")&" de "&ROWS(M54:M57)&" finalizadas" -> 0 de 4 finalizadas | AW53: 0
A54: C41 | B54: 8. Regularización de operaciones | C54: Ingreso a SAP de ventas de contingencia | D54: Actividad | E54: Facturas manuales registradas con su numeración. | F54: Negocio | G54: Comercial / Facturación Colombia | H54: TI Portland SD y FFEE; Implementador – Consultor MM/SD | I54: Presencial | J54: 46335 | K54: 46336 | L54: =K54-J54+1 -> 2 | M54: No iniciado | N54: =IF(M54="Finalizado","",IF(K54<Hoy!$C$4,"Vencida",IF(AND(J54<=Hoy!$C$4,M54="No iniciado"),"Sin iniciar",""))) | P54: =IF(AND($D54="Hito",P$5=$J54),"◆","") | Q54: =IF(AND($D54="Hito",Q$5=$J54),"◆","") | R54: =IF(AND($D54="Hito",R$5=$J54),"◆","") | S54: =IF(AND($D54="Hito",S$5=$J54),"◆","") | T54: =IF(AND($D54="Hito",T$5=$J54),"◆","") | U54: =IF(AND($D54="Hito",U$5=$J54),"◆","") | V54: =IF(AND($D54="Hito",V$5=$J54),"◆","") | W54: =IF(AND($D54="Hito",W$5=$J54),"◆","") | ... AU54: =IF(AND($D54="Hito",AU$5=$J54),"◆","") | AW54: 1 | AX54: =IF(AND(J54<=Hoy!$C$4,K54>=Hoy!$C$4),1,0) -> 0 | AY54: =IF(AX54=1,SUM($AX$6:AX54),"") | AZ54: =IF(N54="Vencida",1,0) -> 0 | BA54: =IF(AZ54=1,SUM($AZ$6:AZ54),"")
A55: C42 | B55: 8. Regularización de operaciones | C55: Ingreso de compras y recepciones de contingencia | D55: Actividad | E55: Pedidos, entradas de mercancía y facturas. | F55: Logístico | G55: Logística / Bodega Colombia | H55: TI Portland MM; Implementador – Consultor MM/SD | I55: Presencial | J55: 46335 | K55: 46336 | L55: =K55-J55+1 -> 2 | M55: No iniciado | N55: =IF(M55="Finalizado","",IF(K55<Hoy!$C$4,"Vencida",IF(AND(J55<=Hoy!$C$4,M55="No iniciado"),"Sin iniciar",""))) | P55: =IF(AND($D55="Hito",P$5=$J55),"◆","") | Q55: =IF(AND($D55="Hito",Q$5=$J55),"◆","") | R55: =IF(AND($D55="Hito",R$5=$J55),"◆","") | S55: =IF(AND($D55="Hito",S$5=$J55),"◆","") | T55: =IF(AND($D55="Hito",T$5=$J55),"◆","") | U55: =IF(AND($D55="Hito",U$5=$J55),"◆","") | V55: =IF(AND($D55="Hito",V$5=$J55),"◆","") | W55: =IF(AND($D55="Hito",W$5=$J55),"◆","") | ... AU55: =IF(AND($D55="Hito",AU$5=$J55),"◆","") | AW55: 1 | AX55: =IF(AND(J55<=Hoy!$C$4,K55>=Hoy!$C$4),1,0) -> 0 | AY55: =IF(AX55=1,SUM($AX$6:AX55),"") | AZ55: =IF(N55="Vencida",1,0) -> 0 | BA55: =IF(AZ55=1,SUM($AZ$6:AZ55),"")
A56: C43 | B56: 8. Regularización de operaciones | C56: Ingreso de cobros y pagos de contingencia | D56: Actividad | E56: Movimientos bancarios del período. | F56: Financiero | G56: Tesorería Colombia | H56: TI Portland FICO; Implementador – Consultor FI/CO | I56: Presencial | J56: 46336 | K56: 46337 | L56: =K56-J56+1 -> 2 | M56: No iniciado | N56: =IF(M56="Finalizado","",IF(K56<Hoy!$C$4,"Vencida",IF(AND(J56<=Hoy!$C$4,M56="No iniciado"),"Sin iniciar",""))) | P56: =IF(AND($D56="Hito",P$5=$J56),"◆","") | Q56: =IF(AND($D56="Hito",Q$5=$J56),"◆","") | R56: =IF(AND($D56="Hito",R$5=$J56),"◆","") | S56: =IF(AND($D56="Hito",S$5=$J56),"◆","") | T56: =IF(AND($D56="Hito",T$5=$J56),"◆","") | U56: =IF(AND($D56="Hito",U$5=$J56),"◆","") | V56: =IF(AND($D56="Hito",V$5=$J56),"◆","") | W56: =IF(AND($D56="Hito",W$5=$J56),"◆","") | ... AU56: =IF(AND($D56="Hito",AU$5=$J56),"◆","") | AW56: 1 | AX56: =IF(AND(J56<=Hoy!$C$4,K56>=Hoy!$C$4),1,0) -> 0 | AY56: =IF(AX56=1,SUM($AX$6:AX56),"") | AZ56: =IF(N56="Vencida",1,0) -> 0 | BA56: =IF(AZ56=1,SUM($AZ$6:AZ56),"")
A57: C44 | B57: 8. Regularización de operaciones | C57: Regularización de Operaciones Finalizada | D57: Hito | E57: Ventas, compras, recepciones, cobros y pagos de contingencia ingresados en SAP; inventario y bancos cuadrados. | F57: Financiero | G57: Gerente de Contabilidad Regional | H57: Contabilidad Colombia; Logística / Bodega Colombia; Tesorería Colombia | I57: Presencial | J57: 46338 | K57: 46338 | L57: =K57-J57+1 -> 1 | M57: No iniciado | N57: =IF(M57="Finalizado","",IF(K57<Hoy!$C$4,"Vencida",IF(AND(J57<=Hoy!$C$4,M57="No iniciado"),"Sin iniciar",""))) | P57: =IF(AND($D57="Hito",P$5=$J57),"◆","") | Q57: =IF(AND($D57="Hito",Q$5=$J57),"◆","") | R57: =IF(AND($D57="Hito",R$5=$J57),"◆","") | S57: =IF(AND($D57="Hito",S$5=$J57),"◆","") | T57: =IF(AND($D57="Hito",T$5=$J57),"◆","") | U57: =IF(AND($D57="Hito",U$5=$J57),"◆","") | V57: =IF(AND($D57="Hito",V$5=$J57),"◆","") | W57: =IF(AND($D57="Hito",W$5=$J57),"◆","") | ... AU57: =IF(AND($D57="Hito",AU$5=$J57),"◆","") | AW57: 1 | AX57: =IF(AND(J57<=Hoy!$C$4,K57>=Hoy!$C$4),1,0) -> 0 | AY57: =IF(AX57=1,SUM($AX$6:AX57),"") | AZ57: =IF(N57="Vencida",1,0) -> 0 | BA57: =IF(AZ57=1,SUM($AZ$6:AZ57),"")
A58: 9 | B58: 9. Hypercare y soporte | C58: Hypercare y soporte | D58: Fase | J58: =MIN(J59:J63) -> 46335 | K58: =MAX(K59:K63) -> 46346 | L58: =K58-J58+1 -> 12 | M58: =IF(COUNTIF(M59:M63,"Finalizado")=ROWS(M59:M63),"Finalizado",IF(OR(COUNTIF(M59:M63,"Demorado")>0,COUNTIF(N59:N63,"Vencida")>0),"Demorado",IF(COUNTIF(M59:M63,"En curso")+COUNTIF(M59:M63,"Finalizado")>0,"En curso","No iniciado"))) -> No iniciado | N58: =IF(COUNTIF(N59:N63,"Vencida")>0,COUNTIF(N59:N63,"Vencida")&" vencida(s)","") | O58: =COUNTIF(M59:M63,"Finalizado")&" de "&ROWS(M59:M63)&" finalizadas" -> 0 de 5 finalizadas | AW58: 0
A59: C45 | B59: 9. Hypercare y soporte | C59: Hypercare presencial – war room diario | D59: Actividad | E59: Atención en sitio y revisión diaria de incidencias. | F59: PMO | G59: Gerente de Proyecto | H59: PMO Portland; Gerente de Contabilidad Regional; TI Portland FICO; Jefe de Implementación | I59: Presencial | J59: 46335 | K59: 46339 | L59: =K59-J59+1 -> 5 | M59: No iniciado | N59: =IF(M59="Finalizado","",IF(K59<Hoy!$C$4,"Vencida",IF(AND(J59<=Hoy!$C$4,M59="No iniciado"),"Sin iniciar",""))) | P59: =IF(AND($D59="Hito",P$5=$J59),"◆","") | Q59: =IF(AND($D59="Hito",Q$5=$J59),"◆","") | R59: =IF(AND($D59="Hito",R$5=$J59),"◆","") | S59: =IF(AND($D59="Hito",S$5=$J59),"◆","") | T59: =IF(AND($D59="Hito",T$5=$J59),"◆","") | U59: =IF(AND($D59="Hito",U$5=$J59),"◆","") | V59: =IF(AND($D59="Hito",V$5=$J59),"◆","") | W59: =IF(AND($D59="Hito",W$5=$J59),"◆","") | ... AU59: =IF(AND($D59="Hito",AU$5=$J59),"◆","") | AW59: 1 | AX59: =IF(AND(J59<=Hoy!$C$4,K59>=Hoy!$C$4),1,0) -> 0 | AY59: =IF(AX59=1,SUM($AX$6:AX59),"") | AZ59: =IF(N59="Vencida",1,0) -> 0 | BA59: =IF(AZ59=1,SUM($AZ$6:AZ59),"")
A60: C46 | B60: 9. Hypercare y soporte | C60: Soporte del implementador – frente Logístico | D60: Actividad | E60: Compras, ventas, entregas, facturación e inventario (MM/SD). | F60: Logístico | G60: Implementador – Consultor MM/SD | H60: TI Portland MM; TI Portland SD y FFEE; Logística / Bodega Colombia; Comercial / Facturación Colombia | I60: Remoto | J60: 46335 | K60: 46346 | L60: =K60-J60+1 -> 12 | M60: No iniciado | N60: =IF(M60="Finalizado","",IF(K60<Hoy!$C$4,"Vencida",IF(AND(J60<=Hoy!$C$4,M60="No iniciado"),"Sin iniciar",""))) | P60: =IF(AND($D60="Hito",P$5=$J60),"◆","") | Q60: =IF(AND($D60="Hito",Q$5=$J60),"◆","") | R60: =IF(AND($D60="Hito",R$5=$J60),"◆","") | S60: =IF(AND($D60="Hito",S$5=$J60),"◆","") | T60: =IF(AND($D60="Hito",T$5=$J60),"◆","") | U60: =IF(AND($D60="Hito",U$5=$J60),"◆","") | V60: =IF(AND($D60="Hito",V$5=$J60),"◆","") | W60: =IF(AND($D60="Hito",W$5=$J60),"◆","") | ... AU60: =IF(AND($D60="Hito",AU$5=$J60),"◆","") | AW60: 1 | AX60: =IF(AND(J60<=Hoy!$C$4,K60>=Hoy!$C$4),1,0) -> 0 | AY60: =IF(AX60=1,SUM($AX$6:AX60),"") | AZ60: =IF(N60="Vencida",1,0) -> 0 | BA60: =IF(AZ60=1,SUM($AZ$6:AZ60),"")
A61: C47 | B61: 9. Hypercare y soporte | C61: Soporte del implementador – frente Financiero | D61: Actividad | E61: Contabilidad, bancos, pagos, impuestos y retenciones (FI/CO). | F61: Financiero | G61: Implementador – Consultor FI/CO | H61: TI Portland FICO; Contabilidad Colombia; Tesorería Colombia | I61: Remoto | J61: 46335 | K61: 46346 | L61: =K61-J61+1 -> 12 | M61: No iniciado | N61: =IF(M61="Finalizado","",IF(K61<Hoy!$C$4,"Vencida",IF(AND(J61<=Hoy!$C$4,M61="No iniciado"),"Sin iniciar",""))) | P61: =IF(AND($D61="Hito",P$5=$J61),"◆","") | Q61: =IF(AND($D61="Hito",Q$5=$J61),"◆","") | R61: =IF(AND($D61="Hito",R$5=$J61),"◆","") | S61: =IF(AND($D61="Hito",S$5=$J61),"◆","") | T61: =IF(AND($D61="Hito",T$5=$J61),"◆","") | U61: =IF(AND($D61="Hito",U$5=$J61),"◆","") | V61: =IF(AND($D61="Hito",V$5=$J61),"◆","") | W61: =IF(AND($D61="Hito",W$5=$J61),"◆","") | ... AU61: =IF(AND($D61="Hito",AU$5=$J61),"◆","") | AW61: 1 | AX61: =IF(AND(J61<=Hoy!$C$4,K61>=Hoy!$C$4),1,0) -> 0 | AY61: =IF(AX61=1,SUM($AX$6:AX61),"") | AZ61: =IF(N61="Vencida",1,0) -> 0 | BA61: =IF(AZ61=1,SUM($AZ$6:AZ61),"")
A62: C48 | B62: 9. Hypercare y soporte | C62: Monitoreo de FE y rechazos DIAN | D62: Actividad | E62: Revisión diaria de documentos rechazados o pendientes. | F62: Localización-FFEE | G62: TI Portland SD y FFEE | H62: Implementador – FFEE/Formularios; Proveedor FE (Estupendo); Comercial / Facturación Colombia | I62: Remoto | J62: 46335 | K62: 46346 | L62: =K62-J62+1 -> 12 | M62: No iniciado | N62: =IF(M62="Finalizado","",IF(K62<Hoy!$C$4,"Vencida",IF(AND(J62<=Hoy!$C$4,M62="No iniciado"),"Sin iniciar",""))) | P62: =IF(AND($D62="Hito",P$5=$J62),"◆","") | Q62: =IF(AND($D62="Hito",Q$5=$J62),"◆","") | R62: =IF(AND($D62="Hito",R$5=$J62),"◆","") | S62: =IF(AND($D62="Hito",S$5=$J62),"◆","") | T62: =IF(AND($D62="Hito",T$5=$J62),"◆","") | U62: =IF(AND($D62="Hito",U$5=$J62),"◆","") | V62: =IF(AND($D62="Hito",V$5=$J62),"◆","") | W62: =IF(AND($D62="Hito",W$5=$J62),"◆","") | ... AU62: =IF(AND($D62="Hito",AU$5=$J62),"◆","") | AW62: 1 | AX62: =IF(AND(J62<=Hoy!$C$4,K62>=Hoy!$C$4),1,0) -> 0 | AY62: =IF(AX62=1,SUM($AX$6:AX62),"") | AZ62: =IF(N62="Vencida",1,0) -> 0 | BA62: =IF(AZ62=1,SUM($AZ$6:AZ62),"")
A63: C49 | B63: 9. Hypercare y soporte | C63: Cierre del Hypercare y traspaso a soporte continuo | D63: Hito | E63: Criterios de salida cumplidos. | F63: PMO | G63: Comité de Proyecto | H63: Gerente de Proyecto; Jefe de Implementación | I63: Remoto | J63: 46346 | K63: 46346 | L63: =K63-J63+1 -> 1 | M63: No iniciado | N63: =IF(M63="Finalizado","",IF(K63<Hoy!$C$4,"Vencida",IF(AND(J63<=Hoy!$C$4,M63="No iniciado"),"Sin iniciar",""))) | P63: =IF(AND($D63="Hito",P$5=$J63),"◆","") | Q63: =IF(AND($D63="Hito",Q$5=$J63),"◆","") | R63: =IF(AND($D63="Hito",R$5=$J63),"◆","") | S63: =IF(AND($D63="Hito",S$5=$J63),"◆","") | T63: =IF(AND($D63="Hito",T$5=$J63),"◆","") | U63: =IF(AND($D63="Hito",U$5=$J63),"◆","") | V63: =IF(AND($D63="Hito",V$5=$J63),"◆","") | W63: =IF(AND($D63="Hito",W$5=$J63),"◆","") | ... AU63: =IF(AND($D63="Hito",AU$5=$J63),"◆","") -> ◆ | AW63: 1 | AX63: =IF(AND(J63<=Hoy!$C$4,K63>=Hoy!$C$4),1,0) -> 0 | AY63: =IF(AX63=1,SUM($AX$6:AX63),"") | AZ63: =IF(N63="Vencida",1,0) -> 0 | BA63: =IF(AZ63=1,SUM($AZ$6:AZ63),"")
B65: Leyenda
C66: No iniciado
C67: En curso
C68: Demorado
C69: Finalizado
C70: Fin de semana / feriado
B71: ◆ | C71: Hito
C72: Alerta: «Vencida» = la fecha de fin ya pasó y no está Finalizada; «Sin iniciar» = debió comenzar y sigue No iniciado. La fecha de referencia es la de la hoja Hoy.

Sheet Resumen
A1: Estatus resumido del cutover
A2: Se calcula desde la hoja Gantt Cutover y la fecha de la hoja Hoy.
B3: ="Fecha de consulta: "&TEXT(Hoy!$C$4,"dd-mm-yyyy")&" · Go-Live: "&TEXT('Equipo y Calendario'!$B$28,"dd-mm-yyyy") -> Fecha de consulta: 28-10-2026 · Go-Live: 09-11-2026
B5: Actividades e hitos | C5: Finalizadas | D5: En curso | E5: Demoradas | F5: No iniciadas | G5: Vencidas | H5: % finalizado | I5: Días al Go-Live
B6: =COUNTIFS('Gantt Cutover'!$D$6:$D$63,"<>Fase") -> 48 | C6: =COUNTIFS('Gantt Cutover'!$D$6:$D$63,"<>Fase",'Gantt Cutover'!$M$6:$M$63,"Finalizado") -> 0 | D6: =COUNTIFS('Gantt Cutover'!$D$6:$D$63,"<>Fase",'Gantt Cutover'!$M$6:$M$63,"En curso") -> 7 | E6: =COUNTIFS('Gantt Cutover'!$D$6:$D$63,"<>Fase",'Gantt Cutover'!$M$6:$M$63,"Demorado") -> 0 | F6: =COUNTIFS('Gantt Cutover'!$D$6:$D$63,"<>Fase",'Gantt Cutover'!$M$6:$M$63,"No iniciado") -> 41 | G6: =COUNTIF('Gantt Cutover'!$N$6:$N$63,"Vencida") -> 0 | H6: =IFERROR(C6/B6,0) -> 0 | I6: ='Equipo y Calendario'!$B$28-Hoy!$C$4 -> 12
B8: Avance por fase
B9: Fase | C9: Inicio | D9: Fin | E9: Total | F9: No iniciado | G9: En curso | H9: Demorado | I9: Finalizado | J9: % finalizado | K9: Vencidas | L9: Estado de la fase
B10: 0. Equipo de proyecto en Colombia | C10: ='Gantt Cutover'!J6 -> 46328 | D10: ='Gantt Cutover'!K6 -> 46346 | E10: =COUNTIFS('Gantt Cutover'!$B$6:$B$63,$B10,'Gantt Cutover'!$D$6:$D$63,"<>Fase") -> 5 | F10: =COUNTIFS('Gantt Cutover'!$B$6:$B$63,$B10,'Gantt Cutover'!$D$6:$D$63,"<>Fase",'Gantt Cutover'!$M$6:$M$63,"No iniciado") -> 5 | G10: =COUNTIFS('Gantt Cutover'!$B$6:$B$63,$B10,'Gantt Cutover'!$D$6:$D$63,"<>Fase",'Gantt Cutover'!$M$6:$M$63,"En curso") -> 0 | H10: =COUNTIFS('Gantt Cutover'!$B$6:$B$63,$B10,'Gantt Cutover'!$D$6:$D$63,"<>Fase",'Gantt Cutover'!$M$6:$M$63,"Demorado") -> 0 | I10: =COUNTIFS('Gantt Cutover'!$B$6:$B$63,$B10,'Gantt Cutover'!$D$6:$D$63,"<>Fase",'Gantt Cutover'!$M$6:$M$63,"Finalizado") -> 0 | J10: =IFERROR(I10/E10,0) -> 0 | K10: =COUNTIFS('Gantt Cutover'!$B$6:$B$63,$B10,'Gantt Cutover'!$N$6:$N$63,"Vencida") -> 0 | L10: ='Gantt Cutover'!M6 -> No iniciado
B11: 1. Pruebas y Validación Modelos de Negocios | C11: ='Gantt Cutover'!J12 -> 46321 | D11: ='Gantt Cutover'!K12 -> 46325 | E11: =COUNTIFS('Gantt Cutover'!$B$6:$B$63,$B11,'Gantt Cutover'!$D$6:$D$63,"<>Fase") -> 3 | F11: =COUNTIFS('Gantt Cutover'!$B$6:$B$63,$B11,'Gantt Cutover'!$D$6:$D$63,"<>Fase",'Gantt Cutover'!$M$6:$M$63,"No iniciado") -> 1 | G11: =COUNTIFS('Gantt Cutover'!$B$6:$B$63,$B11,'Gantt Cutover'!$D$6:$D$63,"<>Fase",'Gantt Cutover'!$M$6:$M$63,"En curso") -> 2 | H11: =COUNTIFS('Gantt Cutover'!$B$6:$B$63,$B11,'Gantt Cutover'!$D$6:$D$63,"<>Fase",'Gantt Cutover'!$M$6:$M$63,"Demorado") -> 0 | I11: =COUNTIFS('Gantt Cutover'!$B$6:$B$63,$B11,'Gantt Cutover'!$D$6:$D$63,"<>Fase",'Gantt Cutover'!$M$6:$M$63,"Finalizado") -> 0 | J11: =IFERROR(I11/E11,0) -> 0 | K11: =COUNTIFS('Gantt Cutover'!$B$6:$B$63,$B11,'Gantt Cutover'!$N$6:$N$63,"Vencida") -> 0 | L11: ='Gantt Cutover'!M12 -> En curso
B12: 2. Datos maestros y Localización | C12: ='Gantt Cutover'!J16 -> 46324 | D12: ='Gantt Cutover'!K16 -> 46328 | E12: =COUNTIFS('Gantt Cutover'!$B$6:$B$63,$B12,'Gantt Cutover'!$D$6:$D$63,"<>Fase") -> 4 | F12: =COUNTIFS('Gantt Cutover'!$B$6:$B$63,$B12,'Gantt Cutover'!$D$6:$D$63,"<>Fase",'Gantt Cutover'!$M$6:$M$63,"No iniciado") -> 2 | G12: =COUNTIFS('Gantt Cutover'!$B$6:$B$63,$B12,'Gantt Cutover'!$D$6:$D$63,"<>Fase",'Gantt Cutover'!$M$6:$M$63,"En curso") -> 2 | H12: =COUNTIFS('Gantt Cutover'!$B$6:$B$63,$B12,'Gantt Cutover'!$D$6:$D$63,"<>Fase",'Gantt Cutover'!$M$6:$M$63,"Demorado") -> 0 | I12: =COUNTIFS('Gantt Cutover'!$B$6:$B$63,$B12,'Gantt Cutover'!$D$6:$D$63,"<>Fase",'Gantt Cutover'!$M$6:$M$63,"Finalizado") -> 0 | J12: =IFERROR(I12/E12,0) -> 0 | K12: =COUNTIFS('Gantt Cutover'!$B$6:$B$63,$B12,'Gantt Cutover'!$N$6:$N$63,"Vencida") -> 0 | L12: ='Gantt Cutover'!M16 -> En curso
B13: 3. Cierre del sistema actual | C13: ='Gantt Cutover'!J21 -> 46321 | D13: ='Gantt Cutover'!K21 -> 46330 | E13: =COUNTIFS('Gantt Cutover'!$B$6:$B$63,$B13,'Gantt Cutover'!$D$6:$D$63,"<>Fase") -> 6 | F13: =COUNTIFS('Gantt Cutover'!$B$6:$B$63,$B13,'Gantt Cutover'!$D$6:$D$63,"<>Fase",'Gantt Cutover'!$M$6:$M$63,"No iniciado") -> 4 | G13: =COUNTIFS('Gantt Cutover'!$B$6:$B$63,$B13,'Gantt Cutover'!$D$6:$D$63,"<>Fase",'Gantt Cutover'!$M$6:$M$63,"En curso") -> 2 | H13: =COUNTIFS('Gantt Cutover'!$B$6:$B$63,$B13,'Gantt Cutover'!$D$6:$D$63,"<>Fase",'Gantt Cutover'!$M$6:$M$63,"Demorado") -> 0 | I13: =COUNTIFS('Gantt Cutover'!$B$6:$B$63,$B13,'Gantt Cutover'!$D$6:$D$63,"<>Fase",'Gantt Cutover'!$M$6:$M$63,"Finalizado") -> 0 | J13: =IFERROR(I13/E13,0) -> 0 | K13: =COUNTIFS('Gantt Cutover'!$B$6:$B$63,$B13,'Gantt Cutover'!$N$6:$N$63,"Vencida") -> 0 | L13: ='Gantt Cutover'!M21 -> En curso
B14: 4. Operación en contingencia | C14: ='Gantt Cutover'!J28 -> 46329 | D14: ='Gantt Cutover'!K28 -> 46332 | E14: =COUNTIFS('Gantt Cutover'!$B$6:$B$63,$B14,'Gantt Cutover'!$D$6:$D$63,"<>Fase") -> 3 | F14: =COUNTIFS('Gantt Cutover'!$B$6:$B$63,$B14,'Gantt Cutover'!$D$6:$D$63,"<>Fase",'Gantt Cutover'!$M$6:$M$63,"No iniciado") -> 3 | G14: =COUNTIFS('Gantt Cutover'!$B$6:$B$63,$B14,'Gantt Cutover'!$D$6:$D$63,"<>Fase",'Gantt Cutover'!$M$6:$M$63,"En curso") -> 0 | H14: =COUNTIFS('Gantt Cutover'!$B$6:$B$63,$B14,'Gantt Cutover'!$D$6:$D$63,"<>Fase",'Gantt Cutover'!$M$6:$M$63,"Demorado") -> 0 | I14: =COUNTIFS('Gantt Cutover'!$B$6:$B$63,$B14,'Gantt Cutover'!$D$6:$D$63,"<>Fase",'Gantt Cutover'!$M$6:$M$63,"Finalizado") -> 0 | J14: =IFERROR(I14/E14,0) -> 0 | K14: =COUNTIFS('Gantt Cutover'!$B$6:$B$63,$B14,'Gantt Cutover'!$N$6:$N$63,"Vencida") -> 0 | L14: ='Gantt Cutover'!M28 -> No iniciado
B15: 5. Secuencia de Paso a Producción | C15: ='Gantt Cutover'!J32 -> 46321 | D15: ='Gantt Cutover'!K32 -> 46330 | E15: =COUNTIFS('Gantt Cutover'!$B$6:$B$63,$B15,'Gantt Cutover'!$D$6:$D$63,"<>Fase") -> 8 | F15: =COUNTIFS('Gantt Cutover'!$B$6:$B$63,$B15,'Gantt Cutover'!$D$6:$D$63,"<>Fase",'Gantt Cutover'!$M$6:$M$63,"No iniciado") -> 7 | G15: =COUNTIFS('Gantt Cutover'!$B$6:$B$63,$B15,'Gantt Cutover'!$D$6:$D$63,"<>Fase",'Gantt Cutover'!$M$6:$M$63,"En curso") -> 1 | H15: =COUNTIFS('Gantt Cutover'!$B$6:$B$63,$B15,'Gantt Cutover'!$D$6:$D$63,"<>Fase",'Gantt Cutover'!$M$6:$M$63,"Demorado") -> 0 | I15: =COUNTIFS('Gantt Cutover'!$B$6:$B$63,$B15,'Gantt Cutover'!$D$6:$D$63,"<>Fase",'Gantt Cutover'!$M$6:$M$63,"Finalizado") -> 0 | J15: =IFERROR(I15/E15,0) -> 0 | K15: =COUNTIFS('Gantt Cutover'!$B$6:$B$63,$B15,'Gantt Cutover'!$N$6:$N$63,"Vencida") -> 0 | L15: ='Gantt Cutover'!M32 -> En curso
B16: 6. Carga de Saldos Iniciales | C16: ='Gantt Cutover'!J41 -> 46330 | D16: ='Gantt Cutover'!K41 -> 46332 | E16: =COUNTIFS('Gantt Cutover'!$B$6:$B$63,$B16,'Gantt Cutover'!$D$6:$D$63,"<>Fase") -> 6 | F16: =COUNTIFS('Gantt Cutover'!$B$6:$B$63,$B16,'Gantt Cutover'!$D$6:$D$63,"<>Fase",'Gantt Cutover'!$M$6:$M$63,"No iniciado") -> 6 | G16: =COUNTIFS('Gantt Cutover'!$B$6:$B$63,$B16,'Gantt Cutover'!$D$6:$D$63,"<>Fase",'Gantt Cutover'!$M$6:$M$63,"En curso") -> 0 | H16: =COUNTIFS('Gantt Cutover'!$B$6:$B$63,$B16,'Gantt Cutover'!$D$6:$D$63,"<>Fase",'Gantt Cutover'!$M$6:$M$63,"Demorado") -> 0 | I16: =COUNTIFS('Gantt Cutover'!$B$6:$B$63,$B16,'Gantt Cutover'!$D$6:$D$63,"<>Fase",'Gantt Cutover'!$M$6:$M$63,"Finalizado") -> 0 | J16: =IFERROR(I16/E16,0) -> 0 | K16: =COUNTIFS('Gantt Cutover'!$B$6:$B$63,$B16,'Gantt Cutover'!$N$6:$N$63,"Vencida") -> 0 | L16: ='Gantt Cutover'!M41 -> No iniciado
B17: 7. Go / No-Go y entrada en vivo | C17: ='Gantt Cutover'!J48 -> 46333 | D17: ='Gantt Cutover'!K48 -> 46335 | E17: =COUNTIFS('Gantt Cutover'!$B$6:$B$63,$B17,'Gantt Cutover'!$D$6:$D$63,"<>Fase") -> 4 | F17: =COUNTIFS('Gantt Cutover'!$B$6:$B$63,$B17,'Gantt Cutover'!$D$6:$D$63,"<>Fase",'Gantt Cutover'!$M$6:$M$63,"No iniciado") -> 4 | G17: =COUNTIFS('Gantt Cutover'!$B$6:$B$63,$B17,'Gantt Cutover'!$D$6:$D$63,"<>Fase",'Gantt Cutover'!$M$6:$M$63,"En curso") -> 0 | H17: =COUNTIFS('Gantt Cutover'!$B$6:$B$63,$B17,'Gantt Cutover'!$D$6:$D$63,"<>Fase",'Gantt Cutover'!$M$6:$M$63,"Demorado") -> 0 | I17: =COUNTIFS('Gantt Cutover'!$B$6:$B$63,$B17,'Gantt Cutover'!$D$6:$D$63,"<>Fase",'Gantt Cutover'!$M$6:$M$63,"Finalizado") -> 0 | J17: =IFERROR(I17/E17,0) -> 0 | K17: =COUNTIFS('Gantt Cutover'!$B$6:$B$63,$B17,'Gantt Cutover'!$N$6:$N$63,"Vencida") -> 0 | L17: ='Gantt Cutover'!M48 -> No iniciado
B18: 8. Regularización de operaciones | C18: ='Gantt Cutover'!J53 -> 46335 | D18: ='Gantt Cutover'!K53 -> 46338 | E18: =COUNTIFS('Gantt Cutover'!$B$6:$B$63,$B18,'Gantt Cutover'!$D$6:$D$63,"<>Fase") -> 4 | F18: =COUNTIFS('Gantt Cutover'!$B$6:$B$63,$B18,'Gantt Cutover'!$D$6:$D$63,"<>Fase",'Gantt Cutover'!$M$6:$M$63,"No iniciado") -> 4 | G18: =COUNTIFS('Gantt Cutover'!$B$6:$B$63,$B18,'Gantt Cutover'!$D$6:$D$63,"<>Fase",'Gantt Cutover'!$M$6:$M$63,"En curso") -> 0 | H18: =COUNTIFS('Gantt Cutover'!$B$6:$B$63,$B18,'Gantt Cutover'!$D$6:$D$63,"<>Fase",'Gantt Cutover'!$M$6:$M$63,"Demorado") -> 0 | I18: =COUNTIFS('Gantt Cutover'!$B$6:$B$63,$B18,'Gantt Cutover'!$D$6:$D$63,"<>Fase",'Gantt Cutover'!$M$6:$M$63,"Finalizado") -> 0 | J18: =IFERROR(I18/E18,0) -> 0 | K18: =COUNTIFS('Gantt Cutover'!$B$6:$B$63,$B18,'Gantt Cutover'!$N$6:$N$63,"Vencida") -> 0 | L18: ='Gantt Cutover'!M53 -> No iniciado
B19: 9. Hypercare y soporte | C19: ='Gantt Cutover'!J58 -> 46335 | D19: ='Gantt Cutover'!K58 -> 46346 | E19: =COUNTIFS('Gantt Cutover'!$B$6:$B$63,$B19,'Gantt Cutover'!$D$6:$D$63,"<>Fase") -> 5 | F19: =COUNTIFS('Gantt Cutover'!$B$6:$B$63,$B19,'Gantt Cutover'!$D$6:$D$63,"<>Fase",'Gantt Cutover'!$M$6:$M$63,"No iniciado") -> 5 | G19: =COUNTIFS('Gantt Cutover'!$B$6:$B$63,$B19,'Gantt Cutover'!$D$6:$D$63,"<>Fase",'Gantt Cutover'!$M$6:$M$63,"En curso") -> 0 | H19: =COUNTIFS('Gantt Cutover'!$B$6:$B$63,$B19,'Gantt Cutover'!$D$6:$D$63,"<>Fase",'Gantt Cutover'!$M$6:$M$63,"Demorado") -> 0 | I19: =COUNTIFS('Gantt Cutover'!$B$6:$B$63,$B19,'Gantt Cutover'!$D$6:$D$63,"<>Fase",'Gantt Cutover'!$M$6:$M$63,"Finalizado") -> 0 | J19: =IFERROR(I19/E19,0) -> 0 | K19: =COUNTIFS('Gantt Cutover'!$B$6:$B$63,$B19,'Gantt Cutover'!$N$6:$N$63,"Vencida") -> 0 | L19: ='Gantt Cutover'!M58 -> No iniciado
B21: Hitos
B22: Hito | C22: Fecha | D22: Responsable | E22: Estado | F22: Días restantes
B23: ='Gantt Cutover'!C15 -> Validación de Modelos de Negocio y Facturación Electrónica | C23: ='Gantt Cutover'!J15 -> 46325 | D23: ='Gantt Cutover'!G15 -> Jefe de Implementación | E23: ='Gantt Cutover'!M15 -> No iniciado | F23: =C23-Hoy!$C$4 -> 2
B24: ='Gantt Cutover'!C18 -> Cierre de planillas de datos maestros del negocio | C24: ='Gantt Cutover'!J18 -> 46325 | D24: ='Gantt Cutover'!G18 -> Gerente de Contabilidad Regional | E24: ='Gantt Cutover'!M18 -> En curso | F24: =C24-Hoy!$C$4 -> 2
B25: ='Gantt Cutover'!C20 -> Planillas de carga aprobadas | C25: ='Gantt Cutover'!J20 -> 46328 | D25: ='Gantt Cutover'!G20 -> Gerente de Contabilidad Regional | E25: ='Gantt Cutover'!M20 -> No iniciado | F25: =C25-Hoy!$C$4 -> 5
B26: ='Gantt Cutover'!C23 -> Cierre de registros del sistema actual | C26: ='Gantt Cutover'!J23 -> 46323 | D26: ='Gantt Cutover'!G23 -> Contabilidad Colombia | E26: ='Gantt Cutover'!M23 -> En curso | F26: =C26-Hoy!$C$4 -> 0
B27: ='Gantt Cutover'!C27 -> Cierre contable con saldos cuadrados | C27: ='Gantt Cutover'!J27 -> 46330 | D27: ='Gantt Cutover'!G27 -> Gerente de Contabilidad Regional | E27: ='Gantt Cutover'!M27 -> No iniciado | F27: =C27-Hoy!$C$4 -> 7
B28: ='Gantt Cutover'!C40 -> Datos maestros cargados y validados | C28: ='Gantt Cutover'!J40 -> 46330 | D28: ='Gantt Cutover'!G40 -> Gerente de Contabilidad Regional | E28: ='Gantt Cutover'!M40 -> No iniciado | F28: =C28-Hoy!$C$4 -> 7
B29: ='Gantt Cutover'!C47 -> Saldos iniciales cargados | C29: ='Gantt Cutover'!J47 -> 46332 | D29: ='Gantt Cutover'!G47 -> Gerente de Contabilidad Regional | E29: ='Gantt Cutover'!M47 -> No iniciado | F29: =C29-Hoy!$C$4 -> 9
B30: ='Gantt Cutover'!C50 -> Reunión de Go / No-Go | C30: ='Gantt Cutover'!J50 -> 46333 | D30: ='Gantt Cutover'!G50 -> Comité de Proyecto | E30: ='Gantt Cutover'!M50 -> No iniciado | F30: =C30-Hoy!$C$4 -> 10
B31: ='Gantt Cutover'!C51 -> Go-Live: apertura de SAP a los usuarios | C31: ='Gantt Cutover'!J51 -> 46335 | D31: ='Gantt Cutover'!G51 -> Gerente de Proyecto | E31: ='Gantt Cutover'!M51 -> No iniciado | F31: =C31-Hoy!$C$4 -> 12
B32: ='Gantt Cutover'!C52 -> Primera factura electrónica emitida desde SAP | C32: ='Gantt Cutover'!J52 -> 46335 | D32: ='Gantt Cutover'!G52 -> Comercial / Facturación Colombia | E32: ='Gantt Cutover'!M52 -> No iniciado | F32: =C32-Hoy!$C$4 -> 12
B33: ='Gantt Cutover'!C57 -> Regularización de Operaciones Finalizada | C33: ='Gantt Cutover'!J57 -> 46338 | D33: ='Gantt Cutover'!G57 -> Gerente de Contabilidad Regional | E33: ='Gantt Cutover'!M57 -> No iniciado | F33: =C33-Hoy!$C$4 -> 15
B34: ='Gantt Cutover'!C63 -> Cierre del Hypercare y traspaso a soporte continuo | C34: ='Gantt Cutover'!J63 -> 46346 | D34: ='Gantt Cutover'!G63 -> Comité de Proyecto | E34: ='Gantt Cutover'!M63 -> No iniciado | F34: =C34-Hoy!$C$4 -> 23
B36: Estado por frente
B37: Frente | C37: Total | D37: No iniciado | E37: En curso | F37: Demorado | G37: Finalizado | H37: Vencidas
B38: PMO | C38: =COUNTIFS('Gantt Cutover'!$F$6:$F$63,$B38,'Gantt Cutover'!$D$6:$D$63,"<>Fase") -> 9 | D38: =COUNTIFS('Gantt Cutover'!$F$6:$F$63,$B38,'Gantt Cutover'!$D$6:$D$63,"<>Fase",'Gantt Cutover'!$M$6:$M$63,"No iniciado") -> 9 | E38: =COUNTIFS('Gantt Cutover'!$F$6:$F$63,$B38,'Gantt Cutover'!$D$6:$D$63,"<>Fase",'Gantt Cutover'!$M$6:$M$63,"En curso") -> 0 | F38: =COUNTIFS('Gantt Cutover'!$F$6:$F$63,$B38,'Gantt Cutover'!$D$6:$D$63,"<>Fase",'Gantt Cutover'!$M$6:$M$63,"Demorado") -> 0 | G38: =COUNTIFS('Gantt Cutover'!$F$6:$F$63,$B38,'Gantt Cutover'!$D$6:$D$63,"<>Fase",'Gantt Cutover'!$M$6:$M$63,"Finalizado") -> 0 | H38: =COUNTIFS('Gantt Cutover'!$F$6:$F$63,$B38,'Gantt Cutover'!$N$6:$N$63,"Vencida") -> 0
B39: Negocio | C39: =COUNTIFS('Gantt Cutover'!$F$6:$F$63,$B39,'Gantt Cutover'!$D$6:$D$63,"<>Fase") -> 9 | D39: =COUNTIFS('Gantt Cutover'!$F$6:$F$63,$B39,'Gantt Cutover'!$D$6:$D$63,"<>Fase",'Gantt Cutover'!$M$6:$M$63,"No iniciado") -> 4 | E39: =COUNTIFS('Gantt Cutover'!$F$6:$F$63,$B39,'Gantt Cutover'!$D$6:$D$63,"<>Fase",'Gantt Cutover'!$M$6:$M$63,"En curso") -> 5 | F39: =COUNTIFS('Gantt Cutover'!$F$6:$F$63,$B39,'Gantt Cutover'!$D$6:$D$63,"<>Fase",'Gantt Cutover'!$M$6:$M$63,"Demorado") -> 0 | G39: =COUNTIFS('Gantt Cutover'!$F$6:$F$63,$B39,'Gantt Cutover'!$D$6:$D$63,"<>Fase",'Gantt Cutover'!$M$6:$M$63,"Finalizado") -> 0 | H39: =COUNTIFS('Gantt Cutover'!$F$6:$F$63,$B39,'Gantt Cutover'!$N$6:$N$63,"Vencida") -> 0
B40: Financiero | C40: =COUNTIFS('Gantt Cutover'!$F$6:$F$63,$B40,'Gantt Cutover'!$D$6:$D$63,"<>Fase") -> 15 | D40: =COUNTIFS('Gantt Cutover'!$F$6:$F$63,$B40,'Gantt Cutover'!$D$6:$D$63,"<>Fase",'Gantt Cutover'!$M$6:$M$63,"No iniciado") -> 15 | E40: =COUNTIFS('Gantt Cutover'!$F$6:$F$63,$B40,'Gantt Cutover'!$D$6:$D$63,"<>Fase",'Gantt Cutover'!$M$6:$M$63,"En curso") -> 0 | F40: =COUNTIFS('Gantt Cutover'!$F$6:$F$63,$B40,'Gantt Cutover'!$D$6:$D$63,"<>Fase",'Gantt Cutover'!$M$6:$M$63,"Demorado") -> 0 | G40: =COUNTIFS('Gantt Cutover'!$F$6:$F$63,$B40,'Gantt Cutover'!$D$6:$D$63,"<>Fase",'Gantt Cutover'!$M$6:$M$63,"Finalizado") -> 0 | H40: =COUNTIFS('Gantt Cutover'!$F$6:$F$63,$B40,'Gantt Cutover'!$N$6:$N$63,"Vencida") -> 0
B41: Logístico | C41: =COUNTIFS('Gantt Cutover'!$F$6:$F$63,$B41,'Gantt Cutover'!$D$6:$D$63,"<>Fase") -> 6 | D41: =COUNTIFS('Gantt Cutover'!$F$6:$F$63,$B41,'Gantt Cutover'!$D$6:$D$63,"<>Fase",'Gantt Cutover'!$M$6:$M$63,"No iniciado") -> 6 | E41: =COUNTIFS('Gantt Cutover'!$F$6:$F$63,$B41,'Gantt Cutover'!$D$6:$D$63,"<>Fase",'Gantt Cutover'!$M$6:$M$63,"En curso") -> 0 | F41: =COUNTIFS('Gantt Cutover'!$F$6:$F$63,$B41,'Gantt Cutover'!$D$6:$D$63,"<>Fase",'Gantt Cutover'!$M$6:$M$63,"Demorado") -> 0 | G41: =COUNTIFS('Gantt Cutover'!$F$6:$F$63,$B41,'Gantt Cutover'!$D$6:$D$63,"<>Fase",'Gantt Cutover'!$M$6:$M$63,"Finalizado") -> 0 | H41: =COUNTIFS('Gantt Cutover'!$F$6:$F$63,$B41,'Gantt Cutover'!$N$6:$N$63,"Vencida") -> 0
B42: Localización-FFEE | C42: =COUNTIFS('Gantt Cutover'!$F$6:$F$63,$B42,'Gantt Cutover'!$D$6:$D$63,"<>Fase") -> 3 | D42: =COUNTIFS('Gantt Cutover'!$F$6:$F$63,$B42,'Gantt Cutover'!$D$6:$D$63,"<>Fase",'Gantt Cutover'!$M$6:$M$63,"No iniciado") -> 2 | E42: =COUNTIFS('Gantt Cutover'!$F$6:$F$63,$B42,'Gantt Cutover'!$D$6:$D$63,"<>Fase",'Gantt Cutover'!$M$6:$M$63,"En curso") -> 1 | F42: =COUNTIFS('Gantt Cutover'!$F$6:$F$63,$B42,'Gantt Cutover'!$D$6:$D$63,"<>Fase",'Gantt Cutover'!$M$6:$M$63,"Demorado") -> 0 | G42: =COUNTIFS('Gantt Cutover'!$F$6:$F$63,$B42,'Gantt Cutover'!$D$6:$D$63,"<>Fase",'Gantt Cutover'!$M$6:$M$63,"Finalizado") -> 0 | H42: =COUNTIFS('Gantt Cutover'!$F$6:$F$63,$B42,'Gantt Cutover'!$N$6:$N$63,"Vencida") -> 0
B43: Técnico | C43: =COUNTIFS('Gantt Cutover'!$F$6:$F$63,$B43,'Gantt Cutover'!$D$6:$D$63,"<>Fase") -> 6 | D43: =COUNTIFS('Gantt Cutover'!$F$6:$F$63,$B43,'Gantt Cutover'!$D$6:$D$63,"<>Fase",'Gantt Cutover'!$M$6:$M$63,"No iniciado") -> 5 | E43: =COUNTIFS('Gantt Cutover'!$F$6:$F$63,$B43,'Gantt Cutover'!$D$6:$D$63,"<>Fase",'Gantt Cutover'!$M$6:$M$63,"En curso") -> 1 | F43: =COUNTIFS('Gantt Cutover'!$F$6:$F$63,$B43,'Gantt Cutover'!$D$6:$D$63,"<>Fase",'Gantt Cutover'!$M$6:$M$63,"Demorado") -> 0 | G43: =COUNTIFS('Gantt Cutover'!$F$6:$F$63,$B43,'Gantt Cutover'!$D$6:$D$63,"<>Fase",'Gantt Cutover'!$M$6:$M$63,"Finalizado") -> 0 | H43: =COUNTIFS('Gantt Cutover'!$F$6:$F$63,$B43,'Gantt Cutover'!$N$6:$N$63,"Vencida") -> 0

Sheet Hoy
A1: Actividades del día
A2: Escriba la fecha en la celda amarilla (por defecto, la fecha actual) y la hoja muestra lo que debe estar ocurriendo ese día y quién participa.
B4: Fecha de consulta | C4: =TODAY() -> 46323
B5: Días al Go-Live | C5: ='Equipo y Calendario'!$B$28-C4 -> 12
B6: Equipo en sitio | C6: =IF(AND(C4>='Equipo y Calendario'!$B$29,C4<='Equipo y Calendario'!$B$30),"Sí – Bogotá","No") -> No
B7: Día no hábil | C7: =IF(COUNTIF('Equipo y Calendario'!$B$33:$B$38,C4)>0,"Feriado en Colombia",IF(WEEKDAY(C4,2)>5,"Fin de semana","Día hábil")) -> Día hábil
B8: Actividades del día | C8: =SUM('Gantt Cutover'!$AX$6:$AX$63) -> 5
B9: Actividades vencidas | C9: =SUM('Gantt Cutover'!$AZ$6:$AZ$63) -> 0
B12: Lo que debe estar ocurriendo en la fecha
B13: # | C13: ID | D13: Fase | E13: Actividad / hito | F13: Responsable | G13: Nombre responsable | H13: Participantes | I13: Modalidad | J13: Inicio | K13: Fin | L13: Estado
B14: 1 | C14: =IFERROR(INDEX('Gantt Cutover'!$A$6:$A$63,MATCH(1,'Gantt Cutover'!$AY$6:$AY$63,0)),"") -> C06 | D14: =IFERROR(INDEX('Gantt Cutover'!$B$6:$B$63,MATCH(1,'Gantt Cutover'!$AY$6:$AY$63,0)),"") -> 1. Pruebas y Validación Modelos de Negocios | E14: =IFERROR(INDEX('Gantt Cutover'!$C$6:$C$63,MATCH(1,'Gantt Cutover'!$AY$6:$AY$63,0)),"") -> Pruebas y ajustes a Modelos de Negocio | F14: =IFERROR(INDEX('Gantt Cutover'!$G$6:$G$63,MATCH(1,'Gantt Cutover'!$AY$6:$AY$63,0)),"") -> Jefe de Implementación | G14: =IFERROR(INDEX('Equipo y Calendario'!$B$5:$B$24,MATCH(F14,'Equipo y Calendario'!$A$5:$A$24,0)),"") -> Jorge Muñoz | H14: =IFERROR(INDEX('Gantt Cutover'!$H$6:$H$63,MATCH(1,'Gantt Cutover'!$AY$6:$AY$63,0)),"") -> Implementador – Consultor FI/CO; Implementador – Consultor MM/SD; TI Portland FICO; TI Portland MM; Contabilidad Colombia; Comercial / Facturación Colombia; Logística / Bodega Colombia | I14: =IFERROR(INDEX('Gantt Cutover'!$I$6:$I$63,MATCH(1,'Gantt Cutover'!$AY$6:$AY$63,0)),"") -> Remoto | J14: =IFERROR(INDEX('Gantt Cutover'!$J$6:$J$63,MATCH(1,'Gantt Cutover'!$AY$6:$AY$63,0)),"") -> 46321 | K14: =IFERROR(INDEX('Gantt Cutover'!$K$6:$K$63,MATCH(1,'Gantt Cutover'!$AY$6:$AY$63,0)),"") -> 46325 | L14: =IFERROR(INDEX('Gantt Cutover'!$M$6:$M$63,MATCH(1,'Gantt Cutover'!$AY$6:$AY$63,0)),"") -> En curso
B15: 2 | C15: =IFERROR(INDEX('Gantt Cutover'!$A$6:$A$63,MATCH(2,'Gantt Cutover'!$AY$6:$AY$63,0)),"") -> C07 | D15: =IFERROR(INDEX('Gantt Cutover'!$B$6:$B$63,MATCH(2,'Gantt Cutover'!$AY$6:$AY$63,0)),"") -> 1. Pruebas y Validación Modelos de Negocios | E15: =IFERROR(INDEX('Gantt Cutover'!$C$6:$C$63,MATCH(2,'Gantt Cutover'!$AY$6:$AY$63,0)),"") -> Pruebas y Ajustes a FFEE | F15: =IFERROR(INDEX('Gantt Cutover'!$G$6:$G$63,MATCH(2,'Gantt Cutover'!$AY$6:$AY$63,0)),"") -> Jefe de Implementación | G15: =IFERROR(INDEX('Equipo y Calendario'!$B$5:$B$24,MATCH(F15,'Equipo y Calendario'!$A$5:$A$24,0)),"") -> Jorge Muñoz | H15: =IFERROR(INDEX('Gantt Cutover'!$H$6:$H$63,MATCH(2,'Gantt Cutover'!$AY$6:$AY$63,0)),"") -> TI Portland SD y FFEE; Implementador – FFEE/Formularios | I15: =IFERROR(INDEX('Gantt Cutover'!$I$6:$I$63,MATCH(2,'Gantt Cutover'!$AY$6:$AY$63,0)),"") -> Remoto | J15: =IFERROR(INDEX('Gantt Cutover'!$J$6:$J$63,MATCH(2,'Gantt Cutover'!$AY$6:$AY$63,0)),"") -> 46321 | K15: =IFERROR(INDEX('Gantt Cutover'!$K$6:$K$63,MATCH(2,'Gantt Cutover'!$AY$6:$AY$63,0)),"") -> 46325 | L15: =IFERROR(INDEX('Gantt Cutover'!$M$6:$M$63,MATCH(2,'Gantt Cutover'!$AY$6:$AY$63,0)),"") -> En curso
B16: 3 | C16: =IFERROR(INDEX('Gantt Cutover'!$A$6:$A$63,MATCH(3,'Gantt Cutover'!$AY$6:$AY$63,0)),"") -> C14 | D16: =IFERROR(INDEX('Gantt Cutover'!$B$6:$B$63,MATCH(3,'Gantt Cutover'!$AY$6:$AY$63,0)),"") -> 3. Cierre del sistema actual | E16: =IFERROR(INDEX('Gantt Cutover'!$C$6:$C$63,MATCH(3,'Gantt Cutover'!$AY$6:$AY$63,0)),"") -> Registro de últimas operaciones en sistema actual | F16: =IFERROR(INDEX('Gantt Cutover'!$G$6:$G$63,MATCH(3,'Gantt Cutover'!$AY$6:$AY$63,0)),"") -> Contabilidad Colombia | G16: =IFERROR(INDEX('Equipo y Calendario'!$B$5:$B$24,MATCH(F16,'Equipo y Calendario'!$A$5:$A$24,0)),"") -> Camila Castiblanco | H16: =IFERROR(INDEX('Gantt Cutover'!$H$6:$H$63,MATCH(3,'Gantt Cutover'!$AY$6:$AY$63,0)),"") -> Comercial / Facturación Colombia; Logística / Bodega Colombia; Tesorería Colombia | I16: =IFERROR(INDEX('Gantt Cutover'!$I$6:$I$63,MATCH(3,'Gantt Cutover'!$AY$6:$AY$63,0)),"") -> Remoto | J16: =IFERROR(INDEX('Gantt Cutover'!$J$6:$J$63,MATCH(3,'Gantt Cutover'!$AY$6:$AY$63,0)),"") -> 46321 | K16: =IFERROR(INDEX('Gantt Cutover'!$K$6:$K$63,MATCH(3,'Gantt Cutover'!$AY$6:$AY$63,0)),"") -> 46323 | L16: =IFERROR(INDEX('Gantt Cutover'!$M$6:$M$63,MATCH(3,'Gantt Cutover'!$AY$6:$AY$63,0)),"") -> En curso
B17: 4 | C17: =IFERROR(INDEX('Gantt Cutover'!$A$6:$A$63,MATCH(4,'Gantt Cutover'!$AY$6:$AY$63,0)),"") -> C15 | D17: =IFERROR(INDEX('Gantt Cutover'!$B$6:$B$63,MATCH(4,'Gantt Cutover'!$AY$6:$AY$63,0)),"") -> 3. Cierre del sistema actual | E17: =IFERROR(INDEX('Gantt Cutover'!$C$6:$C$63,MATCH(4,'Gantt Cutover'!$AY$6:$AY$63,0)),"") -> Cierre de registros del sistema actual | F17: =IFERROR(INDEX('Gantt Cutover'!$G$6:$G$63,MATCH(4,'Gantt Cutover'!$AY$6:$AY$63,0)),"") -> Contabilidad Colombia | G17: =IFERROR(INDEX('Equipo y Calendario'!$B$5:$B$24,MATCH(F17,'Equipo y Calendario'!$A$5:$A$24,0)),"") -> Camila Castiblanco | H17: =IFERROR(INDEX('Gantt Cutover'!$H$6:$H$63,MATCH(4,'Gantt Cutover'!$AY$6:$AY$63,0)),"") -> Gerencia Colombia; PMO Portland | I17: =IFERROR(INDEX('Gantt Cutover'!$I$6:$I$63,MATCH(4,'Gantt Cutover'!$AY$6:$AY$63,0)),"") -> Remoto | J17: =IFERROR(INDEX('Gantt Cutover'!$J$6:$J$63,MATCH(4,'Gantt Cutover'!$AY$6:$AY$63,0)),"") -> 46323 | K17: =IFERROR(INDEX('Gantt Cutover'!$K$6:$K$63,MATCH(4,'Gantt Cutover'!$AY$6:$AY$63,0)),"") -> 46323 | L17: =IFERROR(INDEX('Gantt Cutover'!$M$6:$M$63,MATCH(4,'Gantt Cutover'!$AY$6:$AY$63,0)),"") -> En curso
B18: 5 | C18: =IFERROR(INDEX('Gantt Cutover'!$A$6:$A$63,MATCH(5,'Gantt Cutover'!$AY$6:$AY$63,0)),"") -> C23 | D18: =IFERROR(INDEX('Gantt Cutover'!$B$6:$B$63,MATCH(5,'Gantt Cutover'!$AY$6:$AY$63,0)),"") -> 5. Secuencia de Paso a Producción | E18: =IFERROR(INDEX('Gantt Cutover'!$C$6:$C$63,MATCH(5,'Gantt Cutover'!$AY$6:$AY$63,0)),"") -> Pruebas de Regresión Perú | F18: =IFERROR(INDEX('Gantt Cutover'!$G$6:$G$63,MATCH(5,'Gantt Cutover'!$AY$6:$AY$63,0)),"") -> TI Portland Perú | G18: =IFERROR(INDEX('Equipo y Calendario'!$B$5:$B$24,MATCH(F18,'Equipo y Calendario'!$A$5:$A$24,0)),"") -> Alonso Cuba | H18: =IFERROR(INDEX('Gantt Cutover'!$H$6:$H$63,MATCH(5,'Gantt Cutover'!$AY$6:$AY$63,0)),"") -> TI Portland Perú | I18: =IFERROR(INDEX('Gantt Cutover'!$I$6:$I$63,MATCH(5,'Gantt Cutover'!$AY$6:$AY$63,0)),"") -> Remoto | J18: =IFERROR(INDEX('Gantt Cutover'!$J$6:$J$63,MATCH(5,'Gantt Cutover'!$AY$6:$AY$63,0)),"") -> 46321 | K18: =IFERROR(INDEX('Gantt Cutover'!$K$6:$K$63,MATCH(5,'Gantt Cutover'!$AY$6:$AY$63,0)),"") -> 46323 | L18: =IFERROR(INDEX('Gantt Cutover'!$M$6:$M$63,MATCH(5,'Gantt Cutover'!$AY$6:$AY$63,0)),"") -> En curso
B19: 6 | C19: =IFERROR(INDEX('Gantt Cutover'!$A$6:$A$63,MATCH(6,'Gantt Cutover'!$AY$6:$AY$63,0)),"") | D19: =IFERROR(INDEX('Gantt Cutover'!$B$6:$B$63,MATCH(6,'Gantt Cutover'!$AY$6:$AY$63,0)),"") | E19: =IFERROR(INDEX('Gantt Cutover'!$C$6:$C$63,MATCH(6,'Gantt Cutover'!$AY$6:$AY$63,0)),"") | F19: =IFERROR(INDEX('Gantt Cutover'!$G$6:$G$63,MATCH(6,'Gantt Cutover'!$AY$6:$AY$63,0)),"") | G19: =IFERROR(INDEX('Equipo y Calendario'!$B$5:$B$24,MATCH(F19,'Equipo y Calendario'!$A$5:$A$24,0)),"") | H19: =IFERROR(INDEX('Gantt Cutover'!$H$6:$H$63,MATCH(6,'Gantt Cutover'!$AY$6:$AY$63,0)),"") | I19: =IFERROR(INDEX('Gantt Cutover'!$I$6:$I$63,MATCH(6,'Gantt Cutover'!$AY$6:$AY$63,0)),"") | J19: =IFERROR(INDEX('Gantt Cutover'!$J$6:$J$63,MATCH(6,'Gantt Cutover'!$AY$6:$AY$63,0)),"") | K19: =IFERROR(INDEX('Gantt Cutover'!$K$6:$K$63,MATCH(6,'Gantt Cutover'!$AY$6:$AY$63,0)),"") | L19: =IFERROR(INDEX('Gantt Cutover'!$M$6:$M$63,MATCH(6,'Gantt Cutover'!$AY$6:$AY$63,0)),"")
B20: 7 | C20: =IFERROR(INDEX('Gantt Cutover'!$A$6:$A$63,MATCH(7,'Gantt Cutover'!$AY$6:$AY$63,0)),"") | D20: =IFERROR(INDEX('Gantt Cutover'!$B$6:$B$63,MATCH(7,'Gantt Cutover'!$AY$6:$AY$63,0)),"") | E20: =IFERROR(INDEX('Gantt Cutover'!$C$6:$C$63,MATCH(7,'Gantt Cutover'!$AY$6:$AY$63,0)),"") | F20: =IFERROR(INDEX('Gantt Cutover'!$G$6:$G$63,MATCH(7,'Gantt Cutover'!$AY$6:$AY$63,0)),"") | G20: =IFERROR(INDEX('Equipo y Calendario'!$B$5:$B$24,MATCH(F20,'Equipo y Calendario'!$A$5:$A$24,0)),"") | H20: =IFERROR(INDEX('Gantt Cutover'!$H$6:$H$63,MATCH(7,'Gantt Cutover'!$AY$6:$AY$63,0)),"") | I20: =IFERROR(INDEX('Gantt Cutover'!$I$6:$I$63,MATCH(7,'Gantt Cutover'!$AY$6:$AY$63,0)),"") | J20: =IFERROR(INDEX('Gantt Cutover'!$J$6:$J$63,MATCH(7,'Gantt Cutover'!$AY$6:$AY$63,0)),"") | K20: =IFERROR(INDEX('Gantt Cutover'!$K$6:$K$63,MATCH(7,'Gantt Cutover'!$AY$6:$AY$63,0)),"") | L20: =IFERROR(INDEX('Gantt Cutover'!$M$6:$M$63,MATCH(7,'Gantt Cutover'!$AY$6:$AY$63,0)),"")
B21: 8 | C21: =IFERROR(INDEX('Gantt Cutover'!$A$6:$A$63,MATCH(8,'Gantt Cutover'!$AY$6:$AY$63,0)),"") | D21: =IFERROR(INDEX('Gantt Cutover'!$B$6:$B$63,MATCH(8,'Gantt Cutover'!$AY$6:$AY$63,0)),"") | E21: =IFERROR(INDEX('Gantt Cutover'!$C$6:$C$63,MATCH(8,'Gantt Cutover'!$AY$6:$AY$63,0)),"") | F21: =IFERROR(INDEX('Gantt Cutover'!$G$6:$G$63,MATCH(8,'Gantt Cutover'!$AY$6:$AY$63,0)),"") | G21: =IFERROR(INDEX('Equipo y Calendario'!$B$5:$B$24,MATCH(F21,'Equipo y Calendario'!$A$5:$A$24,0)),"") | H21: =IFERROR(INDEX('Gantt Cutover'!$H$6:$H$63,MATCH(8,'Gantt Cutover'!$AY$6:$AY$63,0)),"") | I21: =IFERROR(INDEX('Gantt Cutover'!$I$6:$I$63,MATCH(8,'Gantt Cutover'!$AY$6:$AY$63,0)),"") | J21: =IFERROR(INDEX('Gantt Cutover'!$J$6:$J$63,MATCH(8,'Gantt Cutover'!$AY$6:$AY$63,0)),"") | K21: =IFERROR(INDEX('Gantt Cutover'!$K$6:$K$63,MATCH(8,'Gantt Cutover'!$AY$6:$AY$63,0)),"") | L21: =IFERROR(INDEX('Gantt Cutover'!$M$6:$M$63,MATCH(8,'Gantt Cutover'!$AY$6:$AY$63,0)),"")
B22: 9 | C22: =IFERROR(INDEX('Gantt Cutover'!$A$6:$A$63,MATCH(9,'Gantt Cutover'!$AY$6:$AY$63,0)),"") | D22: =IFERROR(INDEX('Gantt Cutover'!$B$6:$B$63,MATCH(9,'Gantt Cutover'!$AY$6:$AY$63,0)),"") | E22: =IFERROR(INDEX('Gantt Cutover'!$C$6:$C$63,MATCH(9,'Gantt Cutover'!$AY$6:$AY$63,0)),"") | F22: =IFERROR(INDEX('Gantt Cutover'!$G$6:$G$63,MATCH(9,'Gantt Cutover'!$AY$6:$AY$63,0)),"") | G22: =IFERROR(INDEX('Equipo y Calendario'!$B$5:$B$24,MATCH(F22,'Equipo y Calendario'!$A$5:$A$24,0)),"") | H22: =IFERROR(INDEX('Gantt Cutover'!$H$6:$H$63,MATCH(9,'Gantt Cutover'!$AY$6:$AY$63,0)),"") | I22: =IFERROR(INDEX('Gantt Cutover'!$I$6:$I$63,MATCH(9,'Gantt Cutover'!$AY$6:$AY$63,0)),"") | J22: =IFERROR(INDEX('Gantt Cutover'!$J$6:$J$63,MATCH(9,'Gantt Cutover'!$AY$6:$AY$63,0)),"") | K22: =IFERROR(INDEX('Gantt Cutover'!$K$6:$K$63,MATCH(9,'Gantt Cutover'!$AY$6:$AY$63,0)),"") | L22: =IFERROR(INDEX('Gantt Cutover'!$M$6:$M$63,MATCH(9,'Gantt Cutover'!$AY$6:$AY$63,0)),"")
B23: 10 | C23: =IFERROR(INDEX('Gantt Cutover'!$A$6:$A$63,MATCH(10,'Gantt Cutover'!$AY$6:$AY$63,0)),"") | D23: =IFERROR(INDEX('Gantt Cutover'!$B$6:$B$63,MATCH(10,'Gantt Cutover'!$AY$6:$AY$63,0)),"") | E23: =IFERROR(INDEX('Gantt Cutover'!$C$6:$C$63,MATCH(10,'Gantt Cutover'!$AY$6:$AY$63,0)),"") | F23: =IFERROR(INDEX('Gantt Cutover'!$G$6:$G$63,MATCH(10,'Gantt Cutover'!$AY$6:$AY$63,0)),"") | G23: =IFERROR(INDEX('Equipo y Calendario'!$B$5:$B$24,MATCH(F23,'Equipo y Calendario'!$A$5:$A$24,0)),"") | H23: =IFERROR(INDEX('Gantt Cutover'!$H$6:$H$63,MATCH(10,'Gantt Cutover'!$AY$6:$AY$63,0)),"") | I23: =IFERROR(INDEX('Gantt Cutover'!$I$6:$I$63,MATCH(10,'Gantt Cutover'!$AY$6:$AY$63,0)),"") | J23: =IFERROR(INDEX('Gantt Cutover'!$J$6:$J$63,MATCH(10,'Gantt Cutover'!$AY$6:$AY$63,0)),"") | K23: =IFERROR(INDEX('Gantt Cutover'!$K$6:$K$63,MATCH(10,'Gantt Cutover'!$AY$6:$AY$63,0)),"") | L23: =IFERROR(INDEX('Gantt Cutover'!$M$6:$M$63,MATCH(10,'Gantt Cutover'!$AY$6:$AY$63,0)),"")
B24: 11 | C24: =IFERROR(INDEX('Gantt Cutover'!$A$6:$A$63,MATCH(11,'Gantt Cutover'!$AY$6:$AY$63,0)),"") | D24: =IFERROR(INDEX('Gantt Cutover'!$B$6:$B$63,MATCH(11,'Gantt Cutover'!$AY$6:$AY$63,0)),"") | E24: =IFERROR(INDEX('Gantt Cutover'!$C$6:$C$63,MATCH(11,'Gantt Cutover'!$AY$6:$AY$63,0)),"") | F24: =IFERROR(INDEX('Gantt Cutover'!$G$6:$G$63,MATCH(11,'Gantt Cutover'!$AY$6:$AY$63,0)),"") | G24: =IFERROR(INDEX('Equipo y Calendario'!$B$5:$B$24,MATCH(F24,'Equipo y Calendario'!$A$5:$A$24,0)),"") | H24: =IFERROR(INDEX('Gantt Cutover'!$H$6:$H$63,MATCH(11,'Gantt Cutover'!$AY$6:$AY$63,0)),"") | I24: =IFERROR(INDEX('Gantt Cutover'!$I$6:$I$63,MATCH(11,'Gantt Cutover'!$AY$6:$AY$63,0)),"") | J24: =IFERROR(INDEX('Gantt Cutover'!$J$6:$J$63,MATCH(11,'Gantt Cutover'!$AY$6:$AY$63,0)),"") | K24: =IFERROR(INDEX('Gantt Cutover'!$K$6:$K$63,MATCH(11,'Gantt Cutover'!$AY$6:$AY$63,0)),"") | L24: =IFERROR(INDEX('Gantt Cutover'!$M$6:$M$63,MATCH(11,'Gantt Cutover'!$AY$6:$AY$63,0)),"")
B25: 12 | C25: =IFERROR(INDEX('Gantt Cutover'!$A$6:$A$63,MATCH(12,'Gantt Cutover'!$AY$6:$AY$63,0)),"") | D25: =IFERROR(INDEX('Gantt Cutover'!$B$6:$B$63,MATCH(12,'Gantt Cutover'!$AY$6:$AY$63,0)),"") | E25: =IFERROR(INDEX('Gantt Cutover'!$C$6:$C$63,MATCH(12,'Gantt Cutover'!$AY$6:$AY$63,0)),"") | F25: =IFERROR(INDEX('Gantt Cutover'!$G$6:$G$63,MATCH(12,'Gantt Cutover'!$AY$6:$AY$63,0)),"") | G25: =IFERROR(INDEX('Equipo y Calendario'!$B$5:$B$24,MATCH(F25,'Equipo y Calendario'!$A$5:$A$24,0)),"") | H25: =IFERROR(INDEX('Gantt Cutover'!$H$6:$H$63,MATCH(12,'Gantt Cutover'!$AY$6:$AY$63,0)),"") | I25: =IFERROR(INDEX('Gantt Cutover'!$I$6:$I$63,MATCH(12,'Gantt Cutover'!$AY$6:$AY$63,0)),"") | J25: =IFERROR(INDEX('Gantt Cutover'!$J$6:$J$63,MATCH(12,'Gantt Cutover'!$AY$6:$AY$63,0)),"") | K25: =IFERROR(INDEX('Gantt Cutover'!$K$6:$K$63,MATCH(12,'Gantt Cutover'!$AY$6:$AY$63,0)),"") | L25: =IFERROR(INDEX('Gantt Cutover'!$M$6:$M$63,MATCH(12,'Gantt Cutover'!$AY$6:$AY$63,0)),"")
B26: 13 | C26: =IFERROR(INDEX('Gantt Cutover'!$A$6:$A$63,MATCH(13,'Gantt Cutover'!$AY$6:$AY$63,0)),"") | D26: =IFERROR(INDEX('Gantt Cutover'!$B$6:$B$63,MATCH(13,'Gantt Cutover'!$AY$6:$AY$63,0)),"") | E26: =IFERROR(INDEX('Gantt Cutover'!$C$6:$C$63,MATCH(13,'Gantt Cutover'!$AY$6:$AY$63,0)),"") | F26: =IFERROR(INDEX('Gantt Cutover'!$G$6:$G$63,MATCH(13,'Gantt Cutover'!$AY$6:$AY$63,0)),"") | G26: =IFERROR(INDEX('Equipo y Calendario'!$B$5:$B$24,MATCH(F26,'Equipo y Calendario'!$A$5:$A$24,0)),"") | H26: =IFERROR(INDEX('Gantt Cutover'!$H$6:$H$63,MATCH(13,'Gantt Cutover'!$AY$6:$AY$63,0)),"") | I26: =IFERROR(INDEX('Gantt Cutover'!$I$6:$I$63,MATCH(13,'Gantt Cutover'!$AY$6:$AY$63,0)),"") | J26: =IFERROR(INDEX('Gantt Cutover'!$J$6:$J$63,MATCH(13,'Gantt Cutover'!$AY$6:$AY$63,0)),"") | K26: =IFERROR(INDEX('Gantt Cutover'!$K$6:$K$63,MATCH(13,'Gantt Cutover'!$AY$6:$AY$63,0)),"") | L26: =IFERROR(INDEX('Gantt Cutover'!$M$6:$M$63,MATCH(13,'Gantt Cutover'!$AY$6:$AY$63,0)),"")
B27: 14 | C27: =IFERROR(INDEX('Gantt Cutover'!$A$6:$A$63,MATCH(14,'Gantt Cutover'!$AY$6:$AY$63,0)),"") | D27: =IFERROR(INDEX('Gantt Cutover'!$B$6:$B$63,MATCH(14,'Gantt Cutover'!$AY$6:$AY$63,0)),"") | E27: =IFERROR(INDEX('Gantt Cutover'!$C$6:$C$63,MATCH(14,'Gantt Cutover'!$AY$6:$AY$63,0)),"") | F27: =IFERROR(INDEX('Gantt Cutover'!$G$6:$G$63,MATCH(14,'Gantt Cutover'!$AY$6:$AY$63,0)),"") | G27: =IFERROR(INDEX('Equipo y Calendario'!$B$5:$B$24,MATCH(F27,'Equipo y Calendario'!$A$5:$A$24,0)),"") | H27: =IFERROR(INDEX('Gantt Cutover'!$H$6:$H$63,MATCH(14,'Gantt Cutover'!$AY$6:$AY$63,0)),"") | I27: =IFERROR(INDEX('Gantt Cutover'!$I$6:$I$63,MATCH(14,'Gantt Cutover'!$AY$6:$AY$63,0)),"") | J27: =IFERROR(INDEX('Gantt Cutover'!$J$6:$J$63,MATCH(14,'Gantt Cutover'!$AY$6:$AY$63,0)),"") | K27: =IFERROR(INDEX('Gantt Cutover'!$K$6:$K$63,MATCH(14,'Gantt Cutover'!$AY$6:$AY$63,0)),"") | L27: =IFERROR(INDEX('Gantt Cutover'!$M$6:$M$63,MATCH(14,'Gantt Cutover'!$AY$6:$AY$63,0)),"")
B28: 15 | C28: =IFERROR(INDEX('Gantt Cutover'!$A$6:$A$63,MATCH(15,'Gantt Cutover'!$AY$6:$AY$63,0)),"") | D28: =IFERROR(INDEX('Gantt Cutover'!$B$6:$B$63,MATCH(15,'Gantt Cutover'!$AY$6:$AY$63,0)),"") | E28: =IFERROR(INDEX('Gantt Cutover'!$C$6:$C$63,MATCH(15,'Gantt Cutover'!$AY$6:$AY$63,0)),"") | F28: =IFERROR(INDEX('Gantt Cutover'!$G$6:$G$63,MATCH(15,'Gantt Cutover'!$AY$6:$AY$63,0)),"") | G28: =IFERROR(INDEX('Equipo y Calendario'!$B$5:$B$24,MATCH(F28,'Equipo y Calendario'!$A$5:$A$24,0)),"") | H28: =IFERROR(INDEX('Gantt Cutover'!$H$6:$H$63,MATCH(15,'Gantt Cutover'!$AY$6:$AY$63,0)),"") | I28: =IFERROR(INDEX('Gantt Cutover'!$I$6:$I$63,MATCH(15,'Gantt Cutover'!$AY$6:$AY$63,0)),"") | J28: =IFERROR(INDEX('Gantt Cutover'!$J$6:$J$63,MATCH(15,'Gantt Cutover'!$AY$6:$AY$63,0)),"") | K28: =IFERROR(INDEX('Gantt Cutover'!$K$6:$K$63,MATCH(15,'Gantt Cutover'!$AY$6:$AY$63,0)),"") | L28: =IFERROR(INDEX('Gantt Cutover'!$M$6:$M$63,MATCH(15,'Gantt Cutover'!$AY$6:$AY$63,0)),"")
B29: 16 | C29: =IFERROR(INDEX('Gantt Cutover'!$A$6:$A$63,MATCH(16,'Gantt Cutover'!$AY$6:$AY$63,0)),"") | D29: =IFERROR(INDEX('Gantt Cutover'!$B$6:$B$63,MATCH(16,'Gantt Cutover'!$AY$6:$AY$63,0)),"") | E29: =IFERROR(INDEX('Gantt Cutover'!$C$6:$C$63,MATCH(16,'Gantt Cutover'!$AY$6:$AY$63,0)),"") | F29: =IFERROR(INDEX('Gantt Cutover'!$G$6:$G$63,MATCH(16,'Gantt Cutover'!$AY$6:$AY$63,0)),"") | G29: =IFERROR(INDEX('Equipo y Calendario'!$B$5:$B$24,MATCH(F29,'Equipo y Calendario'!$A$5:$A$24,0)),"") | H29: =IFERROR(INDEX('Gantt Cutover'!$H$6:$H$63,MATCH(16,'Gantt Cutover'!$AY$6:$AY$63,0)),"") | I29: =IFERROR(INDEX('Gantt Cutover'!$I$6:$I$63,MATCH(16,'Gantt Cutover'!$AY$6:$AY$63,0)),"") | J29: =IFERROR(INDEX('Gantt Cutover'!$J$6:$J$63,MATCH(16,'Gantt Cutover'!$AY$6:$AY$63,0)),"") | K29: =IFERROR(INDEX('Gantt Cutover'!$K$6:$K$63,MATCH(16,'Gantt Cutover'!$AY$6:$AY$63,0)),"") | L29: =IFERROR(INDEX('Gantt Cutover'!$M$6:$M$63,MATCH(16,'Gantt Cutover'!$AY$6:$AY$63,0)),"")
B30: 17 | C30: =IFERROR(INDEX('Gantt Cutover'!$A$6:$A$63,MATCH(17,'Gantt Cutover'!$AY$6:$AY$63,0)),"") | D30: =IFERROR(INDEX('Gantt Cutover'!$B$6:$B$63,MATCH(17,'Gantt Cutover'!$AY$6:$AY$63,0)),"") | E30: =IFERROR(INDEX('Gantt Cutover'!$C$6:$C$63,MATCH(17,'Gantt Cutover'!$AY$6:$AY$63,0)),"") | F30: =IFERROR(INDEX('Gantt Cutover'!$G$6:$G$63,MATCH(17,'Gantt Cutover'!$AY$6:$AY$63,0)),"") | G30: =IFERROR(INDEX('Equipo y Calendario'!$B$5:$B$24,MATCH(F30,'Equipo y Calendario'!$A$5:$A$24,0)),"") | H30: =IFERROR(INDEX('Gantt Cutover'!$H$6:$H$63,MATCH(17,'Gantt Cutover'!$AY$6:$AY$63,0)),"") | I30: =IFERROR(INDEX('Gantt Cutover'!$I$6:$I$63,MATCH(17,'Gantt Cutover'!$AY$6:$AY$63,0)),"") | J30: =IFERROR(INDEX('Gantt Cutover'!$J$6:$J$63,MATCH(17,'Gantt Cutover'!$AY$6:$AY$63,0)),"") | K30: =IFERROR(INDEX('Gantt Cutover'!$K$6:$K$63,MATCH(17,'Gantt Cutover'!$AY$6:$AY$63,0)),"") | L30: =IFERROR(INDEX('Gantt Cutover'!$M$6:$M$63,MATCH(17,'Gantt Cutover'!$AY$6:$AY$63,0)),"")
B31: 18 | C31: =IFERROR(INDEX('Gantt Cutover'!$A$6:$A$63,MATCH(18,'Gantt Cutover'!$AY$6:$AY$63,0)),"") | D31: =IFERROR(INDEX('Gantt Cutover'!$B$6:$B$63,MATCH(18,'Gantt Cutover'!$AY$6:$AY$63,0)),"") | E31: =IFERROR(INDEX('Gantt Cutover'!$C$6:$C$63,MATCH(18,'Gantt Cutover'!$AY$6:$AY$63,0)),"") | F31: =IFERROR(INDEX('Gantt Cutover'!$G$6:$G$63,MATCH(18,'Gantt Cutover'!$AY$6:$AY$63,0)),"") | G31: =IFERROR(INDEX('Equipo y Calendario'!$B$5:$B$24,MATCH(F31,'Equipo y Calendario'!$A$5:$A$24,0)),"") | H31: =IFERROR(INDEX('Gantt Cutover'!$H$6:$H$63,MATCH(18,'Gantt Cutover'!$AY$6:$AY$63,0)),"") | I31: =IFERROR(INDEX('Gantt Cutover'!$I$6:$I$63,MATCH(18,'Gantt Cutover'!$AY$6:$AY$63,0)),"") | J31: =IFERROR(INDEX('Gantt Cutover'!$J$6:$J$63,MATCH(18,'Gantt Cutover'!$AY$6:$AY$63,0)),"") | K31: =IFERROR(INDEX('Gantt Cutover'!$K$6:$K$63,MATCH(18,'Gantt Cutover'!$AY$6:$AY$63,0)),"") | L31: =IFERROR(INDEX('Gantt Cutover'!$M$6:$M$63,MATCH(18,'Gantt Cutover'!$AY$6:$AY$63,0)),"")
B32: 19 | C32: =IFERROR(INDEX('Gantt Cutover'!$A$6:$A$63,MATCH(19,'Gantt Cutover'!$AY$6:$AY$63,0)),"") | D32: =IFERROR(INDEX('Gantt Cutover'!$B$6:$B$63,MATCH(19,'Gantt Cutover'!$AY$6:$AY$63,0)),"") | E32: =IFERROR(INDEX('Gantt Cutover'!$C$6:$C$63,MATCH(19,'Gantt Cutover'!$AY$6:$AY$63,0)),"") | F32: =IFERROR(INDEX('Gantt Cutover'!$G$6:$G$63,MATCH(19,'Gantt Cutover'!$AY$6:$AY$63,0)),"") | G32: =IFERROR(INDEX('Equipo y Calendario'!$B$5:$B$24,MATCH(F32,'Equipo y Calendario'!$A$5:$A$24,0)),"") | H32: =IFERROR(INDEX('Gantt Cutover'!$H$6:$H$63,MATCH(19,'Gantt Cutover'!$AY$6:$AY$63,0)),"") | I32: =IFERROR(INDEX('Gantt Cutover'!$I$6:$I$63,MATCH(19,'Gantt Cutover'!$AY$6:$AY$63,0)),"") | J32: =IFERROR(INDEX('Gantt Cutover'!$J$6:$J$63,MATCH(19,'Gantt Cutover'!$AY$6:$AY$63,0)),"") | K32: =IFERROR(INDEX('Gantt Cutover'!$K$6:$K$63,MATCH(19,'Gantt Cutover'!$AY$6:$AY$63,0)),"") | L32: =IFERROR(INDEX('Gantt Cutover'!$M$6:$M$63,MATCH(19,'Gantt Cutover'!$AY$6:$AY$63,0)),"")
B33: 20 | C33: =IFERROR(INDEX('Gantt Cutover'!$A$6:$A$63,MATCH(20,'Gantt Cutover'!$AY$6:$AY$63,0)),"") | D33: =IFERROR(INDEX('Gantt Cutover'!$B$6:$B$63,MATCH(20,'Gantt Cutover'!$AY$6:$AY$63,0)),"") | E33: =IFERROR(INDEX('Gantt Cutover'!$C$6:$C$63,MATCH(20,'Gantt Cutover'!$AY$6:$AY$63,0)),"") | F33: =IFERROR(INDEX('Gantt Cutover'!$G$6:$G$63,MATCH(20,'Gantt Cutover'!$AY$6:$AY$63,0)),"") | G33: =IFERROR(INDEX('Equipo y Calendario'!$B$5:$B$24,MATCH(F33,'Equipo y Calendario'!$A$5:$A$24,0)),"") | H33: =IFERROR(INDEX('Gantt Cutover'!$H$6:$H$63,MATCH(20,'Gantt Cutover'!$AY$6:$AY$63,0)),"") | I33: =IFERROR(INDEX('Gantt Cutover'!$I$6:$I$63,MATCH(20,'Gantt Cutover'!$AY$6:$AY$63,0)),"") | J33: =IFERROR(INDEX('Gantt Cutover'!$J$6:$J$63,MATCH(20,'Gantt Cutover'!$AY$6:$AY$63,0)),"") | K33: =IFERROR(INDEX('Gantt Cutover'!$K$6:$K$63,MATCH(20,'Gantt Cutover'!$AY$6:$AY$63,0)),"") | L33: =IFERROR(INDEX('Gantt Cutover'!$M$6:$M$63,MATCH(20,'Gantt Cutover'!$AY$6:$AY$63,0)),"")
B34: 21 | C34: =IFERROR(INDEX('Gantt Cutover'!$A$6:$A$63,MATCH(21,'Gantt Cutover'!$AY$6:$AY$63,0)),"") | D34: =IFERROR(INDEX('Gantt Cutover'!$B$6:$B$63,MATCH(21,'Gantt Cutover'!$AY$6:$AY$63,0)),"") | E34: =IFERROR(INDEX('Gantt Cutover'!$C$6:$C$63,MATCH(21,'Gantt Cutover'!$AY$6:$AY$63,0)),"") | F34: =IFERROR(INDEX('Gantt Cutover'!$G$6:$G$63,MATCH(21,'Gantt Cutover'!$AY$6:$AY$63,0)),"") | G34: =IFERROR(INDEX('Equipo y Calendario'!$B$5:$B$24,MATCH(F34,'Equipo y Calendario'!$A$5:$A$24,0)),"") | H34: =IFERROR(INDEX('Gantt Cutover'!$H$6:$H$63,MATCH(21,'Gantt Cutover'!$AY$6:$AY$63,0)),"") | I34: =IFERROR(INDEX('Gantt Cutover'!$I$6:$I$63,MATCH(21,'Gantt Cutover'!$AY$6:$AY$63,0)),"") | J34: =IFERROR(INDEX('Gantt Cutover'!$J$6:$J$63,MATCH(21,'Gantt Cutover'!$AY$6:$AY$63,0)),"") | K34: =IFERROR(INDEX('Gantt Cutover'!$K$6:$K$63,MATCH(21,'Gantt Cutover'!$AY$6:$AY$63,0)),"") | L34: =IFERROR(INDEX('Gantt Cutover'!$M$6:$M$63,MATCH(21,'Gantt Cutover'!$AY$6:$AY$63,0)),"")
B35: 22 | C35: =IFERROR(INDEX('Gantt Cutover'!$A$6:$A$63,MATCH(22,'Gantt Cutover'!$AY$6:$AY$63,0)),"") | D35: =IFERROR(INDEX('Gantt Cutover'!$B$6:$B$63,MATCH(22,'Gantt Cutover'!$AY$6:$AY$63,0)),"") | E35: =IFERROR(INDEX('Gantt Cutover'!$C$6:$C$63,MATCH(22,'Gantt Cutover'!$AY$6:$AY$63,0)),"") | F35: =IFERROR(INDEX('Gantt Cutover'!$G$6:$G$63,MATCH(22,'Gantt Cutover'!$AY$6:$AY$63,0)),"") | G35: =IFERROR(INDEX('Equipo y Calendario'!$B$5:$B$24,MATCH(F35,'Equipo y Calendario'!$A$5:$A$24,0)),"") | H35: =IFERROR(INDEX('Gantt Cutover'!$H$6:$H$63,MATCH(22,'Gantt Cutover'!$AY$6:$AY$63,0)),"") | I35: =IFERROR(INDEX('Gantt Cutover'!$I$6:$I$63,MATCH(22,'Gantt Cutover'!$AY$6:$AY$63,0)),"") | J35: =IFERROR(INDEX('Gantt Cutover'!$J$6:$J$63,MATCH(22,'Gantt Cutover'!$AY$6:$AY$63,0)),"") | K35: =IFERROR(INDEX('Gantt Cutover'!$K$6:$K$63,MATCH(22,'Gantt Cutover'!$AY$6:$AY$63,0)),"") | L35: =IFERROR(INDEX('Gantt Cutover'!$M$6:$M$63,MATCH(22,'Gantt Cutover'!$AY$6:$AY$63,0)),"")
B36: 23 | C36: =IFERROR(INDEX('Gantt Cutover'!$A$6:$A$63,MATCH(23,'Gantt Cutover'!$AY$6:$AY$63,0)),"") | D36: =IFERROR(INDEX('Gantt Cutover'!$B$6:$B$63,MATCH(23,'Gantt Cutover'!$AY$6:$AY$63,0)),"") | E36: =IFERROR(INDEX('Gantt Cutover'!$C$6:$C$63,MATCH(23,'Gantt Cutover'!$AY$6:$AY$63,0)),"") | F36: =IFERROR(INDEX('Gantt Cutover'!$G$6:$G$63,MATCH(23,'Gantt Cutover'!$AY$6:$AY$63,0)),"") | G36: =IFERROR(INDEX('Equipo y Calendario'!$B$5:$B$24,MATCH(F36,'Equipo y Calendario'!$A$5:$A$24,0)),"") | H36: =IFERROR(INDEX('Gantt Cutover'!$H$6:$H$63,MATCH(23,'Gantt Cutover'!$AY$6:$AY$63,0)),"") | I36: =IFERROR(INDEX('Gantt Cutover'!$I$6:$I$63,MATCH(23,'Gantt Cutover'!$AY$6:$AY$63,0)),"") | J36: =IFERROR(INDEX('Gantt Cutover'!$J$6:$J$63,MATCH(23,'Gantt Cutover'!$AY$6:$AY$63,0)),"") | K36: =IFERROR(INDEX('Gantt Cutover'!$K$6:$K$63,MATCH(23,'Gantt Cutover'!$AY$6:$AY$63,0)),"") | L36: =IFERROR(INDEX('Gantt Cutover'!$M$6:$M$63,MATCH(23,'Gantt Cutover'!$AY$6:$AY$63,0)),"")
B37: 24 | C37: =IFERROR(INDEX('Gantt Cutover'!$A$6:$A$63,MATCH(24,'Gantt Cutover'!$AY$6:$AY$63,0)),"") | D37: =IFERROR(INDEX('Gantt Cutover'!$B$6:$B$63,MATCH(24,'Gantt Cutover'!$AY$6:$AY$63,0)),"") | E37: =IFERROR(INDEX('Gantt Cutover'!$C$6:$C$63,MATCH(24,'Gantt Cutover'!$AY$6:$AY$63,0)),"") | F37: =IFERROR(INDEX('Gantt Cutover'!$G$6:$G$63,MATCH(24,'Gantt Cutover'!$AY$6:$AY$63,0)),"") | G37: =IFERROR(INDEX('Equipo y Calendario'!$B$5:$B$24,MATCH(F37,'Equipo y Calendario'!$A$5:$A$24,0)),"") | H37: =IFERROR(INDEX('Gantt Cutover'!$H$6:$H$63,MATCH(24,'Gantt Cutover'!$AY$6:$AY$63,0)),"") | I37: =IFERROR(INDEX('Gantt Cutover'!$I$6:$I$63,MATCH(24,'Gantt Cutover'!$AY$6:$AY$63,0)),"") | J37: =IFERROR(INDEX('Gantt Cutover'!$J$6:$J$63,MATCH(24,'Gantt Cutover'!$AY$6:$AY$63,0)),"") | K37: =IFERROR(INDEX('Gantt Cutover'!$K$6:$K$63,MATCH(24,'Gantt Cutover'!$AY$6:$AY$63,0)),"") | L37: =IFERROR(INDEX('Gantt Cutover'!$M$6:$M$63,MATCH(24,'Gantt Cutover'!$AY$6:$AY$63,0)),"")
B38: 25 | C38: =IFERROR(INDEX('Gantt Cutover'!$A$6:$A$63,MATCH(25,'Gantt Cutover'!$AY$6:$AY$63,0)),"") | D38: =IFERROR(INDEX('Gantt Cutover'!$B$6:$B$63,MATCH(25,'Gantt Cutover'!$AY$6:$AY$63,0)),"") | E38: =IFERROR(INDEX('Gantt Cutover'!$C$6:$C$63,MATCH(25,'Gantt Cutover'!$AY$6:$AY$63,0)),"") | F38: =IFERROR(INDEX('Gantt Cutover'!$G$6:$G$63,MATCH(25,'Gantt Cutover'!$AY$6:$AY$63,0)),"") | G38: =IFERROR(INDEX('Equipo y Calendario'!$B$5:$B$24,MATCH(F38,'Equipo y Calendario'!$A$5:$A$24,0)),"") | H38: =IFERROR(INDEX('Gantt Cutover'!$H$6:$H$63,MATCH(25,'Gantt Cutover'!$AY$6:$AY$63,0)),"") | I38: =IFERROR(INDEX('Gantt Cutover'!$I$6:$I$63,MATCH(25,'Gantt Cutover'!$AY$6:$AY$63,0)),"") | J38: =IFERROR(INDEX('Gantt Cutover'!$J$6:$J$63,MATCH(25,'Gantt Cutover'!$AY$6:$AY$63,0)),"") | K38: =IFERROR(INDEX('Gantt Cutover'!$K$6:$K$63,MATCH(25,'Gantt Cutover'!$AY$6:$AY$63,0)),"") | L38: =IFERROR(INDEX('Gantt Cutover'!$M$6:$M$63,MATCH(25,'Gantt Cutover'!$AY$6:$AY$63,0)),"")
B39: 26 | C39: =IFERROR(INDEX('Gantt Cutover'!$A$6:$A$63,MATCH(26,'Gantt Cutover'!$AY$6:$AY$63,0)),"") | D39: =IFERROR(INDEX('Gantt Cutover'!$B$6:$B$63,MATCH(26,'Gantt Cutover'!$AY$6:$AY$63,0)),"") | E39: =IFERROR(INDEX('Gantt Cutover'!$C$6:$C$63,MATCH(26,'Gantt Cutover'!$AY$6:$AY$63,0)),"") | F39: =IFERROR(INDEX('Gantt Cutover'!$G$6:$G$63,MATCH(26,'Gantt Cutover'!$AY$6:$AY$63,0)),"") | G39: =IFERROR(INDEX('Equipo y Calendario'!$B$5:$B$24,MATCH(F39,'Equipo y Calendario'!$A$5:$A$24,0)),"") | H39: =IFERROR(INDEX('Gantt Cutover'!$H$6:$H$63,MATCH(26,'Gantt Cutover'!$AY$6:$AY$63,0)),"") | I39: =IFERROR(INDEX('Gantt Cutover'!$I$6:$I$63,MATCH(26,'Gantt Cutover'!$AY$6:$AY$63,0)),"") | J39: =IFERROR(INDEX('Gantt Cutover'!$J$6:$J$63,MATCH(26,'Gantt Cutover'!$AY$6:$AY$63,0)),"") | K39: =IFERROR(INDEX('Gantt Cutover'!$K$6:$K$63,MATCH(26,'Gantt Cutover'!$AY$6:$AY$63,0)),"") | L39: =IFERROR(INDEX('Gantt Cutover'!$M$6:$M$63,MATCH(26,'Gantt Cutover'!$AY$6:$AY$63,0)),"")
B40: 27 | C40: =IFERROR(INDEX('Gantt Cutover'!$A$6:$A$63,MATCH(27,'Gantt Cutover'!$AY$6:$AY$63,0)),"") | D40: =IFERROR(INDEX('Gantt Cutover'!$B$6:$B$63,MATCH(27,'Gantt Cutover'!$AY$6:$AY$63,0)),"") | E40: =IFERROR(INDEX('Gantt Cutover'!$C$6:$C$63,MATCH(27,'Gantt Cutover'!$AY$6:$AY$63,0)),"") | F40: =IFERROR(INDEX('Gantt Cutover'!$G$6:$G$63,MATCH(27,'Gantt Cutover'!$AY$6:$AY$63,0)),"") | G40: =IFERROR(INDEX('Equipo y Calendario'!$B$5:$B$24,MATCH(F40,'Equipo y Calendario'!$A$5:$A$24,0)),"") | H40: =IFERROR(INDEX('Gantt Cutover'!$H$6:$H$63,MATCH(27,'Gantt Cutover'!$AY$6:$AY$63,0)),"") | I40: =IFERROR(INDEX('Gantt Cutover'!$I$6:$I$63,MATCH(27,'Gantt Cutover'!$AY$6:$AY$63,0)),"") | J40: =IFERROR(INDEX('Gantt Cutover'!$J$6:$J$63,MATCH(27,'Gantt Cutover'!$AY$6:$AY$63,0)),"") | K40: =IFERROR(INDEX('Gantt Cutover'!$K$6:$K$63,MATCH(27,'Gantt Cutover'!$AY$6:$AY$63,0)),"") | L40: =IFERROR(INDEX('Gantt Cutover'!$M$6:$M$63,MATCH(27,'Gantt Cutover'!$AY$6:$AY$63,0)),"")
B41: 28 | C41: =IFERROR(INDEX('Gantt Cutover'!$A$6:$A$63,MATCH(28,'Gantt Cutover'!$AY$6:$AY$63,0)),"") | D41: =IFERROR(INDEX('Gantt Cutover'!$B$6:$B$63,MATCH(28,'Gantt Cutover'!$AY$6:$AY$63,0)),"") | E41: =IFERROR(INDEX('Gantt Cutover'!$C$6:$C$63,MATCH(28,'Gantt Cutover'!$AY$6:$AY$63,0)),"") | F41: =IFERROR(INDEX('Gantt Cutover'!$G$6:$G$63,MATCH(28,'Gantt Cutover'!$AY$6:$AY$63,0)),"") | G41: =IFERROR(INDEX('Equipo y Calendario'!$B$5:$B$24,MATCH(F41,'Equipo y Calendario'!$A$5:$A$24,0)),"") | H41: =IFERROR(INDEX('Gantt Cutover'!$H$6:$H$63,MATCH(28,'Gantt Cutover'!$AY$6:$AY$63,0)),"") | I41: =IFERROR(INDEX('Gantt Cutover'!$I$6:$I$63,MATCH(28,'Gantt Cutover'!$AY$6:$AY$63,0)),"") | J41: =IFERROR(INDEX('Gantt Cutover'!$J$6:$J$63,MATCH(28,'Gantt Cutover'!$AY$6:$AY$63,0)),"") | K41: =IFERROR(INDEX('Gantt Cutover'!$K$6:$K$63,MATCH(28,'Gantt Cutover'!$AY$6:$AY$63,0)),"") | L41: =IFERROR(INDEX('Gantt Cutover'!$M$6:$M$63,MATCH(28,'Gantt Cutover'!$AY$6:$AY$63,0)),"")
B42: 29 | C42: =IFERROR(INDEX('Gantt Cutover'!$A$6:$A$63,MATCH(29,'Gantt Cutover'!$AY$6:$AY$63,0)),"") | D42: =IFERROR(INDEX('Gantt Cutover'!$B$6:$B$63,MATCH(29,'Gantt Cutover'!$AY$6:$AY$63,0)),"") | E42: =IFERROR(INDEX('Gantt Cutover'!$C$6:$C$63,MATCH(29,'Gantt Cutover'!$AY$6:$AY$63,0)),"") | F42: =IFERROR(INDEX('Gantt Cutover'!$G$6:$G$63,MATCH(29,'Gantt Cutover'!$AY$6:$AY$63,0)),"") | G42: =IFERROR(INDEX('Equipo y Calendario'!$B$5:$B$24,MATCH(F42,'Equipo y Calendario'!$A$5:$A$24,0)),"") | H42: =IFERROR(INDEX('Gantt Cutover'!$H$6:$H$63,MATCH(29,'Gantt Cutover'!$AY$6:$AY$63,0)),"") | I42: =IFERROR(INDEX('Gantt Cutover'!$I$6:$I$63,MATCH(29,'Gantt Cutover'!$AY$6:$AY$63,0)),"") | J42: =IFERROR(INDEX('Gantt Cutover'!$J$6:$J$63,MATCH(29,'Gantt Cutover'!$AY$6:$AY$63,0)),"") | K42: =IFERROR(INDEX('Gantt Cutover'!$K$6:$K$63,MATCH(29,'Gantt Cutover'!$AY$6:$AY$63,0)),"") | L42: =IFERROR(INDEX('Gantt Cutover'!$M$6:$M$63,MATCH(29,'Gantt Cutover'!$AY$6:$AY$63,0)),"")
B43: 30 | C43: =IFERROR(INDEX('Gantt Cutover'!$A$6:$A$63,MATCH(30,'Gantt Cutover'!$AY$6:$AY$63,0)),"") | D43: =IFERROR(INDEX('Gantt Cutover'!$B$6:$B$63,MATCH(30,'Gantt Cutover'!$AY$6:$AY$63,0)),"") | E43: =IFERROR(INDEX('Gantt Cutover'!$C$6:$C$63,MATCH(30,'Gantt Cutover'!$AY$6:$AY$63,0)),"") | F43: =IFERROR(INDEX('Gantt Cutover'!$G$6:$G$63,MATCH(30,'Gantt Cutover'!$AY$6:$AY$63,0)),"") | G43: =IFERROR(INDEX('Equipo y Calendario'!$B$5:$B$24,MATCH(F43,'Equipo y Calendario'!$A$5:$A$24,0)),"") | H43: =IFERROR(INDEX('Gantt Cutover'!$H$6:$H$63,MATCH(30,'Gantt Cutover'!$AY$6:$AY$63,0)),"") | I43: =IFERROR(INDEX('Gantt Cutover'!$I$6:$I$63,MATCH(30,'Gantt Cutover'!$AY$6:$AY$63,0)),"") | J43: =IFERROR(INDEX('Gantt Cutover'!$J$6:$J$63,MATCH(30,'Gantt Cutover'!$AY$6:$AY$63,0)),"") | K43: =IFERROR(INDEX('Gantt Cutover'!$K$6:$K$63,MATCH(30,'Gantt Cutover'!$AY$6:$AY$63,0)),"") | L43: =IFERROR(INDEX('Gantt Cutover'!$M$6:$M$63,MATCH(30,'Gantt Cutover'!$AY$6:$AY$63,0)),"")
B45: Actividades vencidas (fin anterior a la fecha y no finalizadas)
B46: # | C46: ID | D46: Fase | E46: Actividad / hito | F46: Responsable | G46: Nombre responsable | H46: Participantes | I46: Modalidad | J46: Inicio | K46: Fin | L46: Estado
B47: 1 | C47: =IFERROR(INDEX('Gantt Cutover'!$A$6:$A$63,MATCH(1,'Gantt Cutover'!$BA$6:$BA$63,0)),"") | D47: =IFERROR(INDEX('Gantt Cutover'!$B$6:$B$63,MATCH(1,'Gantt Cutover'!$BA$6:$BA$63,0)),"") | E47: =IFERROR(INDEX('Gantt Cutover'!$C$6:$C$63,MATCH(1,'Gantt Cutover'!$BA$6:$BA$63,0)),"") | F47: =IFERROR(INDEX('Gantt Cutover'!$G$6:$G$63,MATCH(1,'Gantt Cutover'!$BA$6:$BA$63,0)),"") | G47: =IFERROR(INDEX('Equipo y Calendario'!$B$5:$B$24,MATCH(F47,'Equipo y Calendario'!$A$5:$A$24,0)),"") | H47: =IFERROR(INDEX('Gantt Cutover'!$H$6:$H$63,MATCH(1,'Gantt Cutover'!$BA$6:$BA$63,0)),"") | I47: =IFERROR(INDEX('Gantt Cutover'!$I$6:$I$63,MATCH(1,'Gantt Cutover'!$BA$6:$BA$63,0)),"") | J47: =IFERROR(INDEX('Gantt Cutover'!$J$6:$J$63,MATCH(1,'Gantt Cutover'!$BA$6:$BA$63,0)),"") | K47: =IFERROR(INDEX('Gantt Cutover'!$K$6:$K$63,MATCH(1,'Gantt Cutover'!$BA$6:$BA$63,0)),"") | L47: =IFERROR(INDEX('Gantt Cutover'!$M$6:$M$63,MATCH(1,'Gantt Cutover'!$BA$6:$BA$63,0)),"")
B48: 2 | C48: =IFERROR(INDEX('Gantt Cutover'!$A$6:$A$63,MATCH(2,'Gantt Cutover'!$BA$6:$BA$63,0)),"") | D48: =IFERROR(INDEX('Gantt Cutover'!$B$6:$B$63,MATCH(2,'Gantt Cutover'!$BA$6:$BA$63,0)),"") | E48: =IFERROR(INDEX('Gantt Cutover'!$C$6:$C$63,MATCH(2,'Gantt Cutover'!$BA$6:$BA$63,0)),"") | F48: =IFERROR(INDEX('Gantt Cutover'!$G$6:$G$63,MATCH(2,'Gantt Cutover'!$BA$6:$BA$63,0)),"") | G48: =IFERROR(INDEX('Equipo y Calendario'!$B$5:$B$24,MATCH(F48,'Equipo y Calendario'!$A$5:$A$24,0)),"") | H48: =IFERROR(INDEX('Gantt Cutover'!$H$6:$H$63,MATCH(2,'Gantt Cutover'!$BA$6:$BA$63,0)),"") | I48: =IFERROR(INDEX('Gantt Cutover'!$I$6:$I$63,MATCH(2,'Gantt Cutover'!$BA$6:$BA$63,0)),"") | J48: =IFERROR(INDEX('Gantt Cutover'!$J$6:$J$63,MATCH(2,'Gantt Cutover'!$BA$6:$BA$63,0)),"") | K48: =IFERROR(INDEX('Gantt Cutover'!$K$6:$K$63,MATCH(2,'Gantt Cutover'!$BA$6:$BA$63,0)),"") | L48: =IFERROR(INDEX('Gantt Cutover'!$M$6:$M$63,MATCH(2,'Gantt Cutover'!$BA$6:$BA$63,0)),"")
B49: 3 | C49: =IFERROR(INDEX('Gantt Cutover'!$A$6:$A$63,MATCH(3,'Gantt Cutover'!$BA$6:$BA$63,0)),"") | D49: =IFERROR(INDEX('Gantt Cutover'!$B$6:$B$63,MATCH(3,'Gantt Cutover'!$BA$6:$BA$63,0)),"") | E49: =IFERROR(INDEX('Gantt Cutover'!$C$6:$C$63,MATCH(3,'Gantt Cutover'!$BA$6:$BA$63,0)),"") | F49: =IFERROR(INDEX('Gantt Cutover'!$G$6:$G$63,MATCH(3,'Gantt Cutover'!$BA$6:$BA$63,0)),"") | G49: =IFERROR(INDEX('Equipo y Calendario'!$B$5:$B$24,MATCH(F49,'Equipo y Calendario'!$A$5:$A$24,0)),"") | H49: =IFERROR(INDEX('Gantt Cutover'!$H$6:$H$63,MATCH(3,'Gantt Cutover'!$BA$6:$BA$63,0)),"") | I49: =IFERROR(INDEX('Gantt Cutover'!$I$6:$I$63,MATCH(3,'Gantt Cutover'!$BA$6:$BA$63,0)),"") | J49: =IFERROR(INDEX('Gantt Cutover'!$J$6:$J$63,MATCH(3,'Gantt Cutover'!$BA$6:$BA$63,0)),"") | K49: =IFERROR(INDEX('Gantt Cutover'!$K$6:$K$63,MATCH(3,'Gantt Cutover'!$BA$6:$BA$63,0)),"") | L49: =IFERROR(INDEX('Gantt Cutover'!$M$6:$M$63,MATCH(3,'Gantt Cutover'!$BA$6:$BA$63,0)),"")
B50: 4 | C50: =IFERROR(INDEX('Gantt Cutover'!$A$6:$A$63,MATCH(4,'Gantt Cutover'!$BA$6:$BA$63,0)),"") | D50: =IFERROR(INDEX('Gantt Cutover'!$B$6:$B$63,MATCH(4,'Gantt Cutover'!$BA$6:$BA$63,0)),"") | E50: =IFERROR(INDEX('Gantt Cutover'!$C$6:$C$63,MATCH(4,'Gantt Cutover'!$BA$6:$BA$63,0)),"") | F50: =IFERROR(INDEX('Gantt Cutover'!$G$6:$G$63,MATCH(4,'Gantt Cutover'!$BA$6:$BA$63,0)),"") | G50: =IFERROR(INDEX('Equipo y Calendario'!$B$5:$B$24,MATCH(F50,'Equipo y Calendario'!$A$5:$A$24,0)),"") | H50: =IFERROR(INDEX('Gantt Cutover'!$H$6:$H$63,MATCH(4,'Gantt Cutover'!$BA$6:$BA$63,0)),"") | I50: =IFERROR(INDEX('Gantt Cutover'!$I$6:$I$63,MATCH(4,'Gantt Cutover'!$BA$6:$BA$63,0)),"") | J50: =IFERROR(INDEX('Gantt Cutover'!$J$6:$J$63,MATCH(4,'Gantt Cutover'!$BA$6:$BA$63,0)),"") | K50: =IFERROR(INDEX('Gantt Cutover'!$K$6:$K$63,MATCH(4,'Gantt Cutover'!$BA$6:$BA$63,0)),"") | L50: =IFERROR(INDEX('Gantt Cutover'!$M$6:$M$63,MATCH(4,'Gantt Cutover'!$BA$6:$BA$63,0)),"")
B51: 5 | C51: =IFERROR(INDEX('Gantt Cutover'!$A$6:$A$63,MATCH(5,'Gantt Cutover'!$BA$6:$BA$63,0)),"") | D51: =IFERROR(INDEX('Gantt Cutover'!$B$6:$B$63,MATCH(5,'Gantt Cutover'!$BA$6:$BA$63,0)),"") | E51: =IFERROR(INDEX('Gantt Cutover'!$C$6:$C$63,MATCH(5,'Gantt Cutover'!$BA$6:$BA$63,0)),"") | F51: =IFERROR(INDEX('Gantt Cutover'!$G$6:$G$63,MATCH(5,'Gantt Cutover'!$BA$6:$BA$63,0)),"") | G51: =IFERROR(INDEX('Equipo y Calendario'!$B$5:$B$24,MATCH(F51,'Equipo y Calendario'!$A$5:$A$24,0)),"") | H51: =IFERROR(INDEX('Gantt Cutover'!$H$6:$H$63,MATCH(5,'Gantt Cutover'!$BA$6:$BA$63,0)),"") | I51: =IFERROR(INDEX('Gantt Cutover'!$I$6:$I$63,MATCH(5,'Gantt Cutover'!$BA$6:$BA$63,0)),"") | J51: =IFERROR(INDEX('Gantt Cutover'!$J$6:$J$63,MATCH(5,'Gantt Cutover'!$BA$6:$BA$63,0)),"") | K51: =IFERROR(INDEX('Gantt Cutover'!$K$6:$K$63,MATCH(5,'Gantt Cutover'!$BA$6:$BA$63,0)),"") | L51: =IFERROR(INDEX('Gantt Cutover'!$M$6:$M$63,MATCH(5,'Gantt Cutover'!$BA$6:$BA$63,0)),"")
B52: 6 | C52: =IFERROR(INDEX('Gantt Cutover'!$A$6:$A$63,MATCH(6,'Gantt Cutover'!$BA$6:$BA$63,0)),"") | D52: =IFERROR(INDEX('Gantt Cutover'!$B$6:$B$63,MATCH(6,'Gantt Cutover'!$BA$6:$BA$63,0)),"") | E52: =IFERROR(INDEX('Gantt Cutover'!$C$6:$C$63,MATCH(6,'Gantt Cutover'!$BA$6:$BA$63,0)),"") | F52: =IFERROR(INDEX('Gantt Cutover'!$G$6:$G$63,MATCH(6,'Gantt Cutover'!$BA$6:$BA$63,0)),"") | G52: =IFERROR(INDEX('Equipo y Calendario'!$B$5:$B$24,MATCH(F52,'Equipo y Calendario'!$A$5:$A$24,0)),"") | H52: =IFERROR(INDEX('Gantt Cutover'!$H$6:$H$63,MATCH(6,'Gantt Cutover'!$BA$6:$BA$63,0)),"") | I52: =IFERROR(INDEX('Gantt Cutover'!$I$6:$I$63,MATCH(6,'Gantt Cutover'!$BA$6:$BA$63,0)),"") | J52: =IFERROR(INDEX('Gantt Cutover'!$J$6:$J$63,MATCH(6,'Gantt Cutover'!$BA$6:$BA$63,0)),"") | K52: =IFERROR(INDEX('Gantt Cutover'!$K$6:$K$63,MATCH(6,'Gantt Cutover'!$BA$6:$BA$63,0)),"") | L52: =IFERROR(INDEX('Gantt Cutover'!$M$6:$M$63,MATCH(6,'Gantt Cutover'!$BA$6:$BA$63,0)),"")
B53: 7 | C53: =IFERROR(INDEX('Gantt Cutover'!$A$6:$A$63,MATCH(7,'Gantt Cutover'!$BA$6:$BA$63,0)),"") | D53: =IFERROR(INDEX('Gantt Cutover'!$B$6:$B$63,MATCH(7,'Gantt Cutover'!$BA$6:$BA$63,0)),"") | E53: =IFERROR(INDEX('Gantt Cutover'!$C$6:$C$63,MATCH(7,'Gantt Cutover'!$BA$6:$BA$63,0)),"") | F53: =IFERROR(INDEX('Gantt Cutover'!$G$6:$G$63,MATCH(7,'Gantt Cutover'!$BA$6:$BA$63,0)),"") | G53: =IFERROR(INDEX('Equipo y Calendario'!$B$5:$B$24,MATCH(F53,'Equipo y Calendario'!$A$5:$A$24,0)),"") | H53: =IFERROR(INDEX('Gantt Cutover'!$H$6:$H$63,MATCH(7,'Gantt Cutover'!$BA$6:$BA$63,0)),"") | I53: =IFERROR(INDEX('Gantt Cutover'!$I$6:$I$63,MATCH(7,'Gantt Cutover'!$BA$6:$BA$63,0)),"") | J53: =IFERROR(INDEX('Gantt Cutover'!$J$6:$J$63,MATCH(7,'Gantt Cutover'!$BA$6:$BA$63,0)),"") | K53: =IFERROR(INDEX('Gantt Cutover'!$K$6:$K$63,MATCH(7,'Gantt Cutover'!$BA$6:$BA$63,0)),"") | L53: =IFERROR(INDEX('Gantt Cutover'!$M$6:$M$63,MATCH(7,'Gantt Cutover'!$BA$6:$BA$63,0)),"")
B54: 8 | C54: =IFERROR(INDEX('Gantt Cutover'!$A$6:$A$63,MATCH(8,'Gantt Cutover'!$BA$6:$BA$63,0)),"") | D54: =IFERROR(INDEX('Gantt Cutover'!$B$6:$B$63,MATCH(8,'Gantt Cutover'!$BA$6:$BA$63,0)),"") | E54: =IFERROR(INDEX('Gantt Cutover'!$C$6:$C$63,MATCH(8,'Gantt Cutover'!$BA$6:$BA$63,0)),"") | F54: =IFERROR(INDEX('Gantt Cutover'!$G$6:$G$63,MATCH(8,'Gantt Cutover'!$BA$6:$BA$63,0)),"") | G54: =IFERROR(INDEX('Equipo y Calendario'!$B$5:$B$24,MATCH(F54,'Equipo y Calendario'!$A$5:$A$24,0)),"") | H54: =IFERROR(INDEX('Gantt Cutover'!$H$6:$H$63,MATCH(8,'Gantt Cutover'!$BA$6:$BA$63,0)),"") | I54: =IFERROR(INDEX('Gantt Cutover'!$I$6:$I$63,MATCH(8,'Gantt Cutover'!$BA$6:$BA$63,0)),"") | J54: =IFERROR(INDEX('Gantt Cutover'!$J$6:$J$63,MATCH(8,'Gantt Cutover'!$BA$6:$BA$63,0)),"") | K54: =IFERROR(INDEX('Gantt Cutover'!$K$6:$K$63,MATCH(8,'Gantt Cutover'!$BA$6:$BA$63,0)),"") | L54: =IFERROR(INDEX('Gantt Cutover'!$M$6:$M$63,MATCH(8,'Gantt Cutover'!$BA$6:$BA$63,0)),"")
B55: 9 | C55: =IFERROR(INDEX('Gantt Cutover'!$A$6:$A$63,MATCH(9,'Gantt Cutover'!$BA$6:$BA$63,0)),"") | D55: =IFERROR(INDEX('Gantt Cutover'!$B$6:$B$63,MATCH(9,'Gantt Cutover'!$BA$6:$BA$63,0)),"") | E55: =IFERROR(INDEX('Gantt Cutover'!$C$6:$C$63,MATCH(9,'Gantt Cutover'!$BA$6:$BA$63,0)),"") | F55: =IFERROR(INDEX('Gantt Cutover'!$G$6:$G$63,MATCH(9,'Gantt Cutover'!$BA$6:$BA$63,0)),"") | G55: =IFERROR(INDEX('Equipo y Calendario'!$B$5:$B$24,MATCH(F55,'Equipo y Calendario'!$A$5:$A$24,0)),"") | H55: =IFERROR(INDEX('Gantt Cutover'!$H$6:$H$63,MATCH(9,'Gantt Cutover'!$BA$6:$BA$63,0)),"") | I55: =IFERROR(INDEX('Gantt Cutover'!$I$6:$I$63,MATCH(9,'Gantt Cutover'!$BA$6:$BA$63,0)),"") | J55: =IFERROR(INDEX('Gantt Cutover'!$J$6:$J$63,MATCH(9,'Gantt Cutover'!$BA$6:$BA$63,0)),"") | K55: =IFERROR(INDEX('Gantt Cutover'!$K$6:$K$63,MATCH(9,'Gantt Cutover'!$BA$6:$BA$63,0)),"") | L55: =IFERROR(INDEX('Gantt Cutover'!$M$6:$M$63,MATCH(9,'Gantt Cutover'!$BA$6:$BA$63,0)),"")
B56: 10 | C56: =IFERROR(INDEX('Gantt Cutover'!$A$6:$A$63,MATCH(10,'Gantt Cutover'!$BA$6:$BA$63,0)),"") | D56: =IFERROR(INDEX('Gantt Cutover'!$B$6:$B$63,MATCH(10,'Gantt Cutover'!$BA$6:$BA$63,0)),"") | E56: =IFERROR(INDEX('Gantt Cutover'!$C$6:$C$63,MATCH(10,'Gantt Cutover'!$BA$6:$BA$63,0)),"") | F56: =IFERROR(INDEX('Gantt Cutover'!$G$6:$G$63,MATCH(10,'Gantt Cutover'!$BA$6:$BA$63,0)),"") | G56: =IFERROR(INDEX('Equipo y Calendario'!$B$5:$B$24,MATCH(F56,'Equipo y Calendario'!$A$5:$A$24,0)),"") | H56: =IFERROR(INDEX('Gantt Cutover'!$H$6:$H$63,MATCH(10,'Gantt Cutover'!$BA$6:$BA$63,0)),"") | I56: =IFERROR(INDEX('Gantt Cutover'!$I$6:$I$63,MATCH(10,'Gantt Cutover'!$BA$6:$BA$63,0)),"") | J56: =IFERROR(INDEX('Gantt Cutover'!$J$6:$J$63,MATCH(10,'Gantt Cutover'!$BA$6:$BA$63,0)),"") | K56: =IFERROR(INDEX('Gantt Cutover'!$K$6:$K$63,MATCH(10,'Gantt Cutover'!$BA$6:$BA$63,0)),"") | L56: =IFERROR(INDEX('Gantt Cutover'!$M$6:$M$63,MATCH(10,'Gantt Cutover'!$BA$6:$BA$63,0)),"")
B57: 11 | C57: =IFERROR(INDEX('Gantt Cutover'!$A$6:$A$63,MATCH(11,'Gantt Cutover'!$BA$6:$BA$63,0)),"") | D57: =IFERROR(INDEX('Gantt Cutover'!$B$6:$B$63,MATCH(11,'Gantt Cutover'!$BA$6:$BA$63,0)),"") | E57: =IFERROR(INDEX('Gantt Cutover'!$C$6:$C$63,MATCH(11,'Gantt Cutover'!$BA$6:$BA$63,0)),"") | F57: =IFERROR(INDEX('Gantt Cutover'!$G$6:$G$63,MATCH(11,'Gantt Cutover'!$BA$6:$BA$63,0)),"") | G57: =IFERROR(INDEX('Equipo y Calendario'!$B$5:$B$24,MATCH(F57,'Equipo y Calendario'!$A$5:$A$24,0)),"") | H57: =IFERROR(INDEX('Gantt Cutover'!$H$6:$H$63,MATCH(11,'Gantt Cutover'!$BA$6:$BA$63,0)),"") | I57: =IFERROR(INDEX('Gantt Cutover'!$I$6:$I$63,MATCH(11,'Gantt Cutover'!$BA$6:$BA$63,0)),"") | J57: =IFERROR(INDEX('Gantt Cutover'!$J$6:$J$63,MATCH(11,'Gantt Cutover'!$BA$6:$BA$63,0)),"") | K57: =IFERROR(INDEX('Gantt Cutover'!$K$6:$K$63,MATCH(11,'Gantt Cutover'!$BA$6:$BA$63,0)),"") | L57: =IFERROR(INDEX('Gantt Cutover'!$M$6:$M$63,MATCH(11,'Gantt Cutover'!$BA$6:$BA$63,0)),"")
B58: 12 | C58: =IFERROR(INDEX('Gantt Cutover'!$A$6:$A$63,MATCH(12,'Gantt Cutover'!$BA$6:$BA$63,0)),"") | D58: =IFERROR(INDEX('Gantt Cutover'!$B$6:$B$63,MATCH(12,'Gantt Cutover'!$BA$6:$BA$63,0)),"") | E58: =IFERROR(INDEX('Gantt Cutover'!$C$6:$C$63,MATCH(12,'Gantt Cutover'!$BA$6:$BA$63,0)),"") | F58: =IFERROR(INDEX('Gantt Cutover'!$G$6:$G$63,MATCH(12,'Gantt Cutover'!$BA$6:$BA$63,0)),"") | G58: =IFERROR(INDEX('Equipo y Calendario'!$B$5:$B$24,MATCH(F58,'Equipo y Calendario'!$A$5:$A$24,0)),"") | H58: =IFERROR(INDEX('Gantt Cutover'!$H$6:$H$63,MATCH(12,'Gantt Cutover'!$BA$6:$BA$63,0)),"") | I58: =IFERROR(INDEX('Gantt Cutover'!$I$6:$I$63,MATCH(12,'Gantt Cutover'!$BA$6:$BA$63,0)),"") | J58: =IFERROR(INDEX('Gantt Cutover'!$J$6:$J$63,MATCH(12,'Gantt Cutover'!$BA$6:$BA$63,0)),"") | K58: =IFERROR(INDEX('Gantt Cutover'!$K$6:$K$63,MATCH(12,'Gantt Cutover'!$BA$6:$BA$63,0)),"") | L58: =IFERROR(INDEX('Gantt Cutover'!$M$6:$M$63,MATCH(12,'Gantt Cutover'!$BA$6:$BA$63,0)),"")
B59: 13 | C59: =IFERROR(INDEX('Gantt Cutover'!$A$6:$A$63,MATCH(13,'Gantt Cutover'!$BA$6:$BA$63,0)),"") | D59: =IFERROR(INDEX('Gantt Cutover'!$B$6:$B$63,MATCH(13,'Gantt Cutover'!$BA$6:$BA$63,0)),"") | E59: =IFERROR(INDEX('Gantt Cutover'!$C$6:$C$63,MATCH(13,'Gantt Cutover'!$BA$6:$BA$63,0)),"") | F59: =IFERROR(INDEX('Gantt Cutover'!$G$6:$G$63,MATCH(13,'Gantt Cutover'!$BA$6:$BA$63,0)),"") | G59: =IFERROR(INDEX('Equipo y Calendario'!$B$5:$B$24,MATCH(F59,'Equipo y Calendario'!$A$5:$A$24,0)),"") | H59: =IFERROR(INDEX('Gantt Cutover'!$H$6:$H$63,MATCH(13,'Gantt Cutover'!$BA$6:$BA$63,0)),"") | I59: =IFERROR(INDEX('Gantt Cutover'!$I$6:$I$63,MATCH(13,'Gantt Cutover'!$BA$6:$BA$63,0)),"") | J59: =IFERROR(INDEX('Gantt Cutover'!$J$6:$J$63,MATCH(13,'Gantt Cutover'!$BA$6:$BA$63,0)),"") | K59: =IFERROR(INDEX('Gantt Cutover'!$K$6:$K$63,MATCH(13,'Gantt Cutover'!$BA$6:$BA$63,0)),"") | L59: =IFERROR(INDEX('Gantt Cutover'!$M$6:$M$63,MATCH(13,'Gantt Cutover'!$BA$6:$BA$63,0)),"")
B60: 14 | C60: =IFERROR(INDEX('Gantt Cutover'!$A$6:$A$63,MATCH(14,'Gantt Cutover'!$BA$6:$BA$63,0)),"") | D60: =IFERROR(INDEX('Gantt Cutover'!$B$6:$B$63,MATCH(14,'Gantt Cutover'!$BA$6:$BA$63,0)),"") | E60: =IFERROR(INDEX('Gantt Cutover'!$C$6:$C$63,MATCH(14,'Gantt Cutover'!$BA$6:$BA$63,0)),"") | F60: =IFERROR(INDEX('Gantt Cutover'!$G$6:$G$63,MATCH(14,'Gantt Cutover'!$BA$6:$BA$63,0)),"") | G60: =IFERROR(INDEX('Equipo y Calendario'!$B$5:$B$24,MATCH(F60,'Equipo y Calendario'!$A$5:$A$24,0)),"") | H60: =IFERROR(INDEX('Gantt Cutover'!$H$6:$H$63,MATCH(14,'Gantt Cutover'!$BA$6:$BA$63,0)),"") | I60: =IFERROR(INDEX('Gantt Cutover'!$I$6:$I$63,MATCH(14,'Gantt Cutover'!$BA$6:$BA$63,0)),"") | J60: =IFERROR(INDEX('Gantt Cutover'!$J$6:$J$63,MATCH(14,'Gantt Cutover'!$BA$6:$BA$63,0)),"") | K60: =IFERROR(INDEX('Gantt Cutover'!$K$6:$K$63,MATCH(14,'Gantt Cutover'!$BA$6:$BA$63,0)),"") | L60: =IFERROR(INDEX('Gantt Cutover'!$M$6:$M$63,MATCH(14,'Gantt Cutover'!$BA$6:$BA$63,0)),"")
B61: 15 | C61: =IFERROR(INDEX('Gantt Cutover'!$A$6:$A$63,MATCH(15,'Gantt Cutover'!$BA$6:$BA$63,0)),"") | D61: =IFERROR(INDEX('Gantt Cutover'!$B$6:$B$63,MATCH(15,'Gantt Cutover'!$BA$6:$BA$63,0)),"") | E61: =IFERROR(INDEX('Gantt Cutover'!$C$6:$C$63,MATCH(15,'Gantt Cutover'!$BA$6:$BA$63,0)),"") | F61: =IFERROR(INDEX('Gantt Cutover'!$G$6:$G$63,MATCH(15,'Gantt Cutover'!$BA$6:$BA$63,0)),"") | G61: =IFERROR(INDEX('Equipo y Calendario'!$B$5:$B$24,MATCH(F61,'Equipo y Calendario'!$A$5:$A$24,0)),"") | H61: =IFERROR(INDEX('Gantt Cutover'!$H$6:$H$63,MATCH(15,'Gantt Cutover'!$BA$6:$BA$63,0)),"") | I61: =IFERROR(INDEX('Gantt Cutover'!$I$6:$I$63,MATCH(15,'Gantt Cutover'!$BA$6:$BA$63,0)),"") | J61: =IFERROR(INDEX('Gantt Cutover'!$J$6:$J$63,MATCH(15,'Gantt Cutover'!$BA$6:$BA$63,0)),"") | K61: =IFERROR(INDEX('Gantt Cutover'!$K$6:$K$63,MATCH(15,'Gantt Cutover'!$BA$6:$BA$63,0)),"") | L61: =IFERROR(INDEX('Gantt Cutover'!$M$6:$M$63,MATCH(15,'Gantt Cutover'!$BA$6:$BA$63,0)),"")
B62: 16 | C62: =IFERROR(INDEX('Gantt Cutover'!$A$6:$A$63,MATCH(16,'Gantt Cutover'!$BA$6:$BA$63,0)),"") | D62: =IFERROR(INDEX('Gantt Cutover'!$B$6:$B$63,MATCH(16,'Gantt Cutover'!$BA$6:$BA$63,0)),"") | E62: =IFERROR(INDEX('Gantt Cutover'!$C$6:$C$63,MATCH(16,'Gantt Cutover'!$BA$6:$BA$63,0)),"") | F62: =IFERROR(INDEX('Gantt Cutover'!$G$6:$G$63,MATCH(16,'Gantt Cutover'!$BA$6:$BA$63,0)),"") | G62: =IFERROR(INDEX('Equipo y Calendario'!$B$5:$B$24,MATCH(F62,'Equipo y Calendario'!$A$5:$A$24,0)),"") | H62: =IFERROR(INDEX('Gantt Cutover'!$H$6:$H$63,MATCH(16,'Gantt Cutover'!$BA$6:$BA$63,0)),"") | I62: =IFERROR(INDEX('Gantt Cutover'!$I$6:$I$63,MATCH(16,'Gantt Cutover'!$BA$6:$BA$63,0)),"") | J62: =IFERROR(INDEX('Gantt Cutover'!$J$6:$J$63,MATCH(16,'Gantt Cutover'!$BA$6:$BA$63,0)),"") | K62: =IFERROR(INDEX('Gantt Cutover'!$K$6:$K$63,MATCH(16,'Gantt Cutover'!$BA$6:$BA$63,0)),"") | L62: =IFERROR(INDEX('Gantt Cutover'!$M$6:$M$63,MATCH(16,'Gantt Cutover'!$BA$6:$BA$63,0)),"")
B63: 17 | C63: =IFERROR(INDEX('Gantt Cutover'!$A$6:$A$63,MATCH(17,'Gantt Cutover'!$BA$6:$BA$63,0)),"") | D63: =IFERROR(INDEX('Gantt Cutover'!$B$6:$B$63,MATCH(17,'Gantt Cutover'!$BA$6:$BA$63,0)),"") | E63: =IFERROR(INDEX('Gantt Cutover'!$C$6:$C$63,MATCH(17,'Gantt Cutover'!$BA$6:$BA$63,0)),"") | F63: =IFERROR(INDEX('Gantt Cutover'!$G$6:$G$63,MATCH(17,'Gantt Cutover'!$BA$6:$BA$63,0)),"") | G63: =IFERROR(INDEX('Equipo y Calendario'!$B$5:$B$24,MATCH(F63,'Equipo y Calendario'!$A$5:$A$24,0)),"") | H63: =IFERROR(INDEX('Gantt Cutover'!$H$6:$H$63,MATCH(17,'Gantt Cutover'!$BA$6:$BA$63,0)),"") | I63: =IFERROR(INDEX('Gantt Cutover'!$I$6:$I$63,MATCH(17,'Gantt Cutover'!$BA$6:$BA$63,0)),"") | J63: =IFERROR(INDEX('Gantt Cutover'!$J$6:$J$63,MATCH(17,'Gantt Cutover'!$BA$6:$BA$63,0)),"") | K63: =IFERROR(INDEX('Gantt Cutover'!$K$6:$K$63,MATCH(17,'Gantt Cutover'!$BA$6:$BA$63,0)),"") | L63: =IFERROR(INDEX('Gantt Cutover'!$M$6:$M$63,MATCH(17,'Gantt Cutover'!$BA$6:$BA$63,0)),"")
B64: 18 | C64: =IFERROR(INDEX('Gantt Cutover'!$A$6:$A$63,MATCH(18,'Gantt Cutover'!$BA$6:$BA$63,0)),"") | D64: =IFERROR(INDEX('Gantt Cutover'!$B$6:$B$63,MATCH(18,'Gantt Cutover'!$BA$6:$BA$63,0)),"") | E64: =IFERROR(INDEX('Gantt Cutover'!$C$6:$C$63,MATCH(18,'Gantt Cutover'!$BA$6:$BA$63,0)),"") | F64: =IFERROR(INDEX('Gantt Cutover'!$G$6:$G$63,MATCH(18,'Gantt Cutover'!$BA$6:$BA$63,0)),"") | G64: =IFERROR(INDEX('Equipo y Calendario'!$B$5:$B$24,MATCH(F64,'Equipo y Calendario'!$A$5:$A$24,0)),"") | H64: =IFERROR(INDEX('Gantt Cutover'!$H$6:$H$63,MATCH(18,'Gantt Cutover'!$BA$6:$BA$63,0)),"") | I64: =IFERROR(INDEX('Gantt Cutover'!$I$6:$I$63,MATCH(18,'Gantt Cutover'!$BA$6:$BA$63,0)),"") | J64: =IFERROR(INDEX('Gantt Cutover'!$J$6:$J$63,MATCH(18,'Gantt Cutover'!$BA$6:$BA$63,0)),"") | K64: =IFERROR(INDEX('Gantt Cutover'!$K$6:$K$63,MATCH(18,'Gantt Cutover'!$BA$6:$BA$63,0)),"") | L64: =IFERROR(INDEX('Gantt Cutover'!$M$6:$M$63,MATCH(18,'Gantt Cutover'!$BA$6:$BA$63,0)),"")
B65: 19 | C65: =IFERROR(INDEX('Gantt Cutover'!$A$6:$A$63,MATCH(19,'Gantt Cutover'!$BA$6:$BA$63,0)),"") | D65: =IFERROR(INDEX('Gantt Cutover'!$B$6:$B$63,MATCH(19,'Gantt Cutover'!$BA$6:$BA$63,0)),"") | E65: =IFERROR(INDEX('Gantt Cutover'!$C$6:$C$63,MATCH(19,'Gantt Cutover'!$BA$6:$BA$63,0)),"") | F65: =IFERROR(INDEX('Gantt Cutover'!$G$6:$G$63,MATCH(19,'Gantt Cutover'!$BA$6:$BA$63,0)),"") | G65: =IFERROR(INDEX('Equipo y Calendario'!$B$5:$B$24,MATCH(F65,'Equipo y Calendario'!$A$5:$A$24,0)),"") | H65: =IFERROR(INDEX('Gantt Cutover'!$H$6:$H$63,MATCH(19,'Gantt Cutover'!$BA$6:$BA$63,0)),"") | I65: =IFERROR(INDEX('Gantt Cutover'!$I$6:$I$63,MATCH(19,'Gantt Cutover'!$BA$6:$BA$63,0)),"") | J65: =IFERROR(INDEX('Gantt Cutover'!$J$6:$J$63,MATCH(19,'Gantt Cutover'!$BA$6:$BA$63,0)),"") | K65: =IFERROR(INDEX('Gantt Cutover'!$K$6:$K$63,MATCH(19,'Gantt Cutover'!$BA$6:$BA$63,0)),"") | L65: =IFERROR(INDEX('Gantt Cutover'!$M$6:$M$63,MATCH(19,'Gantt Cutover'!$BA$6:$BA$63,0)),"")
B66: 20 | C66: =IFERROR(INDEX('Gantt Cutover'!$A$6:$A$63,MATCH(20,'Gantt Cutover'!$BA$6:$BA$63,0)),"") | D66: =IFERROR(INDEX('Gantt Cutover'!$B$6:$B$63,MATCH(20,'Gantt Cutover'!$BA$6:$BA$63,0)),"") | E66: =IFERROR(INDEX('Gantt Cutover'!$C$6:$C$63,MATCH(20,'Gantt Cutover'!$BA$6:$BA$63,0)),"") | F66: =IFERROR(INDEX('Gantt Cutover'!$G$6:$G$63,MATCH(20,'Gantt Cutover'!$BA$6:$BA$63,0)),"") | G66: =IFERROR(INDEX('Equipo y Calendario'!$B$5:$B$24,MATCH(F66,'Equipo y Calendario'!$A$5:$A$24,0)),"") | H66: =IFERROR(INDEX('Gantt Cutover'!$H$6:$H$63,MATCH(20,'Gantt Cutover'!$BA$6:$BA$63,0)),"") | I66: =IFERROR(INDEX('Gantt Cutover'!$I$6:$I$63,MATCH(20,'Gantt Cutover'!$BA$6:$BA$63,0)),"") | J66: =IFERROR(INDEX('Gantt Cutover'!$J$6:$J$63,MATCH(20,'Gantt Cutover'!$BA$6:$BA$63,0)),"") | K66: =IFERROR(INDEX('Gantt Cutover'!$K$6:$K$63,MATCH(20,'Gantt Cutover'!$BA$6:$BA$63,0)),"") | L66: =IFERROR(INDEX('Gantt Cutover'!$M$6:$M$63,MATCH(20,'Gantt Cutover'!$BA$6:$BA$63,0)),"")
B67: 21 | C67: =IFERROR(INDEX('Gantt Cutover'!$A$6:$A$63,MATCH(21,'Gantt Cutover'!$BA$6:$BA$63,0)),"") | D67: =IFERROR(INDEX('Gantt Cutover'!$B$6:$B$63,MATCH(21,'Gantt Cutover'!$BA$6:$BA$63,0)),"") | E67: =IFERROR(INDEX('Gantt Cutover'!$C$6:$C$63,MATCH(21,'Gantt Cutover'!$BA$6:$BA$63,0)),"") | F67: =IFERROR(INDEX('Gantt Cutover'!$G$6:$G$63,MATCH(21,'Gantt Cutover'!$BA$6:$BA$63,0)),"") | G67: =IFERROR(INDEX('Equipo y Calendario'!$B$5:$B$24,MATCH(F67,'Equipo y Calendario'!$A$5:$A$24,0)),"") | H67: =IFERROR(INDEX('Gantt Cutover'!$H$6:$H$63,MATCH(21,'Gantt Cutover'!$BA$6:$BA$63,0)),"") | I67: =IFERROR(INDEX('Gantt Cutover'!$I$6:$I$63,MATCH(21,'Gantt Cutover'!$BA$6:$BA$63,0)),"") | J67: =IFERROR(INDEX('Gantt Cutover'!$J$6:$J$63,MATCH(21,'Gantt Cutover'!$BA$6:$BA$63,0)),"") | K67: =IFERROR(INDEX('Gantt Cutover'!$K$6:$K$63,MATCH(21,'Gantt Cutover'!$BA$6:$BA$63,0)),"") | L67: =IFERROR(INDEX('Gantt Cutover'!$M$6:$M$63,MATCH(21,'Gantt Cutover'!$BA$6:$BA$63,0)),"")
B68: 22 | C68: =IFERROR(INDEX('Gantt Cutover'!$A$6:$A$63,MATCH(22,'Gantt Cutover'!$BA$6:$BA$63,0)),"") | D68: =IFERROR(INDEX('Gantt Cutover'!$B$6:$B$63,MATCH(22,'Gantt Cutover'!$BA$6:$BA$63,0)),"") | E68: =IFERROR(INDEX('Gantt Cutover'!$C$6:$C$63,MATCH(22,'Gantt Cutover'!$BA$6:$BA$63,0)),"") | F68: =IFERROR(INDEX('Gantt Cutover'!$G$6:$G$63,MATCH(22,'Gantt Cutover'!$BA$6:$BA$63,0)),"") | G68: =IFERROR(INDEX('Equipo y Calendario'!$B$5:$B$24,MATCH(F68,'Equipo y Calendario'!$A$5:$A$24,0)),"") | H68: =IFERROR(INDEX('Gantt Cutover'!$H$6:$H$63,MATCH(22,'Gantt Cutover'!$BA$6:$BA$63,0)),"") | I68: =IFERROR(INDEX('Gantt Cutover'!$I$6:$I$63,MATCH(22,'Gantt Cutover'!$BA$6:$BA$63,0)),"") | J68: =IFERROR(INDEX('Gantt Cutover'!$J$6:$J$63,MATCH(22,'Gantt Cutover'!$BA$6:$BA$63,0)),"") | K68: =IFERROR(INDEX('Gantt Cutover'!$K$6:$K$63,MATCH(22,'Gantt Cutover'!$BA$6:$BA$63,0)),"") | L68: =IFERROR(INDEX('Gantt Cutover'!$M$6:$M$63,MATCH(22,'Gantt Cutover'!$BA$6:$BA$63,0)),"")
B69: 23 | C69: =IFERROR(INDEX('Gantt Cutover'!$A$6:$A$63,MATCH(23,'Gantt Cutover'!$BA$6:$BA$63,0)),"") | D69: =IFERROR(INDEX('Gantt Cutover'!$B$6:$B$63,MATCH(23,'Gantt Cutover'!$BA$6:$BA$63,0)),"") | E69: =IFERROR(INDEX('Gantt Cutover'!$C$6:$C$63,MATCH(23,'Gantt Cutover'!$BA$6:$BA$63,0)),"") | F69: =IFERROR(INDEX('Gantt Cutover'!$G$6:$G$63,MATCH(23,'Gantt Cutover'!$BA$6:$BA$63,0)),"") | G69: =IFERROR(INDEX('Equipo y Calendario'!$B$5:$B$24,MATCH(F69,'Equipo y Calendario'!$A$5:$A$24,0)),"") | H69: =IFERROR(INDEX('Gantt Cutover'!$H$6:$H$63,MATCH(23,'Gantt Cutover'!$BA$6:$BA$63,0)),"") | I69: =IFERROR(INDEX('Gantt Cutover'!$I$6:$I$63,MATCH(23,'Gantt Cutover'!$BA$6:$BA$63,0)),"") | J69: =IFERROR(INDEX('Gantt Cutover'!$J$6:$J$63,MATCH(23,'Gantt Cutover'!$BA$6:$BA$63,0)),"") | K69: =IFERROR(INDEX('Gantt Cutover'!$K$6:$K$63,MATCH(23,'Gantt Cutover'!$BA$6:$BA$63,0)),"") | L69: =IFERROR(INDEX('Gantt Cutover'!$M$6:$M$63,MATCH(23,'Gantt Cutover'!$BA$6:$BA$63,0)),"")
B70: 24 | C70: =IFERROR(INDEX('Gantt Cutover'!$A$6:$A$63,MATCH(24,'Gantt Cutover'!$BA$6:$BA$63,0)),"") | D70: =IFERROR(INDEX('Gantt Cutover'!$B$6:$B$63,MATCH(24,'Gantt Cutover'!$BA$6:$BA$63,0)),"") | E70: =IFERROR(INDEX('Gantt Cutover'!$C$6:$C$63,MATCH(24,'Gantt Cutover'!$BA$6:$BA$63,0)),"") | F70: =IFERROR(INDEX('Gantt Cutover'!$G$6:$G$63,MATCH(24,'Gantt Cutover'!$BA$6:$BA$63,0)),"") | G70: =IFERROR(INDEX('Equipo y Calendario'!$B$5:$B$24,MATCH(F70,'Equipo y Calendario'!$A$5:$A$24,0)),"") | H70: =IFERROR(INDEX('Gantt Cutover'!$H$6:$H$63,MATCH(24,'Gantt Cutover'!$BA$6:$BA$63,0)),"") | I70: =IFERROR(INDEX('Gantt Cutover'!$I$6:$I$63,MATCH(24,'Gantt Cutover'!$BA$6:$BA$63,0)),"") | J70: =IFERROR(INDEX('Gantt Cutover'!$J$6:$J$63,MATCH(24,'Gantt Cutover'!$BA$6:$BA$63,0)),"") | K70: =IFERROR(INDEX('Gantt Cutover'!$K$6:$K$63,MATCH(24,'Gantt Cutover'!$BA$6:$BA$63,0)),"") | L70: =IFERROR(INDEX('Gantt Cutover'!$M$6:$M$63,MATCH(24,'Gantt Cutover'!$BA$6:$BA$63,0)),"")
B71: 25 | C71: =IFERROR(INDEX('Gantt Cutover'!$A$6:$A$63,MATCH(25,'Gantt Cutover'!$BA$6:$BA$63,0)),"") | D71: =IFERROR(INDEX('Gantt Cutover'!$B$6:$B$63,MATCH(25,'Gantt Cutover'!$BA$6:$BA$63,0)),"") | E71: =IFERROR(INDEX('Gantt Cutover'!$C$6:$C$63,MATCH(25,'Gantt Cutover'!$BA$6:$BA$63,0)),"") | F71: =IFERROR(INDEX('Gantt Cutover'!$G$6:$G$63,MATCH(25,'Gantt Cutover'!$BA$6:$BA$63,0)),"") | G71: =IFERROR(INDEX('Equipo y Calendario'!$B$5:$B$24,MATCH(F71,'Equipo y Calendario'!$A$5:$A$24,0)),"") | H71: =IFERROR(INDEX('Gantt Cutover'!$H$6:$H$63,MATCH(25,'Gantt Cutover'!$BA$6:$BA$63,0)),"") | I71: =IFERROR(INDEX('Gantt Cutover'!$I$6:$I$63,MATCH(25,'Gantt Cutover'!$BA$6:$BA$63,0)),"") | J71: =IFERROR(INDEX('Gantt Cutover'!$J$6:$J$63,MATCH(25,'Gantt Cutover'!$BA$6:$BA$63,0)),"") | K71: =IFERROR(INDEX('Gantt Cutover'!$K$6:$K$63,MATCH(25,'Gantt Cutover'!$BA$6:$BA$63,0)),"") | L71: =IFERROR(INDEX('Gantt Cutover'!$M$6:$M$63,MATCH(25,'Gantt Cutover'!$BA$6:$BA$63,0)),"")
B72: 26 | C72: =IFERROR(INDEX('Gantt Cutover'!$A$6:$A$63,MATCH(26,'Gantt Cutover'!$BA$6:$BA$63,0)),"") | D72: =IFERROR(INDEX('Gantt Cutover'!$B$6:$B$63,MATCH(26,'Gantt Cutover'!$BA$6:$BA$63,0)),"") | E72: =IFERROR(INDEX('Gantt Cutover'!$C$6:$C$63,MATCH(26,'Gantt Cutover'!$BA$6:$BA$63,0)),"") | F72: =IFERROR(INDEX('Gantt Cutover'!$G$6:$G$63,MATCH(26,'Gantt Cutover'!$BA$6:$BA$63,0)),"") | G72: =IFERROR(INDEX('Equipo y Calendario'!$B$5:$B$24,MATCH(F72,'Equipo y Calendario'!$A$5:$A$24,0)),"") | H72: =IFERROR(INDEX('Gantt Cutover'!$H$6:$H$63,MATCH(26,'Gantt Cutover'!$BA$6:$BA$63,0)),"") | I72: =IFERROR(INDEX('Gantt Cutover'!$I$6:$I$63,MATCH(26,'Gantt Cutover'!$BA$6:$BA$63,0)),"") | J72: =IFERROR(INDEX('Gantt Cutover'!$J$6:$J$63,MATCH(26,'Gantt Cutover'!$BA$6:$BA$63,0)),"") | K72: =IFERROR(INDEX('Gantt Cutover'!$K$6:$K$63,MATCH(26,'Gantt Cutover'!$BA$6:$BA$63,0)),"") | L72: =IFERROR(INDEX('Gantt Cutover'!$M$6:$M$63,MATCH(26,'Gantt Cutover'!$BA$6:$BA$63,0)),"")
B73: 27 | C73: =IFERROR(INDEX('Gantt Cutover'!$A$6:$A$63,MATCH(27,'Gantt Cutover'!$BA$6:$BA$63,0)),"") | D73: =IFERROR(INDEX('Gantt Cutover'!$B$6:$B$63,MATCH(27,'Gantt Cutover'!$BA$6:$BA$63,0)),"") | E73: =IFERROR(INDEX('Gantt Cutover'!$C$6:$C$63,MATCH(27,'Gantt Cutover'!$BA$6:$BA$63,0)),"") | F73: =IFERROR(INDEX('Gantt Cutover'!$G$6:$G$63,MATCH(27,'Gantt Cutover'!$BA$6:$BA$63,0)),"") | G73: =IFERROR(INDEX('Equipo y Calendario'!$B$5:$B$24,MATCH(F73,'Equipo y Calendario'!$A$5:$A$24,0)),"") | H73: =IFERROR(INDEX('Gantt Cutover'!$H$6:$H$63,MATCH(27,'Gantt Cutover'!$BA$6:$BA$63,0)),"") | I73: =IFERROR(INDEX('Gantt Cutover'!$I$6:$I$63,MATCH(27,'Gantt Cutover'!$BA$6:$BA$63,0)),"") | J73: =IFERROR(INDEX('Gantt Cutover'!$J$6:$J$63,MATCH(27,'Gantt Cutover'!$BA$6:$BA$63,0)),"") | K73: =IFERROR(INDEX('Gantt Cutover'!$K$6:$K$63,MATCH(27,'Gantt Cutover'!$BA$6:$BA$63,0)),"") | L73: =IFERROR(INDEX('Gantt Cutover'!$M$6:$M$63,MATCH(27,'Gantt Cutover'!$BA$6:$BA$63,0)),"")
B74: 28 | C74: =IFERROR(INDEX('Gantt Cutover'!$A$6:$A$63,MATCH(28,'Gantt Cutover'!$BA$6:$BA$63,0)),"") | D74: =IFERROR(INDEX('Gantt Cutover'!$B$6:$B$63,MATCH(28,'Gantt Cutover'!$BA$6:$BA$63,0)),"") | E74: =IFERROR(INDEX('Gantt Cutover'!$C$6:$C$63,MATCH(28,'Gantt Cutover'!$BA$6:$BA$63,0)),"") | F74: =IFERROR(INDEX('Gantt Cutover'!$G$6:$G$63,MATCH(28,'Gantt Cutover'!$BA$6:$BA$63,0)),"") | G74: =IFERROR(INDEX('Equipo y Calendario'!$B$5:$B$24,MATCH(F74,'Equipo y Calendario'!$A$5:$A$24,0)),"") | H74: =IFERROR(INDEX('Gantt Cutover'!$H$6:$H$63,MATCH(28,'Gantt Cutover'!$BA$6:$BA$63,0)),"") | I74: =IFERROR(INDEX('Gantt Cutover'!$I$6:$I$63,MATCH(28,'Gantt Cutover'!$BA$6:$BA$63,0)),"") | J74: =IFERROR(INDEX('Gantt Cutover'!$J$6:$J$63,MATCH(28,'Gantt Cutover'!$BA$6:$BA$63,0)),"") | K74: =IFERROR(INDEX('Gantt Cutover'!$K$6:$K$63,MATCH(28,'Gantt Cutover'!$BA$6:$BA$63,0)),"") | L74: =IFERROR(INDEX('Gantt Cutover'!$M$6:$M$63,MATCH(28,'Gantt Cutover'!$BA$6:$BA$63,0)),"")
B75: 29 | C75: =IFERROR(INDEX('Gantt Cutover'!$A$6:$A$63,MATCH(29,'Gantt Cutover'!$BA$6:$BA$63,0)),"") | D75: =IFERROR(INDEX('Gantt Cutover'!$B$6:$B$63,MATCH(29,'Gantt Cutover'!$BA$6:$BA$63,0)),"") | E75: =IFERROR(INDEX('Gantt Cutover'!$C$6:$C$63,MATCH(29,'Gantt Cutover'!$BA$6:$BA$63,0)),"") | F75: =IFERROR(INDEX('Gantt Cutover'!$G$6:$G$63,MATCH(29,'Gantt Cutover'!$BA$6:$BA$63,0)),"") | G75: =IFERROR(INDEX('Equipo y Calendario'!$B$5:$B$24,MATCH(F75,'Equipo y Calendario'!$A$5:$A$24,0)),"") | H75: =IFERROR(INDEX('Gantt Cutover'!$H$6:$H$63,MATCH(29,'Gantt Cutover'!$BA$6:$BA$63,0)),"") | I75: =IFERROR(INDEX('Gantt Cutover'!$I$6:$I$63,MATCH(29,'Gantt Cutover'!$BA$6:$BA$63,0)),"") | J75: =IFERROR(INDEX('Gantt Cutover'!$J$6:$J$63,MATCH(29,'Gantt Cutover'!$BA$6:$BA$63,0)),"") | K75: =IFERROR(INDEX('Gantt Cutover'!$K$6:$K$63,MATCH(29,'Gantt Cutover'!$BA$6:$BA$63,0)),"") | L75: =IFERROR(INDEX('Gantt Cutover'!$M$6:$M$63,MATCH(29,'Gantt Cutover'!$BA$6:$BA$63,0)),"")
B76: 30 | C76: =IFERROR(INDEX('Gantt Cutover'!$A$6:$A$63,MATCH(30,'Gantt Cutover'!$BA$6:$BA$63,0)),"") | D76: =IFERROR(INDEX('Gantt Cutover'!$B$6:$B$63,MATCH(30,'Gantt Cutover'!$BA$6:$BA$63,0)),"") | E76: =IFERROR(INDEX('Gantt Cutover'!$C$6:$C$63,MATCH(30,'Gantt Cutover'!$BA$6:$BA$63,0)),"") | F76: =IFERROR(INDEX('Gantt Cutover'!$G$6:$G$63,MATCH(30,'Gantt Cutover'!$BA$6:$BA$63,0)),"") | G76: =IFERROR(INDEX('Equipo y Calendario'!$B$5:$B$24,MATCH(F76,'Equipo y Calendario'!$A$5:$A$24,0)),"") | H76: =IFERROR(INDEX('Gantt Cutover'!$H$6:$H$63,MATCH(30,'Gantt Cutover'!$BA$6:$BA$63,0)),"") | I76: =IFERROR(INDEX('Gantt Cutover'!$I$6:$I$63,MATCH(30,'Gantt Cutover'!$BA$6:$BA$63,0)),"") | J76: =IFERROR(INDEX('Gantt Cutover'!$J$6:$J$63,MATCH(30,'Gantt Cutover'!$BA$6:$BA$63,0)),"") | K76: =IFERROR(INDEX('Gantt Cutover'!$K$6:$K$63,MATCH(30,'Gantt Cutover'!$BA$6:$BA$63,0)),"") | L76: =IFERROR(INDEX('Gantt Cutover'!$M$6:$M$63,MATCH(30,'Gantt Cutover'!$BA$6:$BA$63,0)),"")
B77: 31 | C77: =IFERROR(INDEX('Gantt Cutover'!$A$6:$A$63,MATCH(31,'Gantt Cutover'!$BA$6:$BA$63,0)),"") | D77: =IFERROR(INDEX('Gantt Cutover'!$B$6:$B$63,MATCH(31,'Gantt Cutover'!$BA$6:$BA$63,0)),"") | E77: =IFERROR(INDEX('Gantt Cutover'!$C$6:$C$63,MATCH(31,'Gantt Cutover'!$BA$6:$BA$63,0)),"") | F77: =IFERROR(INDEX('Gantt Cutover'!$G$6:$G$63,MATCH(31,'Gantt Cutover'!$BA$6:$BA$63,0)),"") | G77: =IFERROR(INDEX('Equipo y Calendario'!$B$5:$B$24,MATCH(F77,'Equipo y Calendario'!$A$5:$A$24,0)),"") | H77: =IFERROR(INDEX('Gantt Cutover'!$H$6:$H$63,MATCH(31,'Gantt Cutover'!$BA$6:$BA$63,0)),"") | I77: =IFERROR(INDEX('Gantt Cutover'!$I$6:$I$63,MATCH(31,'Gantt Cutover'!$BA$6:$BA$63,0)),"") | J77: =IFERROR(INDEX('Gantt Cutover'!$J$6:$J$63,MATCH(31,'Gantt Cutover'!$BA$6:$BA$63,0)),"") | K77: =IFERROR(INDEX('Gantt Cutover'!$K$6:$K$63,MATCH(31,'Gantt Cutover'!$BA$6:$BA$63,0)),"") | L77: =IFERROR(INDEX('Gantt Cutover'!$M$6:$M$63,MATCH(31,'Gantt Cutover'!$BA$6:$BA$63,0)),"")
B78: 32 | C78: =IFERROR(INDEX('Gantt Cutover'!$A$6:$A$63,MATCH(32,'Gantt Cutover'!$BA$6:$BA$63,0)),"") | D78: =IFERROR(INDEX('Gantt Cutover'!$B$6:$B$63,MATCH(32,'Gantt Cutover'!$BA$6:$BA$63,0)),"") | E78: =IFERROR(INDEX('Gantt Cutover'!$C$6:$C$63,MATCH(32,'Gantt Cutover'!$BA$6:$BA$63,0)),"") | F78: =IFERROR(INDEX('Gantt Cutover'!$G$6:$G$63,MATCH(32,'Gantt Cutover'!$BA$6:$BA$63,0)),"") | G78: =IFERROR(INDEX('Equipo y Calendario'!$B$5:$B$24,MATCH(F78,'Equipo y Calendario'!$A$5:$A$24,0)),"") | H78: =IFERROR(INDEX('Gantt Cutover'!$H$6:$H$63,MATCH(32,'Gantt Cutover'!$BA$6:$BA$63,0)),"") | I78: =IFERROR(INDEX('Gantt Cutover'!$I$6:$I$63,MATCH(32,'Gantt Cutover'!$BA$6:$BA$63,0)),"") | J78: =IFERROR(INDEX('Gantt Cutover'!$J$6:$J$63,MATCH(32,'Gantt Cutover'!$BA$6:$BA$63,0)),"") | K78: =IFERROR(INDEX('Gantt Cutover'!$K$6:$K$63,MATCH(32,'Gantt Cutover'!$BA$6:$BA$63,0)),"") | L78: =IFERROR(INDEX('Gantt Cutover'!$M$6:$M$63,MATCH(32,'Gantt Cutover'!$BA$6:$BA$63,0)),"")
B79: 33 | C79: =IFERROR(INDEX('Gantt Cutover'!$A$6:$A$63,MATCH(33,'Gantt Cutover'!$BA$6:$BA$63,0)),"") | D79: =IFERROR(INDEX('Gantt Cutover'!$B$6:$B$63,MATCH(33,'Gantt Cutover'!$BA$6:$BA$63,0)),"") | E79: =IFERROR(INDEX('Gantt Cutover'!$C$6:$C$63,MATCH(33,'Gantt Cutover'!$BA$6:$BA$63,0)),"") | F79: =IFERROR(INDEX('Gantt Cutover'!$G$6:$G$63,MATCH(33,'Gantt Cutover'!$BA$6:$BA$63,0)),"") | G79: =IFERROR(INDEX('Equipo y Calendario'!$B$5:$B$24,MATCH(F79,'Equipo y Calendario'!$A$5:$A$24,0)),"") | H79: =IFERROR(INDEX('Gantt Cutover'!$H$6:$H$63,MATCH(33,'Gantt Cutover'!$BA$6:$BA$63,0)),"") | I79: =IFERROR(INDEX('Gantt Cutover'!$I$6:$I$63,MATCH(33,'Gantt Cutover'!$BA$6:$BA$63,0)),"") | J79: =IFERROR(INDEX('Gantt Cutover'!$J$6:$J$63,MATCH(33,'Gantt Cutover'!$BA$6:$BA$63,0)),"") | K79: =IFERROR(INDEX('Gantt Cutover'!$K$6:$K$63,MATCH(33,'Gantt Cutover'!$BA$6:$BA$63,0)),"") | L79: =IFERROR(INDEX('Gantt Cutover'!$M$6:$M$63,MATCH(33,'Gantt Cutover'!$BA$6:$BA$63,0)),"")
B80: 34 | C80: =IFERROR(INDEX('Gantt Cutover'!$A$6:$A$63,MATCH(34,'Gantt Cutover'!$BA$6:$BA$63,0)),"") | D80: =IFERROR(INDEX('Gantt Cutover'!$B$6:$B$63,MATCH(34,'Gantt Cutover'!$BA$6:$BA$63,0)),"") | E80: =IFERROR(INDEX('Gantt Cutover'!$C$6:$C$63,MATCH(34,'Gantt Cutover'!$BA$6:$BA$63,0)),"") | F80: =IFERROR(INDEX('Gantt Cutover'!$G$6:$G$63,MATCH(34,'Gantt Cutover'!$BA$6:$BA$63,0)),"") | G80: =IFERROR(INDEX('Equipo y Calendario'!$B$5:$B$24,MATCH(F80,'Equipo y Calendario'!$A$5:$A$24,0)),"") | H80: =IFERROR(INDEX('Gantt Cutover'!$H$6:$H$63,MATCH(34,'Gantt Cutover'!$BA$6:$BA$63,0)),"") | I80: =IFERROR(INDEX('Gantt Cutover'!$I$6:$I$63,MATCH(34,'Gantt Cutover'!$BA$6:$BA$63,0)),"") | J80: =IFERROR(INDEX('Gantt Cutover'!$J$6:$J$63,MATCH(34,'Gantt Cutover'!$BA$6:$BA$63,0)),"") | K80: =IFERROR(INDEX('Gantt Cutover'!$K$6:$K$63,MATCH(34,'Gantt Cutover'!$BA$6:$BA$63,0)),"") | L80: =IFERROR(INDEX('Gantt Cutover'!$M$6:$M$63,MATCH(34,'Gantt Cutover'!$BA$6:$BA$63,0)),"")
B81: 35 | C81: =IFERROR(INDEX('Gantt Cutover'!$A$6:$A$63,MATCH(35,'Gantt Cutover'!$BA$6:$BA$63,0)),"") | D81: =IFERROR(INDEX('Gantt Cutover'!$B$6:$B$63,MATCH(35,'Gantt Cutover'!$BA$6:$BA$63,0)),"") | E81: =IFERROR(INDEX('Gantt Cutover'!$C$6:$C$63,MATCH(35,'Gantt Cutover'!$BA$6:$BA$63,0)),"") | F81: =IFERROR(INDEX('Gantt Cutover'!$G$6:$G$63,MATCH(35,'Gantt Cutover'!$BA$6:$BA$63,0)),"") | G81: =IFERROR(INDEX('Equipo y Calendario'!$B$5:$B$24,MATCH(F81,'Equipo y Calendario'!$A$5:$A$24,0)),"") | H81: =IFERROR(INDEX('Gantt Cutover'!$H$6:$H$63,MATCH(35,'Gantt Cutover'!$BA$6:$BA$63,0)),"") | I81: =IFERROR(INDEX('Gantt Cutover'!$I$6:$I$63,MATCH(35,'Gantt Cutover'!$BA$6:$BA$63,0)),"") | J81: =IFERROR(INDEX('Gantt Cutover'!$J$6:$J$63,MATCH(35,'Gantt Cutover'!$BA$6:$BA$63,0)),"") | K81: =IFERROR(INDEX('Gantt Cutover'!$K$6:$K$63,MATCH(35,'Gantt Cutover'!$BA$6:$BA$63,0)),"") | L81: =IFERROR(INDEX('Gantt Cutover'!$M$6:$M$63,MATCH(35,'Gantt Cutover'!$BA$6:$BA$63,0)),"")
B82: 36 | C82: =IFERROR(INDEX('Gantt Cutover'!$A$6:$A$63,MATCH(36,'Gantt Cutover'!$BA$6:$BA$63,0)),"") | D82: =IFERROR(INDEX('Gantt Cutover'!$B$6:$B$63,MATCH(36,'Gantt Cutover'!$BA$6:$BA$63,0)),"") | E82: =IFERROR(INDEX('Gantt Cutover'!$C$6:$C$63,MATCH(36,'Gantt Cutover'!$BA$6:$BA$63,0)),"") | F82: =IFERROR(INDEX('Gantt Cutover'!$G$6:$G$63,MATCH(36,'Gantt Cutover'!$BA$6:$BA$63,0)),"") | G82: =IFERROR(INDEX('Equipo y Calendario'!$B$5:$B$24,MATCH(F82,'Equipo y Calendario'!$A$5:$A$24,0)),"") | H82: =IFERROR(INDEX('Gantt Cutover'!$H$6:$H$63,MATCH(36,'Gantt Cutover'!$BA$6:$BA$63,0)),"") | I82: =IFERROR(INDEX('Gantt Cutover'!$I$6:$I$63,MATCH(36,'Gantt Cutover'!$BA$6:$BA$63,0)),"") | J82: =IFERROR(INDEX('Gantt Cutover'!$J$6:$J$63,MATCH(36,'Gantt Cutover'!$BA$6:$BA$63,0)),"") | K82: =IFERROR(INDEX('Gantt Cutover'!$K$6:$K$63,MATCH(36,'Gantt Cutover'!$BA$6:$BA$63,0)),"") | L82: =IFERROR(INDEX('Gantt Cutover'!$M$6:$M$63,MATCH(36,'Gantt Cutover'!$BA$6:$BA$63,0)),"")
B83: 37 | C83: =IFERROR(INDEX('Gantt Cutover'!$A$6:$A$63,MATCH(37,'Gantt Cutover'!$BA$6:$BA$63,0)),"") | D83: =IFERROR(INDEX('Gantt Cutover'!$B$6:$B$63,MATCH(37,'Gantt Cutover'!$BA$6:$BA$63,0)),"") | E83: =IFERROR(INDEX('Gantt Cutover'!$C$6:$C$63,MATCH(37,'Gantt Cutover'!$BA$6:$BA$63,0)),"") | F83: =IFERROR(INDEX('Gantt Cutover'!$G$6:$G$63,MATCH(37,'Gantt Cutover'!$BA$6:$BA$63,0)),"") | G83: =IFERROR(INDEX('Equipo y Calendario'!$B$5:$B$24,MATCH(F83,'Equipo y Calendario'!$A$5:$A$24,0)),"") | H83: =IFERROR(INDEX('Gantt Cutover'!$H$6:$H$63,MATCH(37,'Gantt Cutover'!$BA$6:$BA$63,0)),"") | I83: =IFERROR(INDEX('Gantt Cutover'!$I$6:$I$63,MATCH(37,'Gantt Cutover'!$BA$6:$BA$63,0)),"") | J83: =IFERROR(INDEX('Gantt Cutover'!$J$6:$J$63,MATCH(37,'Gantt Cutover'!$BA$6:$BA$63,0)),"") | K83: =IFERROR(INDEX('Gantt Cutover'!$K$6:$K$63,MATCH(37,'Gantt Cutover'!$BA$6:$BA$63,0)),"") | L83: =IFERROR(INDEX('Gantt Cutover'!$M$6:$M$63,MATCH(37,'Gantt Cutover'!$BA$6:$BA$63,0)),"")
B84: 38 | C84: =IFERROR(INDEX('Gantt Cutover'!$A$6:$A$63,MATCH(38,'Gantt Cutover'!$BA$6:$BA$63,0)),"") | D84: =IFERROR(INDEX('Gantt Cutover'!$B$6:$B$63,MATCH(38,'Gantt Cutover'!$BA$6:$BA$63,0)),"") | E84: =IFERROR(INDEX('Gantt Cutover'!$C$6:$C$63,MATCH(38,'Gantt Cutover'!$BA$6:$BA$63,0)),"") | F84: =IFERROR(INDEX('Gantt Cutover'!$G$6:$G$63,MATCH(38,'Gantt Cutover'!$BA$6:$BA$63,0)),"") | G84: =IFERROR(INDEX('Equipo y Calendario'!$B$5:$B$24,MATCH(F84,'Equipo y Calendario'!$A$5:$A$24,0)),"") | H84: =IFERROR(INDEX('Gantt Cutover'!$H$6:$H$63,MATCH(38,'Gantt Cutover'!$BA$6:$BA$63,0)),"") | I84: =IFERROR(INDEX('Gantt Cutover'!$I$6:$I$63,MATCH(38,'Gantt Cutover'!$BA$6:$BA$63,0)),"") | J84: =IFERROR(INDEX('Gantt Cutover'!$J$6:$J$63,MATCH(38,'Gantt Cutover'!$BA$6:$BA$63,0)),"") | K84: =IFERROR(INDEX('Gantt Cutover'!$K$6:$K$63,MATCH(38,'Gantt Cutover'!$BA$6:$BA$63,0)),"") | L84: =IFERROR(INDEX('Gantt Cutover'!$M$6:$M$63,MATCH(38,'Gantt Cutover'!$BA$6:$BA$63,0)),"")
B85: 39 | C85: =IFERROR(INDEX('Gantt Cutover'!$A$6:$A$63,MATCH(39,'Gantt Cutover'!$BA$6:$BA$63,0)),"") | D85: =IFERROR(INDEX('Gantt Cutover'!$B$6:$B$63,MATCH(39,'Gantt Cutover'!$BA$6:$BA$63,0)),"") | E85: =IFERROR(INDEX('Gantt Cutover'!$C$6:$C$63,MATCH(39,'Gantt Cutover'!$BA$6:$BA$63,0)),"") | F85: =IFERROR(INDEX('Gantt Cutover'!$G$6:$G$63,MATCH(39,'Gantt Cutover'!$BA$6:$BA$63,0)),"") | G85: =IFERROR(INDEX('Equipo y Calendario'!$B$5:$B$24,MATCH(F85,'Equipo y Calendario'!$A$5:$A$24,0)),"") | H85: =IFERROR(INDEX('Gantt Cutover'!$H$6:$H$63,MATCH(39,'Gantt Cutover'!$BA$6:$BA$63,0)),"") | I85: =IFERROR(INDEX('Gantt Cutover'!$I$6:$I$63,MATCH(39,'Gantt Cutover'!$BA$6:$BA$63,0)),"") | J85: =IFERROR(INDEX('Gantt Cutover'!$J$6:$J$63,MATCH(39,'Gantt Cutover'!$BA$6:$BA$63,0)),"") | K85: =IFERROR(INDEX('Gantt Cutover'!$K$6:$K$63,MATCH(39,'Gantt Cutover'!$BA$6:$BA$63,0)),"") | L85: =IFERROR(INDEX('Gantt Cutover'!$M$6:$M$63,MATCH(39,'Gantt Cutover'!$BA$6:$BA$63,0)),"")
B86: 40 | C86: =IFERROR(INDEX('Gantt Cutover'!$A$6:$A$63,MATCH(40,'Gantt Cutover'!$BA$6:$BA$63,0)),"") | D86: =IFERROR(INDEX('Gantt Cutover'!$B$6:$B$63,MATCH(40,'Gantt Cutover'!$BA$6:$BA$63,0)),"") | E86: =IFERROR(INDEX('Gantt Cutover'!$C$6:$C$63,MATCH(40,'Gantt Cutover'!$BA$6:$BA$63,0)),"") | F86: =IFERROR(INDEX('Gantt Cutover'!$G$6:$G$63,MATCH(40,'Gantt Cutover'!$BA$6:$BA$63,0)),"") | G86: =IFERROR(INDEX('Equipo y Calendario'!$B$5:$B$24,MATCH(F86,'Equipo y Calendario'!$A$5:$A$24,0)),"") | H86: =IFERROR(INDEX('Gantt Cutover'!$H$6:$H$63,MATCH(40,'Gantt Cutover'!$BA$6:$BA$63,0)),"") | I86: =IFERROR(INDEX('Gantt Cutover'!$I$6:$I$63,MATCH(40,'Gantt Cutover'!$BA$6:$BA$63,0)),"") | J86: =IFERROR(INDEX('Gantt Cutover'!$J$6:$J$63,MATCH(40,'Gantt Cutover'!$BA$6:$BA$63,0)),"") | K86: =IFERROR(INDEX('Gantt Cutover'!$K$6:$K$63,MATCH(40,'Gantt Cutover'!$BA$6:$BA$63,0)),"") | L86: =IFERROR(INDEX('Gantt Cutover'!$M$6:$M$63,MATCH(40,'Gantt Cutover'!$BA$6:$BA$63,0)),"")
B87: 41 | C87: =IFERROR(INDEX('Gantt Cutover'!$A$6:$A$63,MATCH(41,'Gantt Cutover'!$BA$6:$BA$63,0)),"") | D87: =IFERROR(INDEX('Gantt Cutover'!$B$6:$B$63,MATCH(41,'Gantt Cutover'!$BA$6:$BA$63,0)),"") | E87: =IFERROR(INDEX('Gantt Cutover'!$C$6:$C$63,MATCH(41,'Gantt Cutover'!$BA$6:$BA$63,0)),"") | F87: =IFERROR(INDEX('Gantt Cutover'!$G$6:$G$63,MATCH(41,'Gantt Cutover'!$BA$6:$BA$63,0)),"") | G87: =IFERROR(INDEX('Equipo y Calendario'!$B$5:$B$24,MATCH(F87,'Equipo y Calendario'!$A$5:$A$24,0)),"") | H87: =IFERROR(INDEX('Gantt Cutover'!$H$6:$H$63,MATCH(41,'Gantt Cutover'!$BA$6:$BA$63,0)),"") | I87: =IFERROR(INDEX('Gantt Cutover'!$I$6:$I$63,MATCH(41,'Gantt Cutover'!$BA$6:$BA$63,0)),"") | J87: =IFERROR(INDEX('Gantt Cutover'!$J$6:$J$63,MATCH(41,'Gantt Cutover'!$BA$6:$BA$63,0)),"") | K87: =IFERROR(INDEX('Gantt Cutover'!$K$6:$K$63,MATCH(41,'Gantt Cutover'!$BA$6:$BA$63,0)),"") | L87: =IFERROR(INDEX('Gantt Cutover'!$M$6:$M$63,MATCH(41,'Gantt Cutover'!$BA$6:$BA$63,0)),"")
B88: 42 | C88: =IFERROR(INDEX('Gantt Cutover'!$A$6:$A$63,MATCH(42,'Gantt Cutover'!$BA$6:$BA$63,0)),"") | D88: =IFERROR(INDEX('Gantt Cutover'!$B$6:$B$63,MATCH(42,'Gantt Cutover'!$BA$6:$BA$63,0)),"") | E88: =IFERROR(INDEX('Gantt Cutover'!$C$6:$C$63,MATCH(42,'Gantt Cutover'!$BA$6:$BA$63,0)),"") | F88: =IFERROR(INDEX('Gantt Cutover'!$G$6:$G$63,MATCH(42,'Gantt Cutover'!$BA$6:$BA$63,0)),"") | G88: =IFERROR(INDEX('Equipo y Calendario'!$B$5:$B$24,MATCH(F88,'Equipo y Calendario'!$A$5:$A$24,0)),"") | H88: =IFERROR(INDEX('Gantt Cutover'!$H$6:$H$63,MATCH(42,'Gantt Cutover'!$BA$6:$BA$63,0)),"") | I88: =IFERROR(INDEX('Gantt Cutover'!$I$6:$I$63,MATCH(42,'Gantt Cutover'!$BA$6:$BA$63,0)),"") | J88: =IFERROR(INDEX('Gantt Cutover'!$J$6:$J$63,MATCH(42,'Gantt Cutover'!$BA$6:$BA$63,0)),"") | K88: =IFERROR(INDEX('Gantt Cutover'!$K$6:$K$63,MATCH(42,'Gantt Cutover'!$BA$6:$BA$63,0)),"") | L88: =IFERROR(INDEX('Gantt Cutover'!$M$6:$M$63,MATCH(42,'Gantt Cutover'!$BA$6:$BA$63,0)),"")
B89: 43 | C89: =IFERROR(INDEX('Gantt Cutover'!$A$6:$A$63,MATCH(43,'Gantt Cutover'!$BA$6:$BA$63,0)),"") | D89: =IFERROR(INDEX('Gantt Cutover'!$B$6:$B$63,MATCH(43,'Gantt Cutover'!$BA$6:$BA$63,0)),"") | E89: =IFERROR(INDEX('Gantt Cutover'!$C$6:$C$63,MATCH(43,'Gantt Cutover'!$BA$6:$BA$63,0)),"") | F89: =IFERROR(INDEX('Gantt Cutover'!$G$6:$G$63,MATCH(43,'Gantt Cutover'!$BA$6:$BA$63,0)),"") | G89: =IFERROR(INDEX('Equipo y Calendario'!$B$5:$B$24,MATCH(F89,'Equipo y Calendario'!$A$5:$A$24,0)),"") | H89: =IFERROR(INDEX('Gantt Cutover'!$H$6:$H$63,MATCH(43,'Gantt Cutover'!$BA$6:$BA$63,0)),"") | I89: =IFERROR(INDEX('Gantt Cutover'!$I$6:$I$63,MATCH(43,'Gantt Cutover'!$BA$6:$BA$63,0)),"") | J89: =IFERROR(INDEX('Gantt Cutover'!$J$6:$J$63,MATCH(43,'Gantt Cutover'!$BA$6:$BA$63,0)),"") | K89: =IFERROR(INDEX('Gantt Cutover'!$K$6:$K$63,MATCH(43,'Gantt Cutover'!$BA$6:$BA$63,0)),"") | L89: =IFERROR(INDEX('Gantt Cutover'!$M$6:$M$63,MATCH(43,'Gantt Cutover'!$BA$6:$BA$63,0)),"")
B90: 44 | C90: =IFERROR(INDEX('Gantt Cutover'!$A$6:$A$63,MATCH(44,'Gantt Cutover'!$BA$6:$BA$63,0)),"") | D90: =IFERROR(INDEX('Gantt Cutover'!$B$6:$B$63,MATCH(44,'Gantt Cutover'!$BA$6:$BA$63,0)),"") | E90: =IFERROR(INDEX('Gantt Cutover'!$C$6:$C$63,MATCH(44,'Gantt Cutover'!$BA$6:$BA$63,0)),"") | F90: =IFERROR(INDEX('Gantt Cutover'!$G$6:$G$63,MATCH(44,'Gantt Cutover'!$BA$6:$BA$63,0)),"") | G90: =IFERROR(INDEX('Equipo y Calendario'!$B$5:$B$24,MATCH(F90,'Equipo y Calendario'!$A$5:$A$24,0)),"") | H90: =IFERROR(INDEX('Gantt Cutover'!$H$6:$H$63,MATCH(44,'Gantt Cutover'!$BA$6:$BA$63,0)),"") | I90: =IFERROR(INDEX('Gantt Cutover'!$I$6:$I$63,MATCH(44,'Gantt Cutover'!$BA$6:$BA$63,0)),"") | J90: =IFERROR(INDEX('Gantt Cutover'!$J$6:$J$63,MATCH(44,'Gantt Cutover'!$BA$6:$BA$63,0)),"") | K90: =IFERROR(INDEX('Gantt Cutover'!$K$6:$K$63,MATCH(44,'Gantt Cutover'!$BA$6:$BA$63,0)),"") | L90: =IFERROR(INDEX('Gantt Cutover'!$M$6:$M$63,MATCH(44,'Gantt Cutover'!$BA$6:$BA$63,0)),"")
B91: 45 | C91: =IFERROR(INDEX('Gantt Cutover'!$A$6:$A$63,MATCH(45,'Gantt Cutover'!$BA$6:$BA$63,0)),"") | D91: =IFERROR(INDEX('Gantt Cutover'!$B$6:$B$63,MATCH(45,'Gantt Cutover'!$BA$6:$BA$63,0)),"") | E91: =IFERROR(INDEX('Gantt Cutover'!$C$6:$C$63,MATCH(45,'Gantt Cutover'!$BA$6:$BA$63,0)),"") | F91: =IFERROR(INDEX('Gantt Cutover'!$G$6:$G$63,MATCH(45,'Gantt Cutover'!$BA$6:$BA$63,0)),"") | G91: =IFERROR(INDEX('Equipo y Calendario'!$B$5:$B$24,MATCH(F91,'Equipo y Calendario'!$A$5:$A$24,0)),"") | H91: =IFERROR(INDEX('Gantt Cutover'!$H$6:$H$63,MATCH(45,'Gantt Cutover'!$BA$6:$BA$63,0)),"") | I91: =IFERROR(INDEX('Gantt Cutover'!$I$6:$I$63,MATCH(45,'Gantt Cutover'!$BA$6:$BA$63,0)),"") | J91: =IFERROR(INDEX('Gantt Cutover'!$J$6:$J$63,MATCH(45,'Gantt Cutover'!$BA$6:$BA$63,0)),"") | K91: =IFERROR(INDEX('Gantt Cutover'!$K$6:$K$63,MATCH(45,'Gantt Cutover'!$BA$6:$BA$63,0)),"") | L91: =IFERROR(INDEX('Gantt Cutover'!$M$6:$M$63,MATCH(45,'Gantt Cutover'!$BA$6:$BA$63,0)),"")
B92: 46 | C92: =IFERROR(INDEX('Gantt Cutover'!$A$6:$A$63,MATCH(46,'Gantt Cutover'!$BA$6:$BA$63,0)),"") | D92: =IFERROR(INDEX('Gantt Cutover'!$B$6:$B$63,MATCH(46,'Gantt Cutover'!$BA$6:$BA$63,0)),"") | E92: =IFERROR(INDEX('Gantt Cutover'!$C$6:$C$63,MATCH(46,'Gantt Cutover'!$BA$6:$BA$63,0)),"") | F92: =IFERROR(INDEX('Gantt Cutover'!$G$6:$G$63,MATCH(46,'Gantt Cutover'!$BA$6:$BA$63,0)),"") | G92: =IFERROR(INDEX('Equipo y Calendario'!$B$5:$B$24,MATCH(F92,'Equipo y Calendario'!$A$5:$A$24,0)),"") | H92: =IFERROR(INDEX('Gantt Cutover'!$H$6:$H$63,MATCH(46,'Gantt Cutover'!$BA$6:$BA$63,0)),"") | I92: =IFERROR(INDEX('Gantt Cutover'!$I$6:$I$63,MATCH(46,'Gantt Cutover'!$BA$6:$BA$63,0)),"") | J92: =IFERROR(INDEX('Gantt Cutover'!$J$6:$J$63,MATCH(46,'Gantt Cutover'!$BA$6:$BA$63,0)),"") | K92: =IFERROR(INDEX('Gantt Cutover'!$K$6:$K$63,MATCH(46,'Gantt Cutover'!$BA$6:$BA$63,0)),"") | L92: =IFERROR(INDEX('Gantt Cutover'!$M$6:$M$63,MATCH(46,'Gantt Cutover'!$BA$6:$BA$63,0)),"")
B93: 47 | C93: =IFERROR(INDEX('Gantt Cutover'!$A$6:$A$63,MATCH(47,'Gantt Cutover'!$BA$6:$BA$63,0)),"") | D93: =IFERROR(INDEX('Gantt Cutover'!$B$6:$B$63,MATCH(47,'Gantt Cutover'!$BA$6:$BA$63,0)),"") | E93: =IFERROR(INDEX('Gantt Cutover'!$C$6:$C$63,MATCH(47,'Gantt Cutover'!$BA$6:$BA$63,0)),"") | F93: =IFERROR(INDEX('Gantt Cutover'!$G$6:$G$63,MATCH(47,'Gantt Cutover'!$BA$6:$BA$63,0)),"") | G93: =IFERROR(INDEX('Equipo y Calendario'!$B$5:$B$24,MATCH(F93,'Equipo y Calendario'!$A$5:$A$24,0)),"") | H93: =IFERROR(INDEX('Gantt Cutover'!$H$6:$H$63,MATCH(47,'Gantt Cutover'!$BA$6:$BA$63,0)),"") | I93: =IFERROR(INDEX('Gantt Cutover'!$I$6:$I$63,MATCH(47,'Gantt Cutover'!$BA$6:$BA$63,0)),"") | J93: =IFERROR(INDEX('Gantt Cutover'!$J$6:$J$63,MATCH(47,'Gantt Cutover'!$BA$6:$BA$63,0)),"") | K93: =IFERROR(INDEX('Gantt Cutover'!$K$6:$K$63,MATCH(47,'Gantt Cutover'!$BA$6:$BA$63,0)),"") | L93: =IFERROR(INDEX('Gantt Cutover'!$M$6:$M$63,MATCH(47,'Gantt Cutover'!$BA$6:$BA$63,0)),"")
B94: 48 | C94: =IFERROR(INDEX('Gantt Cutover'!$A$6:$A$63,MATCH(48,'Gantt Cutover'!$BA$6:$BA$63,0)),"") | D94: =IFERROR(INDEX('Gantt Cutover'!$B$6:$B$63,MATCH(48,'Gantt Cutover'!$BA$6:$BA$63,0)),"") | E94: =IFERROR(INDEX('Gantt Cutover'!$C$6:$C$63,MATCH(48,'Gantt Cutover'!$BA$6:$BA$63,0)),"") | F94: =IFERROR(INDEX('Gantt Cutover'!$G$6:$G$63,MATCH(48,'Gantt Cutover'!$BA$6:$BA$63,0)),"") | G94: =IFERROR(INDEX('Equipo y Calendario'!$B$5:$B$24,MATCH(F94,'Equipo y Calendario'!$A$5:$A$24,0)),"") | H94: =IFERROR(INDEX('Gantt Cutover'!$H$6:$H$63,MATCH(48,'Gantt Cutover'!$BA$6:$BA$63,0)),"") | I94: =IFERROR(INDEX('Gantt Cutover'!$I$6:$I$63,MATCH(48,'Gantt Cutover'!$BA$6:$BA$63,0)),"") | J94: =IFERROR(INDEX('Gantt Cutover'!$J$6:$J$63,MATCH(48,'Gantt Cutover'!$BA$6:$BA$63,0)),"") | K94: =IFERROR(INDEX('Gantt Cutover'!$K$6:$K$63,MATCH(48,'Gantt Cutover'!$BA$6:$BA$63,0)),"") | L94: =IFERROR(INDEX('Gantt Cutover'!$M$6:$M$63,MATCH(48,'Gantt Cutover'!$BA$6:$BA$63,0)),"")
B95: 49 | C95: =IFERROR(INDEX('Gantt Cutover'!$A$6:$A$63,MATCH(49,'Gantt Cutover'!$BA$6:$BA$63,0)),"") | D95: =IFERROR(INDEX('Gantt Cutover'!$B$6:$B$63,MATCH(49,'Gantt Cutover'!$BA$6:$BA$63,0)),"") | E95: =IFERROR(INDEX('Gantt Cutover'!$C$6:$C$63,MATCH(49,'Gantt Cutover'!$BA$6:$BA$63,0)),"") | F95: =IFERROR(INDEX('Gantt Cutover'!$G$6:$G$63,MATCH(49,'Gantt Cutover'!$BA$6:$BA$63,0)),"") | G95: =IFERROR(INDEX('Equipo y Calendario'!$B$5:$B$24,MATCH(F95,'Equipo y Calendario'!$A$5:$A$24,0)),"") | H95: =IFERROR(INDEX('Gantt Cutover'!$H$6:$H$63,MATCH(49,'Gantt Cutover'!$BA$6:$BA$63,0)),"") | I95: =IFERROR(INDEX('Gantt Cutover'!$I$6:$I$63,MATCH(49,'Gantt Cutover'!$BA$6:$BA$63,0)),"") | J95: =IFERROR(INDEX('Gantt Cutover'!$J$6:$J$63,MATCH(49,'Gantt Cutover'!$BA$6:$BA$63,0)),"") | K95: =IFERROR(INDEX('Gantt Cutover'!$K$6:$K$63,MATCH(49,'Gantt Cutover'!$BA$6:$BA$63,0)),"") | L95: =IFERROR(INDEX('Gantt Cutover'!$M$6:$M$63,MATCH(49,'Gantt Cutover'!$BA$6:$BA$63,0)),"")
B96: 50 | C96: =IFERROR(INDEX('Gantt Cutover'!$A$6:$A$63,MATCH(50,'Gantt Cutover'!$BA$6:$BA$63,0)),"") | D96: =IFERROR(INDEX('Gantt Cutover'!$B$6:$B$63,MATCH(50,'Gantt Cutover'!$BA$6:$BA$63,0)),"") | E96: =IFERROR(INDEX('Gantt Cutover'!$C$6:$C$63,MATCH(50,'Gantt Cutover'!$BA$6:$BA$63,0)),"") | F96: =IFERROR(INDEX('Gantt Cutover'!$G$6:$G$63,MATCH(50,'Gantt Cutover'!$BA$6:$BA$63,0)),"") | G96: =IFERROR(INDEX('Equipo y Calendario'!$B$5:$B$24,MATCH(F96,'Equipo y Calendario'!$A$5:$A$24,0)),"") | H96: =IFERROR(INDEX('Gantt Cutover'!$H$6:$H$63,MATCH(50,'Gantt Cutover'!$BA$6:$BA$63,0)),"") | I96: =IFERROR(INDEX('Gantt Cutover'!$I$6:$I$63,MATCH(50,'Gantt Cutover'!$BA$6:$BA$63,0)),"") | J96: =IFERROR(INDEX('Gantt Cutover'!$J$6:$J$63,MATCH(50,'Gantt Cutover'!$BA$6:$BA$63,0)),"") | K96: =IFERROR(INDEX('Gantt Cutover'!$K$6:$K$63,MATCH(50,'Gantt Cutover'!$BA$6:$BA$63,0)),"") | L96: =IFERROR(INDEX('Gantt Cutover'!$M$6:$M$63,MATCH(50,'Gantt Cutover'!$BA$6:$BA$63,0)),"")
B97: 51 | C97: =IFERROR(INDEX('Gantt Cutover'!$A$6:$A$63,MATCH(51,'Gantt Cutover'!$BA$6:$BA$63,0)),"") | D97: =IFERROR(INDEX('Gantt Cutover'!$B$6:$B$63,MATCH(51,'Gantt Cutover'!$BA$6:$BA$63,0)),"") | E97: =IFERROR(INDEX('Gantt Cutover'!$C$6:$C$63,MATCH(51,'Gantt Cutover'!$BA$6:$BA$63,0)),"") | F97: =IFERROR(INDEX('Gantt Cutover'!$G$6:$G$63,MATCH(51,'Gantt Cutover'!$BA$6:$BA$63,0)),"") | G97: =IFERROR(INDEX('Equipo y Calendario'!$B$5:$B$24,MATCH(F97,'Equipo y Calendario'!$A$5:$A$24,0)),"") | H97: =IFERROR(INDEX('Gantt Cutover'!$H$6:$H$63,MATCH(51,'Gantt Cutover'!$BA$6:$BA$63,0)),"") | I97: =IFERROR(INDEX('Gantt Cutover'!$I$6:$I$63,MATCH(51,'Gantt Cutover'!$BA$6:$BA$63,0)),"") | J97: =IFERROR(INDEX('Gantt Cutover'!$J$6:$J$63,MATCH(51,'Gantt Cutover'!$BA$6:$BA$63,0)),"") | K97: =IFERROR(INDEX('Gantt Cutover'!$K$6:$K$63,MATCH(51,'Gantt Cutover'!$BA$6:$BA$63,0)),"") | L97: =IFERROR(INDEX('Gantt Cutover'!$M$6:$M$63,MATCH(51,'Gantt Cutover'!$BA$6:$BA$63,0)),"")
B98: 52 | C98: =IFERROR(INDEX('Gantt Cutover'!$A$6:$A$63,MATCH(52,'Gantt Cutover'!$BA$6:$BA$63,0)),"") | D98: =IFERROR(INDEX('Gantt Cutover'!$B$6:$B$63,MATCH(52,'Gantt Cutover'!$BA$6:$BA$63,0)),"") | E98: =IFERROR(INDEX('Gantt Cutover'!$C$6:$C$63,MATCH(52,'Gantt Cutover'!$BA$6:$BA$63,0)),"") | F98: =IFERROR(INDEX('Gantt Cutover'!$G$6:$G$63,MATCH(52,'Gantt Cutover'!$BA$6:$BA$63,0)),"") | G98: =IFERROR(INDEX('Equipo y Calendario'!$B$5:$B$24,MATCH(F98,'Equipo y Calendario'!$A$5:$A$24,0)),"") | H98: =IFERROR(INDEX('Gantt Cutover'!$H$6:$H$63,MATCH(52,'Gantt Cutover'!$BA$6:$BA$63,0)),"") | I98: =IFERROR(INDEX('Gantt Cutover'!$I$6:$I$63,MATCH(52,'Gantt Cutover'!$BA$6:$BA$63,0)),"") | J98: =IFERROR(INDEX('Gantt Cutover'!$J$6:$J$63,MATCH(52,'Gantt Cutover'!$BA$6:$BA$63,0)),"") | K98: =IFERROR(INDEX('Gantt Cutover'!$K$6:$K$63,MATCH(52,'Gantt Cutover'!$BA$6:$BA$63,0)),"") | L98: =IFERROR(INDEX('Gantt Cutover'!$M$6:$M$63,MATCH(52,'Gantt Cutover'!$BA$6:$BA$63,0)),"")
B99: 53 | C99: =IFERROR(INDEX('Gantt Cutover'!$A$6:$A$63,MATCH(53,'Gantt Cutover'!$BA$6:$BA$63,0)),"") | D99: =IFERROR(INDEX('Gantt Cutover'!$B$6:$B$63,MATCH(53,'Gantt Cutover'!$BA$6:$BA$63,0)),"") | E99: =IFERROR(INDEX('Gantt Cutover'!$C$6:$C$63,MATCH(53,'Gantt Cutover'!$BA$6:$BA$63,0)),"") | F99: =IFERROR(INDEX('Gantt Cutover'!$G$6:$G$63,MATCH(53,'Gantt Cutover'!$BA$6:$BA$63,0)),"") | G99: =IFERROR(INDEX('Equipo y Calendario'!$B$5:$B$24,MATCH(F99,'Equipo y Calendario'!$A$5:$A$24,0)),"") | H99: =IFERROR(INDEX('Gantt Cutover'!$H$6:$H$63,MATCH(53,'Gantt Cutover'!$BA$6:$BA$63,0)),"") | I99: =IFERROR(INDEX('Gantt Cutover'!$I$6:$I$63,MATCH(53,'Gantt Cutover'!$BA$6:$BA$63,0)),"") | J99: =IFERROR(INDEX('Gantt Cutover'!$J$6:$J$63,MATCH(53,'Gantt Cutover'!$BA$6:$BA$63,0)),"") | K99: =IFERROR(INDEX('Gantt Cutover'!$K$6:$K$63,MATCH(53,'Gantt Cutover'!$BA$6:$BA$63,0)),"") | L99: =IFERROR(INDEX('Gantt Cutover'!$M$6:$M$63,MATCH(53,'Gantt Cutover'!$BA$6:$BA$63,0)),"")
B100: 54 | C100: =IFERROR(INDEX('Gantt Cutover'!$A$6:$A$63,MATCH(54,'Gantt Cutover'!$BA$6:$BA$63,0)),"") | D100: =IFERROR(INDEX('Gantt Cutover'!$B$6:$B$63,MATCH(54,'Gantt Cutover'!$BA$6:$BA$63,0)),"") | E100: =IFERROR(INDEX('Gantt Cutover'!$C$6:$C$63,MATCH(54,'Gantt Cutover'!$BA$6:$BA$63,0)),"") | F100: =IFERROR(INDEX('Gantt Cutover'!$G$6:$G$63,MATCH(54,'Gantt Cutover'!$BA$6:$BA$63,0)),"") | G100: =IFERROR(INDEX('Equipo y Calendario'!$B$5:$B$24,MATCH(F100,'Equipo y Calendario'!$A$5:$A$24,0)),"") | H100: =IFERROR(INDEX('Gantt Cutover'!$H$6:$H$63,MATCH(54,'Gantt Cutover'!$BA$6:$BA$63,0)),"") | I100: =IFERROR(INDEX('Gantt Cutover'!$I$6:$I$63,MATCH(54,'Gantt Cutover'!$BA$6:$BA$63,0)),"") | J100: =IFERROR(INDEX('Gantt Cutover'!$J$6:$J$63,MATCH(54,'Gantt Cutover'!$BA$6:$BA$63,0)),"") | K100: =IFERROR(INDEX('Gantt Cutover'!$K$6:$K$63,MATCH(54,'Gantt Cutover'!$BA$6:$BA$63,0)),"") | L100: =IFERROR(INDEX('Gantt Cutover'!$M$6:$M$63,MATCH(54,'Gantt Cutover'!$BA$6:$BA$63,0)),"")
B101: 55 | C101: =IFERROR(INDEX('Gantt Cutover'!$A$6:$A$63,MATCH(55,'Gantt Cutover'!$BA$6:$BA$63,0)),"") | D101: =IFERROR(INDEX('Gantt Cutover'!$B$6:$B$63,MATCH(55,'Gantt Cutover'!$BA$6:$BA$63,0)),"") | E101: =IFERROR(INDEX('Gantt Cutover'!$C$6:$C$63,MATCH(55,'Gantt Cutover'!$BA$6:$BA$63,0)),"") | F101: =IFERROR(INDEX('Gantt Cutover'!$G$6:$G$63,MATCH(55,'Gantt Cutover'!$BA$6:$BA$63,0)),"") | G101: =IFERROR(INDEX('Equipo y Calendario'!$B$5:$B$24,MATCH(F101,'Equipo y Calendario'!$A$5:$A$24,0)),"") | H101: =IFERROR(INDEX('Gantt Cutover'!$H$6:$H$63,MATCH(55,'Gantt Cutover'!$BA$6:$BA$63,0)),"") | I101: =IFERROR(INDEX('Gantt Cutover'!$I$6:$I$63,MATCH(55,'Gantt Cutover'!$BA$6:$BA$63,0)),"") | J101: =IFERROR(INDEX('Gantt Cutover'!$J$6:$J$63,MATCH(55,'Gantt Cutover'!$BA$6:$BA$63,0)),"") | K101: =IFERROR(INDEX('Gantt Cutover'!$K$6:$K$63,MATCH(55,'Gantt Cutover'!$BA$6:$BA$63,0)),"") | L101: =IFERROR(INDEX('Gantt Cutover'!$M$6:$M$63,MATCH(55,'Gantt Cutover'!$BA$6:$BA$63,0)),"")
B102: 56 | C102: =IFERROR(INDEX('Gantt Cutover'!$A$6:$A$63,MATCH(56,'Gantt Cutover'!$BA$6:$BA$63,0)),"") | D102: =IFERROR(INDEX('Gantt Cutover'!$B$6:$B$63,MATCH(56,'Gantt Cutover'!$BA$6:$BA$63,0)),"") | E102: =IFERROR(INDEX('Gantt Cutover'!$C$6:$C$63,MATCH(56,'Gantt Cutover'!$BA$6:$BA$63,0)),"") | F102: =IFERROR(INDEX('Gantt Cutover'!$G$6:$G$63,MATCH(56,'Gantt Cutover'!$BA$6:$BA$63,0)),"") | G102: =IFERROR(INDEX('Equipo y Calendario'!$B$5:$B$24,MATCH(F102,'Equipo y Calendario'!$A$5:$A$24,0)),"") | H102: =IFERROR(INDEX('Gantt Cutover'!$H$6:$H$63,MATCH(56,'Gantt Cutover'!$BA$6:$BA$63,0)),"") | I102: =IFERROR(INDEX('Gantt Cutover'!$I$6:$I$63,MATCH(56,'Gantt Cutover'!$BA$6:$BA$63,0)),"") | J102: =IFERROR(INDEX('Gantt Cutover'!$J$6:$J$63,MATCH(56,'Gantt Cutover'!$BA$6:$BA$63,0)),"") | K102: =IFERROR(INDEX('Gantt Cutover'!$K$6:$K$63,MATCH(56,'Gantt Cutover'!$BA$6:$BA$63,0)),"") | L102: =IFERROR(INDEX('Gantt Cutover'!$M$6:$M$63,MATCH(56,'Gantt Cutover'!$BA$6:$BA$63,0)),"")
B103: 57 | C103: =IFERROR(INDEX('Gantt Cutover'!$A$6:$A$63,MATCH(57,'Gantt Cutover'!$BA$6:$BA$63,0)),"") | D103: =IFERROR(INDEX('Gantt Cutover'!$B$6:$B$63,MATCH(57,'Gantt Cutover'!$BA$6:$BA$63,0)),"") | E103: =IFERROR(INDEX('Gantt Cutover'!$C$6:$C$63,MATCH(57,'Gantt Cutover'!$BA$6:$BA$63,0)),"") | F103: =IFERROR(INDEX('Gantt Cutover'!$G$6:$G$63,MATCH(57,'Gantt Cutover'!$BA$6:$BA$63,0)),"") | G103: =IFERROR(INDEX('Equipo y Calendario'!$B$5:$B$24,MATCH(F103,'Equipo y Calendario'!$A$5:$A$24,0)),"") | H103: =IFERROR(INDEX('Gantt Cutover'!$H$6:$H$63,MATCH(57,'Gantt Cutover'!$BA$6:$BA$63,0)),"") | I103: =IFERROR(INDEX('Gantt Cutover'!$I$6:$I$63,MATCH(57,'Gantt Cutover'!$BA$6:$BA$63,0)),"") | J103: =IFERROR(INDEX('Gantt Cutover'!$J$6:$J$63,MATCH(57,'Gantt Cutover'!$BA$6:$BA$63,0)),"") | K103: =IFERROR(INDEX('Gantt Cutover'!$K$6:$K$63,MATCH(57,'Gantt Cutover'!$BA$6:$BA$63,0)),"") | L103: =IFERROR(INDEX('Gantt Cutover'!$M$6:$M$63,MATCH(57,'Gantt Cutover'!$BA$6:$BA$63,0)),"")
B104: 58 | C104: =IFERROR(INDEX('Gantt Cutover'!$A$6:$A$63,MATCH(58,'Gantt Cutover'!$BA$6:$BA$63,0)),"") | D104: =IFERROR(INDEX('Gantt Cutover'!$B$6:$B$63,MATCH(58,'Gantt Cutover'!$BA$6:$BA$63,0)),"") | E104: =IFERROR(INDEX('Gantt Cutover'!$C$6:$C$63,MATCH(58,'Gantt Cutover'!$BA$6:$BA$63,0)),"") | F104: =IFERROR(INDEX('Gantt Cutover'!$G$6:$G$63,MATCH(58,'Gantt Cutover'!$BA$6:$BA$63,0)),"") | G104: =IFERROR(INDEX('Equipo y Calendario'!$B$5:$B$24,MATCH(F104,'Equipo y Calendario'!$A$5:$A$24,0)),"") | H104: =IFERROR(INDEX('Gantt Cutover'!$H$6:$H$63,MATCH(58,'Gantt Cutover'!$BA$6:$BA$63,0)),"") | I104: =IFERROR(INDEX('Gantt Cutover'!$I$6:$I$63,MATCH(58,'Gantt Cutover'!$BA$6:$BA$63,0)),"") | J104: =IFERROR(INDEX('Gantt Cutover'!$J$6:$J$63,MATCH(58,'Gantt Cutover'!$BA$6:$BA$63,0)),"") | K104: =IFERROR(INDEX('Gantt Cutover'!$K$6:$K$63,MATCH(58,'Gantt Cutover'!$BA$6:$BA$63,0)),"") | L104: =IFERROR(INDEX('Gantt Cutover'!$M$6:$M$63,MATCH(58,'Gantt Cutover'!$BA$6:$BA$63,0)),"")
...

Sheet Equipo y Calendario
A1: Equipo de cutover y calendario
A2: Roles usados en Responsable y Participantes. Los nombres (amarillo) se muestran en la hoja Hoy.
A4: Rol | B4: Nombre | C4: Organización | D4: En Bogotá
A5: Gerencia Colombia | B5: Juliana Gomez | C5: Portland Colombia | D5: Local
A6: Contabilidad Colombia | B6: Camila Castiblanco | C6: Portland Colombia | D6: Local
A7: Tesorería Colombia | B7: Felipe Fernadez | C7: Portland Colombia | D7: Local
A8: Comercial / Facturación Colombia | B8: Diana Trujillo / Santiago Saavedra | C8: Portland Colombia | D8: Local
A9: Logística / Bodega Colombia | B9: Andrés García | C9: Portland Colombia | D9: Local
A10: Gerente de Proyecto | B10: Germán Faundes | C10: Portland | D10: 02 al 12-11
A11: Gerente de Contabilidad Regional | B11: Daniela Correa | C11: Portland | D11: 02 al 12-11
A12: TI Portland FICO | B12: Oscar Sella | C12: Portland | D12: 02 al 12-11
A13: TI Portland MM | B13: Leandro Jara | C13: Portland | D13: No
A14: TI Portland SD y FFEE | B14: Héctor Correa | C14: Portland | D14: No
A15: PMO Portland | B15: Gabriel Salinas | C15: Portland | D15: 02 al 12-11
... A24: TI Portland Perú | B24: Alonso Cuba | C24: Portland TI Perú | D24: 15 al 20-11
A27: Calendario
A28: Go-Live | B28: 46335
A29: Inicio del viaje del equipo | B29: 46328
A30: Fin del viaje del equipo | B30: 46338
A32: Feriados en el período (Colombia)
A33: Día de Todos los Santos (trasladado) | B33: 46328
A40: Fuente de los feriados: calendario oficial de festivos de Colombia 2026.
